Workbook

Sheet All DP
A1: Agent | B1: Kode DP | C1: nama dp | D1: status
A2: AGENT10 | B2: BLM14 | C2: WAY_TUBA | D2: Masih
A3: AGENT10 | B3: SKD15 | C3: PASIR_SAKTI | D3: Masih
A4: AGENT10 | B4: KOG20 | C4: PEKON_WONOSOBO | D4: Masih
A5: AGENT10 | B5: KOG15 | C5: PULAU_PANGGUNG | D5: Masih
A6: AGENT10 | B6: GTT07 | C6: WAY_LIMA | D6: Masih
A7: AGENT10 | B7: LWA02A | C7: KEMBAHANG | D7: Masih
A8: AGENT10 | B8: KBB14 | C8: BERNAH | D8: Masih
A9: AGENT10 | B9: KBB05 | C9: ABUNG_SEMULI | D9: Masih
A10: AGENT10 | B10: KBB21 | C10: NEGARA_RATU | D10: Masih
A11: AGENT10 | B11: BKH02C | C11: SIDOASRI | D11: Masih
A12: AGENT12 | B12: BAL01D | C12: GADING_KELAPA_DUA | D12: Tidak
... A3508: AGENT40 | B3508: JKT21U | C3508: DC_GANDARIA | D3508: Masih

Sheet raw Base
B1: Tanggal upload fin | C1: Kode Agent 代理区代码 | D1: Nama Drop Point 网点名称 | E1: Kode Drop Point 网点代码 | F1: Video Briefing 班前例会视频 | G1: Summary Briefing 会议要点总结 | H1: Kategori Materi | I1: Tanggal Upload 上传日期 | J1: Sprinter Ikut breifing hari ini | K1: Total Sprinter | L1: created by | M1: status | N1: Last Modified Date 2 | O1: feedback DP | P1: total DP
B2: =INT(I2) -> 46266 | C2: AGENT23 | D2: MASOHI | E2: MSI01 | F2: 2026-09-01 06.34.05_.mp4 | G2: POD VALID DAN MARKETING | H2: Marketing | I2: 46266.194 | J2: 8 | K2: 16 | L2: Amina Abd. Khair | N2: 46266.194 | O2: Masih | P2: 175
B3: =INT(I3) -> 46266 | C3: AGENT23 | D3: WAEAPO | E3: NAM02 | F3: 1ac716247d7932dbfa26a61de418409e.jpg | G3: BRIFING DP NAM02 1 AGUSTUS 2026 - RITASE - PAYCOOLS - E POD - POD RETUR VALID - ARBITRASE - LONG TAIL - TIKET PLATFROM - PARCEL CARE - DENDA HQ | H3: other | I3: 46266.196 | J3: 5 | K3: 10 | L3: Marselinus Tehe | N3: 46266.196 | O3: Masih | P3: 175
B4: =INT(I4) -> 46266 | C4: AGENT23 | D4: GEMBA | E4: PRU02 | F4: BREFING.jpeg | G4: BREAFING GEMBA TGL 01 September 2026 1. PUSH TTD KEJAR RITASE > 90% 2. PEMBAYARAN PAYCOOLS 3. EPOD HARUS VALID 92% 4. KODE KETIGA 5. RETUR DGN POD VALID 6. KEBERSIHAN DP 7. PENGGUNAAN KODE QR DP & SPRINTER 8. SOP MENGANTAR 9.PARCEL CARE | H4: Marketing | I4: 46266.213 | J4: 3 | K4: 3 | L4: Dewi Sriyanti Seipalla | N4: 46266.213 | O4: Masih | P4: 175
B5: =INT(I5) -> 46266 | C5: AGENT23 | D5: LABUHA | E5: LAH01 | F5: 2026-09-01 06.46.11__(Judul-Absensi).mp4 | G5: 1. Absensi sebelum jam 6:30 2. Delivery sebelum jam 12 3. Tidak boleh tahan paket diatas 3 hari Jaga kebersihan dp 4. Terapkan 3S | H5: other | I5: 46266.227 | J5: 21 | K5: 25 | L5: Rifaldi Sanaba | N5: 46266.227 | O5: Masih | P5: 175
B6: =INT(I6) -> 46266 | C6: AGENT23 | D6: GALALA | E6: AMQ07 | F6: 2026-09-01 07.20.44_Jalan Jenderal Sudirman_(Pemeriksa-DP AMQ07_GALALA).jpg | G6: BRIEFING PAGI AMQ07 GALALA 1 SEPTEMBER 2026 ABSEN 6.30 PUSH TTD JAM 12 LONGTAIL PARCEL CARE POD RETUR DAN PU VALID PUSH PAYCOOLS | H6: other | I6: 46266.229 | J6: 23 | K6: 24 | L6: Zulfikry Ramadhan Ismail | N6: 46266.229 | O6: Masih | P6: 175
B7: =INT(I7) -> 46266 | C7: AGENT23 | D7: BOBONG | E7: BOB01 | F7: 20260901_70848AMByGPSMapCamera.jpg | G7: *GROOMING & BRIEFING BOBONG* Pembahasan. ->Push TTD ->TTD REAL TIME ->Di perhatikan paket yg stuck. ->Jujur dalam berkerja. ->Disiplin dgn waktu. ->Penambahan SDM | H7: other | I7: 46266.234 | J7: 1 | K7: 1 | L7: Farisal Irawan | N7: 46266.234 | O7: Masih | P7: 175
B8: =INT(I8) -> 46266 | C8: AGENT23 | D8: PAGUYAMAN | E8: LBO02 | F8: 2026-09-01 06.32.23_.mp4 | G8: PUSH 6.30 PUSH QR SPRINTER PUSH TTD/RITASE | H8: Marketing | I8: 46266.234 | J8: 7 | K8: 8 | L8: Alvian Ahmad | N8: 46266.234 | O8: Masih | P8: 175
B9: =INT(I9) -> 46266 | C9: AGENT23 | D9: DONGGALA | E9: DON01 | F9: 2026-09-01 06.33.10_Jalan Pettalolo_(Judul-DP DON01).jpg | G9: ABSENSI PUSH TTD PAYCOOLS POD VALID LONGTAIL QR SPRINTER | H9: Marketing | I9: 46266.235 | J9: 10 | K9: 17 | L9: Zainuddin . | N9: 46266.236 | O9: Masih | P9: 175
B10: =INT(I10) -> 46266 | C10: AGENT23 | D10: KEBUN_CENGKEH | E10: AMQ02 | F10: 20260901-053848.jpg | G10: 1. QUIZ APP SPRINTER 2. PUSH ABSENSI 06.30 3. PICK-UP 4. SIMPANG GUDANG POD VALID 5. KELUAR 07.30 DAN TTD JAM 12.00 6. PAYCOOLS & GOPAY 7. LONGTAIL | H10: other | I10: 46266.239 | J10: 4 | K10: 20 | L10: Fahbi Safitri | N10: 46266.239 | O10: Masih | P10: 175
B11: =INT(I11) -> 46266 | C11: AGENT23 | D11: FALAJAWA2 | E11: TTE05 | F11: WhatsApp Video 2026-09-01 at 07.46.25.mp4 | G11: PUSH KPI | H11: other | I11: 46266.244 | J11: 2 | K11: 3 | L11: Fadila Samsudin | N11: 46266.244 | O11: Masih | P11: 175
B12: =INT(I12) -> 46266 | C12: AGENT23 | D12: SOJOL | E12: DON13 | F12: IMG-20260901-WA0003(1).jpg | G12: Awb HV,pod, simpan gudang, ujian sprinter | H12: Marketing | I12: 46266.244 | J12: 5 | K12: 5 | L12: Memet . | N12: 46266.244 | O12: Masih | P12: 175
B13: =INT(I13) -> 46266 | C13: AGENT21 | D13: KETEWEL | E13: GIA01B | F13: 20260901_64122AMByGPSMapCamera.mp4 | G13: brifing tentang TTD paksa T7 keatas | H13: other | I13: 46266.245 | J13: 19 | K13: 26 | L13: Rifqi Al'Afif Ramadhan | N13: 46266.245 | O13: Masih | P13: 176
... B17: =INT(I17) -> 46266 | C17: AGENT23 | D17: TUAL | E17: UAL01 | F17: 2026-09-01 07.14.34_Jalan Doktor Leimena_(Judul-Visit)_(Catatan-Kunjungan Harian).jpg | G17: Push TTD sebelum jam 12 Push paycools Push satu sprinter satu pickupan | H17: Marketing | I17: 46266.252 | J17: 6 | K17: 8 | L17: Kufra Ahmad Toha Rery | N17: 46266.252 | O17: Masih | P17: 175
B18: =INT(I18) -> 46266 | C18: AGENT22 | D18: PEKKABATA | E18: PRR02 | F18: VID-20260901-WA0051.mp4 | G18: Absensi Quis app Paket longtail | H18: other | I18: 46266.252 | J18: 11 | K18: 16 | L18: Rusli At | N18: 46266.253 | P18: 148
B19: =INT(I19) -> 46266 | C19: AGENT23 | D19: SOJOL | E19: DON13 | F19: 9b1b0ccd-8eab-4dce-b25b-ebcffcd2fc57.jpeg | G19: ABSENSI QUIS SPRINTER LONGTAIL POD VALID TTD SEBELUM JAM 12 | H19: other | I19: 46266.254 | J19: 5 | K19: 5 | L19: Pengguna Tamu 98700 | N19: 46266.254 | O19: Masih | P19: 175
B20: =INT(I20) -> 46266 | C20: AGENT23 | D20: BONE_PANTAI | E20: SUW02 | F20: 2026-09-01 06.46.43_.jpg | G20: ABESENSI 06.30, TTD SEBELUM JAM 12 | H20: other | I20: 46266.254 | J20: 5 | K20: 9 | L20: Arya Yoga Pangestu | N20: 46266.254 | O20: Masih | P20: 175
B21: =INT(I21) -> 46266 | C21: AGENT23 | D21: MABA | E21: MAB01 | F21: 2026-09-01 07.42.55_Maba Sangaji.JPEG | G21: QR SPRINTER (mkt) ptmp, stuck (NM) | H21: Marketing | I21: 46266.257 | J21: 10 | K21: 6 | L21: Hardi . | N21: 46266.257 | O21: Masih | P21: 175
B22: =INT(I22) -> 46266 | C22: AGENT23 | D22: AMPIBABO | E22: PII04 | F22: BRIFING PAGI.jpg | G22: PUSH PAKET LONGTAIL ABSENSI TIKTOK REVERSE | H22: other | I22: 46266.257 | J22: 4 | K22: 9 | L22: Nurhaliza . | N22: 46266.257 | O22: Masih | P22: 175
B23: =INT(I23) -> 46266 | C23: AGENT23 | D23: DIMEMBE | E23: AID02A | F23: 2026-09-01_06.51.38_Jalan_Sukur_-_Likupang_(Company-J&T_Express)[1].jpg | G23: END STATUS, POD | H23: other | I23: 46266.257 | J23: 4 | K23: 9 | L23: Febrika Falensia Effendie | N23: 46266.257 | P23: 175
B24: =INT(I24) -> 46266 | C24: AGENT22 | D24: BENU_BENUA | E24: KDI11 | F24: 2026-09-01 07.03.32_Jnt Benu Benua.jpeg | G24: memaksimalkan paket di dp mengedukasikan untuk datang lebih awal agar keluar delivery lebih awal juga hati2 saat berkendara mengedukasikan uktuk menggunakan pod valid pada saat meretur dan gagal pick up paket | H24: other | I24: 46266.257 | J24: 15 | K24: 19 | L24: Fitra Chalik | N24: 46266.257 | P24: 148
B25: =INT(I25) -> 46266 | C25: AGENT23 | D25: TENTENA | E25: PSJ02 | F25: IMG_4724.JPEG | G25: 1. PARCEL CARE 2. KEBERSIHAN DP 3. PUSH TTD SEBELUM JAM 12 4. POD VALID 5. POD RETUR 6. PELAYANAN DP 7. MAKSIMALKAN PAKET 8. PICKUP QR SPRINTER 9. ABSENSI 6.30 | H25: Marketing | I25: 46266.257 | J25: 11 | K25: 11 | L25: Stefi Landika | N25: 46266.258 | O25: Masih | P25: 175
B26: =INT(I26) -> 46266 | C26: AGENT28 | D26: MERAUKE | E26: MKQ01 | F26: TimePhoto_20260901_075908.jpg | G26: paket lontail dan paket priofitas | H26: other | I26: 46266.258 | J26: 19 | K26: 3 | L26: Pengguna Tamu 46219 | N26: 46266.258 | P26: 13
B27: =INT(I27) -> 46266 | C27: AGENT22 | D27: NGAPA | E27: LAS02 | F27: hasil_LAS02_1788217968721.mp4 | G27: pod, absensi, delivery jam 07.30 | H27: other | I27: 46266.261 | J27: 13 | K27: 15 | L27: Pengguna Tamu 90586 | N27: 46266.261 | P27: 148
B28: =INT(I28) -> 46266 | C28: AGENT23 | D28: MADIDIR | E28: BIT03 | F28: WhatsApp Image 2026-09-01 at 07.04.35.jpeg,WhatsApp Video 2026-09-01 at 07.06.30.mp4 | G28: LONG TAIL TTD JAM 12 ABSENSI KEBERSIHAN | H28: other | I28: 46266.261 | J28: 23 | K28: 23 | L28: Anglie Meihua Lim | N28: 46266.261 | O28: Masih | P28: 175
B29: =INT(I29) -> 46266 | C29: AGENT21 | D29: SEMINYAK_1 | E29: MGW04C | F29: b1ddf51b-73cb-4ea1-a651-99ab727fd3e8.mp4 | G29: Longtail | H29: other | I29: 46266.261 | J29: 40 | K29: 50 | L29: Diana Ursula Wati | N29: 46266.261 | O29: Masih | P29: 176
B30: =INT(I30) -> 46266 | C30: AGENT22 | D30: TINANGGEA | E30: WAG21 | F30: 2026-09-01 07.13.58_Jalan Poros Lapulu_(TINANGGEA).jpg | G30: pod Ttd absen | H30: other | I30: 46266.261 | J30: 18 | K30: 18 | L30: Sutarno . | N30: 46266.261 | P30: 148
B31: =INT(I31) -> 46266 | C31: AGENT23 | D31: KAKASKASEN | E31: TMH02 | F31: img_v3_02154_e328b5c8-c7cd-4eec-8fc6-d2f54ec1e2hu.jpg | G31: POD PARCELCARE QR SPRINTER/DP PAYCOOLS LONGTAIL KEBERSIHAN | H31: Marketing | I31: 46266.262 | J31: 13 | K31: 20 | L31: Anggreyni Marini Marentek | N31: 46266.262 | O31: Masih | P31: 175
B32: =INT(I32) -> 46266 | C32: AGENT23 | D32: SOFIFI | E32: TID02 | F32: VID-20260901-WA0006.mp4 | G32: PAKET 3 HARI STORAN | H32: other | I32: 46266.264 | J32: 12 | K32: 20 | L32: Karmila Gorotomole | N32: 46266.264 | O32: Masih | P32: 175
B33: =INT(I33) -> 46266 | C33: AGENT22 | D33: BALANIPA | E33: PWX03 | F33: IMG-20260901-WA0021.jpg | G33: Target pick up dan pod retur | H33: other | I33: 46266.264 | J33: 18 | K33: 28 | L33: Wahyu . | N33: 46266.264 | P33: 148
B34: =INT(I34) -> 46266 | C34: AGENT18 | D34: NGAGLIK | E34: SLM03 | F34: aa0c843b-4be0-42dd-9224-5dafa88ce718.JPEG | G34: ttd jam 12 | H34: other | I34: 46266.266 | J34: 7 | K34: 23 | L34: Soeko Wicaksono Novianto | N34: 46266.266 | O34: Masih | P34: 129
B35: =INT(I35) -> 46266 | C35: AGENT21 | D35: NEGARA_1 | E35: NRG01A | F35: 20260901_71748AMByGPSMapCamera.mp4 | G35: mengenai paket yang sudah 3 hari dan simpan gudang atau paket bermasalah | H35: other | I35: 46266.266 | J35: 30 | K35: 45 | L35: Pengguna Tamu 95133 | N35: 46266.266 | O35: Masih | P35: 176
B36: =INT(I36) -> 46266 | C36: AGENT27 | D36: SAMARINDA | E36: SRI01 | F36: 2026-09-01 07.23.24_Citraland City.jpeg | G36: ttd sblm jm12 | H36: other | I36: 46266.267 | J36: 4 | K36: 21 | L36: Pengguna Tamu 68821 | N36: 46266.267 | P36: 165
B37: =INT(I37) -> 46266 | C37: AGENT22 | D37: MAKASSAR | E37: UPG01 | F37: 2026-09-01 7.12.33 AM_Jalan Veteran Selatan No. 64.mp4 | G37: POD Scan Bermasalah | H37: other | I37: 46266.268 | J37: 7 | K37: 31 | L37: Guest User 21841 | N37: 46266.268 | P37: 148
B38: =INT(I38) -> 46266 | C38: AGENT23 | D38: TOMPASO_BARU | E38: AMR16 | F38: 2026-09-01 07.09.58_.jpg | G38: ABSENSI SLA TTD SSEBELUM JAM 12 PEYCOLS | H38: other | I38: 46266.269 | J38: 5 | K38: 11 | L38: Cinta Celsi Tarumingkeng | N38: 46266.269 | O38: Masih | P38: 175
B39: =INT(I39) -> 46266 | C39: AGENT21 | D39: JEMBRANA | E39: NRG03A | F39: WhatsApp Video 2026-09-01 at 06.25.40.mp4 | G39: SHARING SPRINTER BINTANG 5 PENILAIAN CUSTOMER DI APP CUSTOMER | H39: Marketing | I39: 46266.269 | J39: 18 | K39: 19 | L39: Eni Maryana | N39: 46266.269 | O39: Masih | P39: 176
B40: =INT(I40) -> 46266 | C40: AGENT22 | D40: WUNDULAKO | E40: KOL05 | F40: 2026-09-01 07.16.56_.mp4 | G40: memaksimalkanp | H40: other | I40: 46266.271 | J40: 8 | K40: 9 | L40: Irpandi . | N40: 46266.271 | P40: 148
B41: =INT(I41) -> 46266 | C41: AGENT22 | D41: KADIA | E41: KDI02 | F41: WhatsApp Image 2026-09-01 at 06.29.32.jpeg | G41: 1awb perhari | H41: Marketing | I41: 46266.272 | J41: 23 | K41: 26 | L41: Andi Fachri Ramadhan | N41: 46266.273 | P41: 148
B42: =INT(I42) -> 46266 | C42: AGENT19 | D42: DC_PORONG | E42: SDA24 | F42: 2026-09-01 06.29.42_No.447, Jalan Bhayangkari.jpg,2026-09-01 06.29.45_No.447, Jalan Bhayangkari.mp4 | G42: SDA JAM 12 TARGET LEGULER KEDATANGAN | H42: other | I42: 46266.273 | J42: 50 | K42: 56 | L42: fandi rakhmad_SDA24 | N42: 46266.273 | O42: Masih | P42: 365
B43: =INT(I43) -> 46266 | C43: AGENT21 | D43: NUSA_PENIDA | E43: KKL03 | F43: 1 September.mp4 | G43: Briefing pagi : Menyampaikan materi briefing sesuai ketentuan HQ yang dibagi menjadi 3 section. | H43: other | I43: 46266.275 | J43: 26 | K43: 27 | L43: I Dewa Made Dwipayana | N43: 46266.275 | O43: Masih | P43: 176
B44: =INT(I44) -> 46266 | C44: AGENT40 | D44: CP_PULO_GADUNG | E44: JKT57G | F44: image.png | G44: brifing pagi cp pulo gadung absen 6.30 keluar gudang 7.30 ttd jam 12.00 dan all ritase longtail, paket stuck penanganan paket DG qr sprinter kejar dari awal bulan dan juga prospek pelanggan vip evaluasi pencapaian agustus | H44: Marketing | I44: 46266.276 | J44: 147 | K44: 155 | L44: Arman Suryadi | N44: 46266.276 | P44: 73
B45: =INT(I45) -> 46266 | C45: AGENT40 | D45: CP_TANJUNG_DUREN_2 | E45: JKT39O | F45: 2026-09-01 06.29.58_No. 118, Jalan Daan Mogot.jpg,2026-09-01 06.30.01_No. 118, Jalan Daan Mogot.mp4 | G45: .Brifing pagi cp tanjung duren raya .masuk 06.30 pagi .keluar gudang 07.30 .TTD JAM 12 .TTD ALL RITASE . Sosialisasi paket barang barang DG . Kebersihan lingkungan kerja .pod retur valid | H45: other | I45: 46266.277 | J45: 79 | K45: 88 | L45: Retno Pratama | N45: 46266.277 | O45: Masih | P45: 73
B46: =INT(I46) -> 46266 | C46: AGENT23 | D46: BOROKO | E46: BRK01 | F46: IMG_1287.jpeg | G46: ABSENSI LONGTAIL RITASE QR SPRINTER | H46: Marketing | I46: 46266.277 | J46: 10 | K46: 6 | L46: Pengguna Tamu 74791 | N46: 46266.277 | O46: Masih | P46: 175
B47: =INT(I47) -> 46266 | C47: AGENT40 | D47: TEBET | E47: JKT25 | F47: image.png | G47: - ABSENSI KEHADIRAN - QR SPRINTER - PICKUP REGULER - RIMENDER PAKET DG/DILARANG KIRIM - POD VALID - TTD JAM 12&ALLRITASE - KELUAR GUDANG 07.30 | H47: Marketing | I47: 46266.278 | J47: 92 | K47: 133 | L47: Muhamad Faisal | N47: 46266.278 | O47: Masih | P47: 73
B48: =INT(I48) -> 46266 | C48: AGENT23 | D48: DAMPAL | E48: TLI04 | F48: WhatsApp Video 2026-09-01 at 06.10.25.mp4,WhatsApp Image 2026-09-01 at 06.10.22.jpeg | G48: tli04 dampal tgl 1/9/2026 penggunaan paycools ttd realtime pod valid longtail | H48: other | I48: 46266.278 | J48: 7 | K48: 12 | L48: Nurul Istiqamah | N48: 46266.278 | O48: Masih | P48: 175
B49: =INT(I49) -> 46266 | C49: AGENT23 | D49: KALAWAT | E49: AID02 | F49: WhatsApp Video 2026-09-01 at 06.37.51.mp4 | G49: MAKSIMALKAN TTD SEBLUM JAM 12 | H49: other | I49: 46266.279 | J49: 15 | K49: 15 | L49: Ariandani Musbar Norcahayanto | N49: 46266.279 | O49: Masih | P49: 175
B50: =INT(I50) -> 46266 | C50: AGENT40 | D50: MERUYA_UTARA | E50: JKT02Q | F50: TimePhoto_20260901_063457.jpg | G50: Briefing DC Meruya Utara - Keluar gudang 07.30 - Absensi 06.30 - TTD 12.00 - TTD all ritase - QR Sprinter - CODFD - Dangerous Goods - POD Valid | H50: Marketing | I50: 46266.279 | J50: 51 | K50: 60 | L50: Raka Fahrizki | N50: 46266.279 | O50: Tidak | P50: 73
B51: =INT(I51) -> 46266 | C51: AGENT40 | D51: KAMAL_MUARA | E51: JKT08L | F51: 20260901-064225.jpg | G51: Brifing pagi DC kamal muara - Ketepatan absensi 06:30 target 90% - Keluar gudang 07:30 - TTD real-time sebelum jam 12:00 90% ( Balik rit sebelum jam 12, simgud paket bermasalah dengan POD Valid) - Pickup QR Sprinter 1 Hari 1 Awb - Sosialisasi mengenai barang dilarang kirim | H51: Marketing | I51: 46266.28 | J51: 37 | K51: 37 | L51: Fikri Gilang P JKT-08L | N51: 46266.28 | O51: Masih | P51: 73
B52: =INT(I52) -> 46266 | C52: AGENT40 | D52: KEPULAUAN_SERIBU | E52: JKT08C | F52: 20260901-064225.jpg | G52: - Ketepatan absensi 06:30 target 90% - Keluar gudang 07:30 - TTD real-time sebelum jam 12:00 90% ( Balik rit sebelum jam 12, simgud paket bermasalah dengan POD Valid) - Pickup QR Sprinter 1 Hari 1 Awb - Sosialisasi mengenai barang dilarang kirim | H52: Marketing | I52: 46266.28 | J52: 31 | K52: 31 | L52: Fikri Gilang P JKT-08L | N52: 46266.28 | O52: Masih | P52: 73
B53: =INT(I53) -> 46266 | C53: AGENT21 | D53: ENDE | E53: ENE01 | F53: TimeVideo_20260901_073618.mp4 | G53: Push TTD dan target dp | H53: other | I53: 46266.28 | J53: 13 | K53: 19 | L53: Nur Azizah | N53: 46266.28 | O53: Masih | P53: 176
B54: =INT(I54) -> 46266 | C54: AGENT22 | D54: WANGGODO | E54: WAG01 | F54: WhatsApp Video 2026-09-01 at 06.49.10.mp4 | G54: TT RIVERS & TPTW | H54: other | I54: 46266.281 | J54: 20 | K54: 20 | L54: Pengguna Tamu 75295 | N54: 46266.281 | P54: 148
B55: =INT(I55) -> 46266 | C55: AGENT40 | D55: DC_KELAPA_GADING | E55: JKT07U | F55: 20260901-064409.jpg | G55: Briefing Pagi DC Kelapa gading - Absensi 06.30 - Scan Deliv 07.30 - TTD Jam 12.00 - TTD All Ritase - POD Valid - Longtail - Penggunaan Pembayaran Online - Parcel & RSAT - QR Sprinter - Quiz App Sprinter - Prospek pelanggan - paket DG | H55: Marketing | I55: 46266.281 | J55: 77 | K55: 105 | L55: Ikhsan Alif Al Mi' Roj | N55: 46266.281 | O55: Masih | P55: 73
B56: =INT(I56) -> 46266 | C56: AGENT40 | D56: DC_KEMAYORAN | E56: JKT15K | F56: image.png | G56: Briefing pagi DC kemayoran Absensi 06.30 Keluar Gudang 07.30 TTD 12.00 TTD ALL Ritase Pemaksimalan Area Office yang tutup Parcel Care QR Sprinter 1 AWB 1 Sprinter Paket Dangerous Goods, paket-paket berbahaya dilarang kirim, Paket Cairan harus dengan packing yang rapat dan baik Penambahan Man Power untuk Persiapan Peak Season 6S POD Retur Valid Penekanan serta penurunan CODFD | H56: Marketing | I56: 46266.281 | J56: 50 | K56: 128 | L56: M Satiri | N56: 46266.281 | O56: Masih | P56: 73
B57: =INT(I57) -> 46266 | C57: AGENT40 | D57: ROROTAN | E57: JKT10B | F57: WhatsApp Image 2026-09-01 at 06.44.24.jpeg | G57: . Absensi 06:30 . keluar DC 07:30 . TTD JAM 12 . TTD all ritase . Pickup reguler . QR sprinter . Quis app sprinter . Menghindari paket2 dilarang kirim DG | H57: Marketing | I57: 46266.283 | J57: 65 | K57: 75 | L57: Tadin Saputra | N57: 46266.283 | O57: Masih | P57: 73
B58: =INT(I58) -> 46266 | C58: AGENT28 | D58: NABIRE | E58: NBX01 | F58: 1495b594-2966-479b-b9d9-9cdee5952f71.jpg | G58: push paket,paket complaint,parcel care,push ttd | H58: other | I58: 46266.283 | J58: 3 | K58: 5 | L58: Hayu Hutami | N58: 46266.283 | P58: 13
B59: =INT(I59) -> 46266 | C59: AGENT40 | D59: DC_PALMERAH | E59: JKT03E | F59: VID-20260901-WA0031.mp4 | G59: BRIEFING PAGI DC PALMERAH •KELUAR GUDANG 07:30 •QR SPRINTER •POD RETUR •TTD ALLRITASE •TTD JAM 12:00 •EVALUASI PERFORMANCE BULAN AGUSTUS •MEMINUMALISIR PAKET SIMPAN GUDANG | H59: Marketing | I59: 46266.283 | J59: 63 | K59: 138 | L59: Govur | N59: 46266.283 | O59: Masih | P59: 73
B60: =INT(I60) -> 46266 | C60: AGENT22 | D60: WUNDULAKO | E60: KOL05 | F60: 2026-09-01 07.16.56_.mp4 | G60: memaksimalkan paket | H60: other | I60: 46266.283 | J60: 8 | K60: 9 | L60: Irpandi . | N60: 46266.283 | P60: 148
B61: =INT(I61) -> 46266 | C61: AGENT21 | D61: APU05A | E61: APU05A | F61: VID-20260528-WA0002.mp4 | G61: Asen, paket stuck, setoran, ttd | H61: other | I61: 46266.284 | J61: 25 | K61: 27 | L61: I Wayan Widia | N61: 46266.284 | O61: Masih | P61: 176
B62: =INT(I62) -> 46266 | C62: AGENT21 | D62: LARANTUKA | E62: LKA01 | F62: 20260721_80234AM_ByGPSVideoCamera.mp4 | G62: Absensi, pus TTD, retur tepat waktu, | H62: other | I62: 46266.284 | J62: 15 | K62: 20 | L62: Yulianus Hedung Hajon | N62: 46266.284 | O62: Masih | P62: 176
B63: =INT(I63) -> 46266 | C63: AGENT23 | D63: MASAMA | E63: BAG06 | F63: 2026-09-01 07.43.48_Jalan Trans Luwuk.jpg | G63: RITASE LONGTAIL TTD SEBELUM JAM 12 ABSENSI | H63: other | I63: 46266.284 | J63: 5 | K63: 9 | L63: Susi Susanti | N63: 46266.284 | O63: Masih | P63: 175
B64: =INT(I64) -> 46266 | C64: AGENT22 | D64: SUNGGUMINASA | E64: SGM01 | F64: 2026-09-01 07.35.41_No.47, Jalan Andi Tonro.jpg | G64: pencarian new customer | H64: Marketing | I64: 46266.285 | J64: 26 | K64: 26 | L64: Dedhy Amiruddin | N64: 46266.285 | P64: 148
B65: =INT(I65) -> 46266 | C65: AGENT22 | D65: SUNU | E65: UPG09 | F65: IMG-20260901-WA0003.jpg | G65: pod scan bermasalah valid | H65: other | I65: 46266.286 | J65: 9 | K65: 23 | L65: Firwansyah M | N65: 46266.286 | P65: 148
B66: =INT(I66) -> 46266 | C66: AGENT40 | D66: CP_KOJA_1 | E66: JKT63B | F66: 999.jpg | G66: Selamat pagi, berikut laporan briefing pagi CP KOJA : 1. Absensi tepat waktu jam 06:30 pagi target 92% 2. Keluar gudang tepat waktu jam 07:30 pagi target 95% 3. TTD Sebelum jam 12:00 siang target 90% 4. TTD All ritase harian dan bulanan target 97% 5. Reminder pod retur valid (bukti chat dan foto) 6. Sosialisasi mengenai barang yang di larang kirim (DG) Terima kasih🙏 | H66: other | I66: 46266.287 | J66: 30 | K66: 161 | L66: Mohamad Irvan | N66: 46266.287 | O66: Masih | P66: 73
B67: =INT(I67) -> 46266 | C67: AGENT40 | D67: DC_PASAR_MINGGU | E67: JKT23P | F67: img_v3_02154_4bcd5cba-334b-4ebe-8ede-dbd86c3875ix.jpg | G67: ABSENSI 6:30 KELUAR GUDANG 7:30 TTD JAM 12:00 TTD ALL RITASE PROSPECT PELUANG PELANGGAN SOSIALISASI PAKET DG POD VALID LONGTAIL QUIZ SPRINTER QR SPRINTER | H67: Marketing | I67: 46266.289 | J67: 14 | K67: 85 | L67: MuhamadRamdan_DC PASAR MINGGU | N67: 46266.289 | O67: Masih | P67: 73
B68: =INT(I68) -> 46266 | C68: AGENT23 | D68: TATAARAN | E68: TDO04 | F68: img_v3_02154_5cd1991d-f740-4ff6-8271-9260857173hu.jpg | G68: PUSH KPI ABSENSI POD VALID | H68: other | I68: 46266.289 | J68: 10 | K68: 11 | L68: Keven Joshua Van Bone | N68: 46266.289 | O68: Masih | P68: 175
B69: =INT(I69) -> 46266 | C69: AGENT22 | D69: UPG_SALES | E69: UPG888 | F69: TimePhoto_20260901_071431.jpg | G69: PEMAKSIMALAN PICKUP DAN TTD JAM 12 | H69: other | I69: 46266.289 | J69: 32 | K69: 36 | L69: Edwin Saifuddin Thayeb | N69: 46266.289 | P69: 148
B70: =INT(I70) -> 46266 | C70: AGENT21 | D70: DENPASAR_SELATAN_2 | E70: DPS05B | F70: 20260901_73815AMByGPSMapCamera.mp4 | G70: Marketing Absensi Keluar gudang 07.30 TTD sebelum jam 12.00 TTD Ritase | H70: Marketing | I70: 46266.289 | J70: 6 | K70: 32 | L70: Rezky Fernando Labidu | N70: 46266.289 | O70: Masih | P70: 176
B71: =INT(I71) -> 46266 | C71: AGENT21 | D71: RUTENG | E71: RTG01 | F71: VID-20260901-WA0005.mp4 | G71: RTK DAN PTMP | H71: other | I71: 46266.29 | J71: 11 | K71: 17 | L71: Aloysius Riwanto | N71: 46266.29 | O71: Masih | P71: 176
B72: =INT(I72) -> 46266 | C72: AGENT40 | D72: KALIBARU_01 | E72: JKT10H | F72: image.png,image.png | G72: BRIFING PAGI DC KALIBARU_01 ABSENSI 06:30 KELUAR GUDANG 07:30 TTD JAM 12 90% ALL RITASE 97% QR SPRINTER 1 AWB 1 HARI BARANG BARANG YANG DILARANG KIRIM / ATAU BARANG DG KEBERSIHAN GUDANG | H72: Marketing | I72: 46266.29 | J72: 107 | K72: 135 | L72: A.Abdullah JKT10H | N72: 46266.29 | O72: Masih | P72: 73
B73: =INT(I73) -> 46266 | C73: AGENT23 | D73: BIAU_01 | E73: BUO07B | F73: img_v3_02154_366f634b-cce8-4d80-bf3b-55f8023c68hu.jpg | G73: PAYCOOLS PUSH TTD PARCEL CARE | H73: other | I73: 46266.29 | J73: 4 | K73: 14 | L73: Chikita S. Mentemas | N73: 46266.29 | O73: Tidak | P73: 175
B74: =INT(I74) -> 46266 | C74: AGENT21 | D74: AMPENAN | E74: AMI15 | F74: VID-20260901-WA0064.mp4 | G74: push delivery sebelum 7:30 dan ttd tepat waktu sebelum jam 12 | H74: other | I74: 46266.29 | J74: 24 | K74: 28 | L74: Abdul Latip | N74: 46266.29 | O74: Masih | P74: 176
B75: =INT(I75) -> 46266 | C75: AGENT22 | D75: TELKOMAS | E75: UPG57A | F75: VID-20260720-WA0085.mp4 | G75: Push pencapaian pickup 1 awb 1spt/hari dan scan bermasalah wajib pod valid | H75: other | I75: 46266.291 | J75: 29 | K75: 34 | L75: Supriadi . | N75: 46266.291 | P75: 148
B76: =INT(I76) -> 46266 | C76: AGENT23 | D76: SOEKARNO_HATTA_01 | E76: PLW03G | F76: 046860d1-fbac-48c3-83e8-33c591328afc.jpg | G76: KEBERSIHAN LONGTAIL PUSH TTD | H76: other | I76: 46266.291 | J76: 3 | K76: 14 | L76: Safril Nasaru | N76: 46266.291 | P76: 175
B77: =INT(I77) -> 46266 | C77: AGENT23 | D77: TAHUNA_01 | E77: THA01A | F77: 01-09-2026.jpg | G77: ABSENSI LONGTAIL TTD SBLM JAM 12 | H77: other | I77: 46266.293 | J77: 23 | K77: 32 | L77: Yesenia Makapedua | N77: 46266.293 | O77: Masih | P77: 175
B78: =INT(I78) -> 46266 | C78: AGENT21 | D78: DC_MENGWI_1 | E78: MGW01F | F78: 31-03-202608:21:47AM_1486_ByGPSMapCamera.mp4 | G78: stuk | H78: other | I78: 46266.293 | J78: 51 | K78: 51 | L78: I Putu Adi Putra | N78: 46266.293 | O78: Masih | P78: 176
B79: =INT(I79) -> 46266 | C79: AGENT07 | D79: TEBO_ILIR | E79: MUT07 | F79: TimeVideo_20260901_065852.mp4 | G79: target ttd aktual target ttd jam 12 absensi | H79: other | I79: 46266.294 | J79: 20 | K79: 21 | L79: Guest User 84911 | N79: 46266.294 | O79: Masih | P79: 65
B80: =INT(I80) -> 46266 | C80: AGENT21 | D80: SERUNI | E80: AMI06 | F80: VID_20260901_080228.mp4 | G80: perbaikan TTTDAktual | H80: other | I80: 46266.295 | J80: 23 | K80: 27 | L80: Muhammad Tazki Ardian | N80: 46266.295 | O80: Masih | P80: 176
B81: =INT(I81) -> 46266 | C81: AGENT40 | D81: DC_MAKASAR | E81: JKT20J | F81: WhatsApp Image 2026-09-01 at 07.02.49.jpeg | G81: ABSEN KLUAR GUDANG TTD JAM 12 TTD ALL RITASE | H81: other | I81: 46266.295 | J81: 33 | K81: 99 | L81: Rio Permanna Wijaya | N81: 46266.295 | O81: Masih | P81: 73
B82: =INT(I82) -> 46266 | C82: AGENT40 | D82: SENEN | E82: JKT12 | F82: img_v3_02154_afc825b1-ce4b-4457-b5e3-1406eda55ahu.jpg | G82: BRIFING PAGI DC_SENEN -ABSEN PAGI 06.30 -KELUAR DC 07.30 -TARGET TTD JAM 12 -TARGET ALRITASE -QR SPRINTER 1 AWB/HARI -POD VALID RETUR -6S -PAKET DG | H82: Marketing | I82: 46266.295 | J82: 80 | K82: 132 | L82: Agusman Hulu | N82: 46266.296 | O82: Masih | P82: 73
B83: =INT(I83) -> 46266 | C83: AGENT07 | D83: SLN07 | E83: SLN07 | F83: VID20260812071100.mp4,IMG20260812071146_01.jpg | G83: POD & TTD RETUR | H83: other | I83: 46266.296 | J83: 9 | K83: 9 | L83: Guest User 56467 | N83: 46266.296 | O83: Masih | P83: 65
B84: =INT(I84) -> 46266 | C84: AGENT40 | D84: JOHAR_BARU_01 | E84: JKT13K | F84: TC_00577.jpeg | G84: DANGEROUS GOODS TTD ALL RITASE TTD JAM 12 ABSENSI SPRINTER | H84: other | I84: 46266.296 | J84: 139 | K84: 139 | L84: Pengguna Tamu 97405 | N84: 46266.296 | O84: Masih | P84: 73
B85: =INT(I85) -> 46266 | C85: AGENT22 | D85: LAEYA | E85: WAG04 | F85: IMG-20260901-WA0072.jpg | G85: Pemaksimalan Backup Coveran Delivery | H85: other | I85: 46266.297 | J85: 7 | K85: 10 | L85: Tamsir Tawakal Sp | N85: 46266.297 | P85: 148
B86: =INT(I86) -> 46266 | C86: AGENT21 | D86: WAIKABUBAK | E86: WBK01 | F86: VID-20260901-WA0015.mp4 | G86: Outgoing,target TTD,dan penilaian RSAT DAN PARCEL CARE | H86: other | I86: 46266.297 | J86: 10 | K86: 14 | L86: Dewiyana Yuliana Malo | N86: 46266.297 | O86: Masih | P86: 176
B87: =INT(I87) -> 46266 | C87: AGENT22 | D87: RANDOMAYANG | E87: PAK03 | F87: 2026-09-01 07.58.18_.jpg | G87: Mengarahkan Sprinter mencari customer potensial di lapangan | H87: Marketing | I87: 46266.298 | J87: 11 | K87: 11 | L87: Andi Sudirman Adi Putra | N87: 46266.298 | P87: 148
B88: =INT(I88) -> 46266 | C88: AGENT23 | D88: AMPANA_RAYA | E88: AMP01A | F88: 1788221303069_img_v3_02154_a2808d28-8759-44a6-8e90-253d6e38b5hu.jpg | G88: AMPANA_RAYA LONGTAIL PAYCOOLS TTD SEBELUM JAM 12 POD VALID RITASE TTD QR SPRINTER | H88: Marketing | I88: 46266.298 | J88: 16 | K88: 18 | L88: Moh. Laxmana | N88: 46266.298 | O88: Masih | P88: 175
B89: =INT(I89) -> 46266 | C89: AGENT40 | D89: CP_PONDOK_PINANG_2 | E89: JKT31I | F89: 2026-09-01 07.05.17_5, Jalan Ismail_(Company-BASEY 1).jpg | G89: Briefing pagi cp pondok pinang 2 1. Absensi 06:30 target 92% 2. Keluar gudang 07:30 target 94% 3. TTD jam 12 target 90% 4. Longtail 5. parcel care tiktok dan tokped ( RSAT ) 6. All ritase target 97% 7. Pickup reguler per hari 1 8. Peluang Pelanggan customer baru 9. Penggunaan QR Sprinter 10. COD FD 11. Setoran gopay (reward 80% : 60rb , 90% : 80rb , 100% :100rb) 12. Ketentuan POD Retur 13. Quis sprinter jawab bener semua 14. Barang DG | H89: Marketing | I89: 46266.298 | J89: 30 | K89: 50 | L89: Guest User 92352 | N89: 46266.298 | O89: Masih | P89: 73
B90: =INT(I90) -> 46266 | C90: AGENT22 | D90: MALILI | E90: MAL01 | F90: TimeVideo_20260901_065515.mp4 | G90: QR sprinter bagi prospek bagi untung. | H90: Marketing | I90: 46266.299 | J90: 18 | K90: 23 | L90: Holidin Din | N90: 46266.299 | P90: 148
B91: =INT(I91) -> 46266 | C91: AGENT12 | D91: CILANGKAHAN | E91: RKS20 | F91: 2026-09-01 07.05.56_Jalan Raya Pasar Malingping.mp4 | G91: TTD JAM 12 DAN MEMAKSIMALKAN PAKET PAKET SISA | H91: other | I91: 46266.299 | J91: 60 | K91: 74 | L91: Muhammad SamsudinRKS20 | N91: 46266.299 | P91: 114
B92: =INT(I92) -> 46266 | C92: AGENT22 | D92: UIN_ALAUDDIN | E92: UPG16 | F92: image_2026-09-01_071046075.png | G92: Kode ketiga dan TTD jam 12 | H92: other | I92: 46266.299 | J92: 20 | K92: 39 | L92: Wilhelmus Owen Johnson | N92: 46266.3 | P92: 148
B93: =INT(I93) -> 46266 | C93: AGENT21 | D93: LEWOLEBA | E93: LEW01 | F93: VID-20260901-WA0053.mp4 | G93: push ttd, kurangi paket stuck dan sebelum pulang pastikan aplikasitkosekelumsud | H93: other | I93: 46266.302 | J93: 10 | K93: 15 | L93: Arnoldus Olak Tukan | N93: 46266.302 | O93: Masih | P93: 176
B94: =INT(I94) -> 46266 | C94: AGENT07 | D94: MUS08 | E94: MUS08 | F94: WhatsApp Image 2026-09-01 at 07.13.00.jpeg | G94: POD DAN TTD RETUR | H94: other | I94: 46266.302 | J94: 5 | K94: 10 | L94: Muhammad Rizky | N94: 46266.302 | O94: Masih | P94: 65
B95: =INT(I95) -> 46266 | C95: AGENT40 | D95: DC_CILINCING | E95: JKT10G | F95: IMG-20260901-WA0007.jpg | G95: Absensi Keluar Gudang TTD 12 TTD Ritase Qr Reguler Paket DG Kebersihan Gudang | H95: other | I95: 46266.302 | J95: 89 | K95: 89 | L95: Saleh Saleh | N95: 46266.302 | O95: Tidak | P95: 73
B96: =INT(I96) -> 46266 | C96: AGENT03 | D96: PULAU_RAKYAT | E96: AEK03 | F96: 2026-09-01 07.08.27_No. 50, Jalan Perintis Kemerdekaan_(Judul-JNT EXPRESS PULAU RAKYAT)_(Catatan-PANGLIMA KURIR).jpg | G96: 1. JAM ABSENSI 2. SOP RETURAN 3. MARKETING QR DP DAN QR SPRINTER | H96: Marketing | I96: 46266.303 | J96: 24 | K96: 25 | L96: Pengguna Tamu 66302 | N96: 46266.303 | P96: 74
B97: =INT(I97) -> 46266 | C97: AGENT40 | D97: CP_CIGANJUR | E97: JKT62C | F97: image.png | G97: *ABSENSI 06.30 *KELUAR GUDANG // DC 07.30 *TTD 12.00 & ALL RITASE *KODE KE 3 *KEBERSIHAN GUDANG // DC *PENANGANAN PAKET DG(DANGEROUS GOODS) *SETORAN CODFOD *PENGGUNAAN GOPAY, PAYCOL & QR SPRINTER | H97: Marketing | I97: 46266.303 | J97: 23 | K97: 80 | L97: Rendi CP_ciganjur | N97: 46266.303 | O97: Masih | P97: 73
B98: =INT(I98) -> 46266 | C98: AGENT21 | D98: TNW02B | E98: TNW02B | F98: briefing 1 sep.mp4 | G98: Push TTD sebelum jam 12 dan push stuck , dan pick up sprinter QR | H98: Marketing | I98: 46266.303 | J98: 14 | K98: 24 | L98: I Putu Aridana | N98: 46266.303 | O98: Masih | P98: 176
B99: =INT(I99) -> 46266 | C99: AGENT23 | D99: LANGOWAN | E99: TDO02 | F99: d8b77c54-eb8d-409e-ae5e-60e1b3ffd0f2.JPEG,IMG_9847.mp4 | G99: PUSH KPI | H99: other | I99: 46266.304 | J99: 10 | K99: 12 | L99: Hizkia Runtuwarow | N99: 46266.304 | O99: Masih | P99: 175
B100: =INT(I100) -> 46266 | C100: AGENT22 | D100: ATTAPANGE | E100: SEK03 | F100: 2026-09-01 06.39.40_.jpg | G100: Target pickup harian sprinter pod simpan gudang prospek pelanggan | H100: Marketing | I100: 46266.304 | J100: 10 | K100: 18 | L100: Guest User 15040 | N100: 46266.305 | P100: 148
B101: =INT(I101) -> 46266 | C101: AGENT22 | D101: SOROAKO | E101: MAL02 | F101: VID-20260822-WA0268.mp4 | G101: Pod valid Paket longtail | H101: other | I101: 46266.305 | J101: 15 | K101: 19 | L101: Bagus Adi Saputra | N101: 46266.305 | P101: 148
B102: =INT(I102) -> 46266 | C102: AGENT28 | D102: MANOKWARI | E102: MKW01 | F102: WhatsApp Video 2026-09-01 at 07.14.01.mp4 | G102: MEMPERKENALKAN KURIR BARU, MENGINFOKAN WAJIB INVENTORI, KEBERSIHAN | H102: other | I102: 46266.305 | J102: 4 | K102: 11 | L102: Pengguna Tamu 42526 | N102: 46266.305 | P102: 13
B103: =INT(I103) -> 46266 | C103: AGENT12 | D103: JAMBE_RAYA | E103: BAL02A | F103: VID-20260901-WA0003(1).mp4 | G103: Absensi kehadiran 06:29 Ttd sebelum jam 12 Ttd aktual Gopay Pod Retur | H103: other | I103: 46266.305 | J103: 28 | K103: 36 | L103: Kadiday _BAL02A | N103: 46266.305 | P103: 114
...

Sheet Raw JMS
A1: Tanggal upload fin | B1: Kode Agent 代理区代码 | C1: Nama Drop Point 网点名称 | D1: Kode Drop Point 网点代码 | E1: Video Briefing 班前例会视频 | F1: Summary Briefing 会议要点总结 | G1: Kategori Materi | H1: Tanggal Upload 上传日期 | I1: Sprinter Ikut breifing hari ini | J1: Total Sprinter | K1: created by | L1: status | M1: Last Modified Date 2 | N1: feedback DP | O1: total DP | P1: paste here
A2: =INT(H2) -> 46266 | B2: =RIGHT(Q2,7) -> AGENT19 | C2: =L2 -> SUMBERBARU_1 | D2: =K2 -> JBR30 | H2: =P2 -> 2026-09-01 18:05:03 | K2: {=_xlfn.TEXTSPLIT(R2," ")} -> JBR30 | L2: SUMBERBARU_1 | P2: 2026-09-01 18:05:03 | Q2: 6660019 AGENT19 | R2: JBR30 SUMBERBARU_1 | S2: JBR30000001 | T2: Rahman JM0330010 | U2: obaforever/idnztapp/meeting/20260901/upload_1788260691243951140af7ca34de8ab0bf55b61c8d99c.mp4
A3: =INT(H3) -> 46266 | B3: =RIGHT(Q3,7) -> AGENT19 | C3: =L3 -> MULYOREJO_1 | D3: =K3 -> SUB39A | H3: =P3 -> 2026-09-01 18:02:20 | K3: {=_xlfn.TEXTSPLIT(R3," ")} -> SUB39A | L3: MULYOREJO_1 | P3: 2026-09-01 18:02:20 | Q3: 6660019 AGENT19 | R3: SUB39A MULYOREJO_1 | S3: SUB39A0030 | T3: Bayu Jm0010007 | U3: obaforever/idnztapp/meeting/20260901/upload_178826048773355737032f80d451fa3d75ffc7fc23eef.mp4 | V3: serah terima oaketbreguler klien dengan prosesing double cek minimalisir double penerima, salah temoel alamat dari pengirim
A4: =INT(H4) -> 46266 | B4: =RIGHT(Q4,7) -> AGENT04 | C4: =L4 -> BANGKINANG_01 | D4: =K4 -> BNG01A | H4: =P4 -> 2026-09-01 17:57:32 | K4: {=_xlfn.TEXTSPLIT(R4," ")} -> BNG01A | L4: BANGKINANG_01 | P4: 2026-09-01 17:57:32 | Q4: 6660004 AGENT04 | R4: BNG01A BANGKINANG_01 | S4: LS0000272317 | T4: Sahrul Wadi | U4: obaforever/idnztapp/meeting/20260901/VID_2026-09-01 05-56-1516444229928efe833075194017b20be3f1518f375f.mp4
A5: =INT(H5) -> 46266 | B5: =RIGHT(Q5,7) -> AGENT16 | C5: =L5 -> DC_CINAMBO | D5: =K5 -> BDO05A | H5: =P5 -> 2026-09-01 17:56:56 | K5: {=_xlfn.TEXTSPLIT(R5," ")} -> BDO05A | L5: DC_CINAMBO | P5: 2026-09-01 17:56:56 | Q5: 6660016 AGENT16 | R5: BDO05A DC_CINAMBO | S5: LS0000415301 | T5: Nezar Hikmatiar | U5: obaforever/idnztapp/meeting/20260901/VID_2026-09-01 05-56-24-115250108660c243aefff14f25beef84aeb3cfb38c.mp4
A6: =INT(H6) -> 46266 | B6: =RIGHT(Q6,7) -> AGENT19 | C6: =L6 -> SUKODONO_1 | D6: =K6 -> SDA38 | H6: =P6 -> 2026-09-01 17:54:52 | K6: {=_xlfn.TEXTSPLIT(R6," ")} -> SDA38 | L6: SUKODONO_1 | P6: 2026-09-01 17:54:52 | Q6: 6660019 AGENT19 | R6: SDA38 SUKODONO_1 | S6: SDA380115 | T6: Fery J07192286 | U6: obaforever/idnztapp/meeting/20260901/upload_178825999901436681E65-06C4-4AAB-B7DD-393CE941D2C5ef569a64f91c486db10eab519a9dedf1.mp4 | V6: grooming & capain reg
A7: =INT(H7) -> 46266 | B7: =RIGHT(Q7,7) -> AGENT19 | C7: =L7 -> MANTUP_1 | D7: =K7 -> LMG11A | H7: =P7 -> 2026-09-01 17:48:43 | K7: {=_xlfn.TEXTSPLIT(R7," ")} -> LMG11A | L7: MANTUP_1 | P7: 2026-09-01 17:48:43 | Q7: 6660019 AGENT19 | R7: LMG11A MANTUP_1 | S7: LS0000191119 | T7: Andy J07181603 | U7: obaforever/idnztapp/meeting/20260901/upload_178825970792429ef259307524b2f9063d092014eea8f.MOV | V7: QR SPRINTER
A8: =INT(H8) -> 46266 | B8: =RIGHT(Q8,7) -> AGENT19 | C8: =L8 -> TIKUNG_2 | D8: =K8 -> LMG16A | H8: =P8 -> 2026-09-01 17:47:26 | K8: {=_xlfn.TEXTSPLIT(R8," ")} -> LMG16A | L8: TIKUNG_2 | P8: 2026-09-01 17:47:26 | Q8: 6660019 AGENT19 | R8: LMG16A TIKUNG_2 | S8: LS0000191120 | T8: Andy J07181603 | U8: obaforever/idnztapp/meeting/20260901/upload_17882596387188c5fd341c1f740458587409c40a8208b.MOV | V8: QR SPRINTER
A9: =INT(H9) -> 46266 | B9: =RIGHT(Q9,7) -> AGENT19 | C9: =L9 -> LAMONGAN_2 | D9: =K9 -> LMG01A | H9: =P9 -> 2026-09-01 17:46:36 | K9: {=_xlfn.TEXTSPLIT(R9," ")} -> LMG01A | L9: LAMONGAN_2 | P9: 2026-09-01 17:46:36 | Q9: 6660019 AGENT19 | R9: LMG01A LAMONGAN_2 | S9: 00552807 | T9: Ahmad Andy Fajar Wijaya | U9: obaforever/idnztapp/meeting/20260901/upload_1788259585707038868c22f8242ee8568de9349e01880.MOV | V9: QR SPRINTER
A10: =INT(H10) -> 46266 | B10: =RIGHT(Q10,7) -> AGENT04 | C10: =L10 -> UJUNG_TANJUNG_01 | D10: =K10 -> BAS02A | H10: =P10 -> 2026-09-01 17:45:31 | K10: {=_xlfn.TEXTSPLIT(R10," ")} -> BAS02A | L10: UJUNG_TANJUNG_01 | P10: 2026-09-01 17:45:31 | Q10: 6660004 AGENT04 | R10: BAS02A UJUNG_TANJUNG_01 | S10: 01685590 | T10: Febrianto . | U10: obaforever/idnztapp/meeting/20260901/upload_178825952006868c2272616514b6ab93e4a3b500f44ad.mp4
A11: =INT(H11) -> 46266 | B11: =RIGHT(Q11,7) -> AGENT19 | C11: =L11 -> MAYJEND_BARAT | D11: =K11 -> SUB90 | H11: =P11 -> 2026-09-01 17:16:47 | K11: {=_xlfn.TEXTSPLIT(R11," ")} -> SUB90 | L11: MAYJEND_BARAT | P11: 2026-09-01 17:16:47 | Q11: 6660019 AGENT19 | R11: SUB90 MAYJEND_BARAT | S11: SUB90000025 | T11: Ragil JM0060007 | U11: obaforever/idnztapp/meeting/20260901/upload_1788257796437c8f526b55e6a4c089c0dfbd7f48f2960.mp4 | V11: bulan baru target baru
A12: =INT(H12) -> 46266 | B12: =RIGHT(Q12,7) -> AGENT03 | C12: =L12 -> NEGERI_BARU_02 | D12: =K12 -> RPT02B | H12: =P12 -> 2026-09-01 17:14:23 | K12: {=_xlfn.TEXTSPLIT(R12," ")} -> RPT02B | L12: NEGERI_BARU_02 | P12: 2026-09-01 17:14:23 | Q12: 6660003 AGENT03 | R12: RPT02B NEGERI_BARU_02 | S12: LS0000221064 | T12: SITI NURHAZIZAH RPT02B | U12: obaforever/idnztapp/meeting/20260901/upload_1788257657324a5ac9f4360494dfaaa450b4e92064464.mp4
A13: =INT(H13) -> 46266 | B13: =RIGHT(Q13,7) -> AGENT19 | C13: =L13 -> BWI_GENTENG | D13: =K13 -> BWI10B | H13: =P13 -> 2026-09-01 17:14:13 | K13: {=_xlfn.TEXTSPLIT(R13," ")} -> BWI10B | L13: BWI_GENTENG | P13: 2026-09-01 17:14:13 | Q13: 6660019 AGENT19 | R13: BWI10B BWI_GENTENG | S13: LS0000371669 | T13: Prakoso J07230496 | U13: obaforever/idnztapp/meeting/20260901/VID_2026-09-01 05-12-351555569492aa3f98537874449fac259c490d57eece.mp4 | V13: Indikator rating Sprinter dan penilaian di setiap poin, penilaian customer dan fokus input paket reguler
A14: =INT(H14) -> 46266 | B14: =RIGHT(Q14,7) -> AGENT19 | C14: =L14 -> GLENMORE_1 | D14: =K14 -> BWI09A | H14: =P14 -> 2026-09-01 17:14:01 | K14: {=_xlfn.TEXTSPLIT(R14," ")} -> BWI09A | L14: GLENMORE_1 | P14: 2026-09-01 17:14:01 | Q14: 6660019 AGENT19 | R14: BWI09A GLENMORE_1 | S14: 01378927 | T14: Nor Dwi Prakoso | U14: obaforever/idnztapp/meeting/20260901/VID_2026-09-01 05-12-3057356577733569bd43f78433880dbd496f5ed36fb.mp4 | V14: Indikator rating Sprinter dan penilaian di setiap poin, penilaian customer dan fokus input paket reguler
A15: =INT(H15) -> 46266 | B15: =RIGHT(Q15,7) -> AGENT16 | C15: =L15 -> KALIANGSANA_2 | D15: =K15 -> SBG30 | H15: =P15 -> 2026-09-01 17:09:33 | K15: {=_xlfn.TEXTSPLIT(R15," ")} -> SBG30 | L15: KALIANGSANA_2 | P15: 2026-09-01 17:09:33 | Q15: 6660016 AGENT16 | R15: SBG30 KALIANGSANA_2 | S15: 01206511 | T15: Dede Rino Mailudin | U15: obaforever/idnztapp/meeting/20260901/upload_1788257347947f1f932143bcf4c5bbeade353ac055f10.MOV | V15: QUIZ APP SPRINTER
A16: =INT(H16) -> 46266 | B16: =RIGHT(Q16,7) -> AGENT23 | C16: =L16 -> WINANGUN_01 | D16: =K16 -> MDC09C | H16: =P16 -> 2026-09-01 17:08:34 | K16: {=_xlfn.TEXTSPLIT(R16," ")} -> MDC09C | L16: WINANGUN_01 | P16: 2026-09-01 17:08:34 | Q16: 6660023 AGENT23 | R16: MDC09C WINANGUN_01 | S16: MDC09C000001 | T16: Hizkia Owen Gosal | U16: obaforever/idnztapp/meeting/20260901/upload_17882573086253463309ebc284c3490bea4cf44e1e561.mp4
A17: =INT(H17) -> 46266 | B17: =RIGHT(Q17,7) -> AGENT19 | C17: =L17 -> GENTENG_BWI_1 | D17: =K17 -> BWI10A | H17: =P17 -> 2026-09-01 17:08:30 | K17: {=_xlfn.TEXTSPLIT(R17," ")} -> BWI10A | L17: GENTENG_BWI_1 | P17: 2026-09-01 17:08:30 | Q17: 6660019 AGENT19 | R17: BWI10A GENTENG_BWI_1 | S17: LS0000371717 | T17: Dwi J07230496 | U17: obaforever/idnztapp/meeting/20260901/VID_2026-09-01 05-07-111923041408d20a449e10284235ba0210bab66fc2ee.mp4 | V17: Indikator rating Sprinter dan penilaian di setiap poin, penilaian customer dan fokus input paket reguler
A18: =INT(H18) -> 46266 | B18: =RIGHT(Q18,7) -> AGENT25 | C18: =L18 -> TEWAH | D18: =K18 -> KUK02 | H18: =P18 -> 2026-09-01 17:06:00 | K18: {=_xlfn.TEXTSPLIT(R18," ")} -> KUK02 | L18: TEWAH | P18: 2026-09-01 17:06:00 | Q18: 6660025 AGENT25 | R18: KUK02 TEWAH | S18: 01254245 | T18: Predi Sinambela | U18: obaforever/idnztapp/meeting/20260901/upload_17882571566209e68082fbf4942a9814d4f03c9bbdf09.mp4
A19: =INT(H19) -> 46266 | B19: =RIGHT(Q19,7) -> AGENT16 | C19: =L19 -> SUM08D | D19: =K19 -> SUM08D | H19: =P19 -> 2026-09-01 17:04:52 | K19: {=_xlfn.TEXTSPLIT(R19," ")} -> SUM08D | L19: SUM08D | P19: 2026-09-01 17:04:52 | Q19: 6660016 AGENT16 | R19: SUM08D SUM08D | S19: LS0000415171 | T19: Indra Nuryanto | U19: obaforever/idnztapp/meeting/20260901/upload_17882570703524b61934086e6445e8e807cc274ea968f.MOV | V19: keluar gudang ttd jam 12 ttd aktual paycools gopay absensi karyawan
A20: =INT(H20) -> 46266 | B20: =RIGHT(Q20,7) -> AGENT19 | C20: =L20 -> SAMBENG | D20: =K20 -> LMG10 | H20: =P20 -> 2026-09-01 17:02:57 | K20: {=_xlfn.TEXTSPLIT(R20," ")} -> LMG10 | L20: SAMBENG | P20: 2026-09-01 17:02:57 | Q20: 6660019 AGENT19 | R20: LMG10 SAMBENG | S20: LMG100078 | T20: Said Jm0280021 | U20: obaforever/idnztapp/meeting/20260901/upload_1788256968542aa2e42b6c46141edbf895181d6efe7f5.mp4
A21: =INT(H21) -> 46266 | B21: =RIGHT(Q21,7) -> AGENT19 | C21: =L21 -> KEDUNGPRING_2 | D21: =K21 -> LMG24 | H21: =P21 -> 2026-09-01 17:02:00 | K21: {=_xlfn.TEXTSPLIT(R21," ")} -> LMG24 | L21: KEDUNGPRING_2 | P21: 2026-09-01 17:02:00 | Q21: 6660019 AGENT19 | R21: LMG24 KEDUNGPRING_2 | S21: LS0000208253 | T21: Said_01 JM0280021 | U21: obaforever/idnztapp/meeting/20260901/upload_1788256908761560ab8b7f44b487eba0d645e66b2c347.mp4
A22: =INT(H22) -> 46266 | B22: =RIGHT(Q22,7) -> AGENT16 | C22: =L22 -> KRW17A | D22: =K22 -> KRW17A | H22: =P22 -> 2026-09-01 16:56:44 | K22: {=_xlfn.TEXTSPLIT(R22," ")} -> KRW17A | L22: KRW17A | P22: 2026-09-01 16:56:44 | Q22: 6660016 AGENT16 | R22: KRW17A KRW17A | S22: LS0000415130 | T22: Reza Zaqiyuddin | U22: obaforever/idnztapp/meeting/20260901/upload_17882566002024c9df87eb2b843159b7d8e875f0af5e5.mp4
A23: =INT(H23) -> 46266 | B23: =RIGHT(Q23,7) -> AGENT16 | C23: =L23 -> BATUJAYA | D23: =K23 -> KRW16 | H23: =P23 -> 2026-09-01 16:56:15 | K23: {=_xlfn.TEXTSPLIT(R23," ")} -> KRW16 | L23: BATUJAYA | P23: 2026-09-01 16:56:15 | Q23: 6660016 AGENT16 | R23: KRW16 BATUJAYA | S23: LS0000415129 | T23: Reza Zaqiyuddin | U23: obaforever/idnztapp/meeting/20260901/upload_1788256570324c834262d2fb5498eb12410c7ede5bc7c.mp4
A24: =INT(H24) -> 46266 | B24: =RIGHT(Q24,7) -> AGENT16 | C24: =L24 -> CRN03E | D24: =K24 -> CRN03E | H24: =P24 -> 2026-09-01 16:55:35 | K24: {=_xlfn.TEXTSPLIT(R24," ")} -> CRN03E | L24: CRN03E | P24: 2026-09-01 16:55:35 | Q24: 6660016 AGENT16 | R24: CRN03E CRN03E | S24: LS0000415305 | T24: Dany Kurniawan | U24: obaforever/idnztapp/meeting/20260901/upload_178825637681328d3a36bc3a04dc4856316eecb5cd36d.mp4 | V24: peran sprinter
A25: =INT(H25) -> 46266 | B25: =RIGHT(Q25,7) -> AGENT26 | C25: =L25 -> UPAS_MAJU | D25: =K25 -> TTT02A | H25: =P25 -> 2026-09-01 16:41:51 | K25: {=_xlfn.TEXTSPLIT(R25," ")} -> TTT02A | L25: UPAS_MAJU | P25: 2026-09-01 16:41:51 | Q25: 6660026 AGENT26 | R25: TTT02A UPAS_MAJU | S25: LS0000430535 | T25: Darwis Mas Kartiwa_FL | U25: obaforever/idnztapp/meeting/20260901/upload_1788255659752e599d14c67624dfc954eec7e8517c987.mp4 | V25: brifing penggunaan yoyi dan stuk yoyi
A26: =INT(H26) -> 46266 | B26: =RIGHT(Q26,7) -> AGENT26 | C26: =L26 -> SAJINGAN_BESAR_01 | D26: =K26 -> SAS07A | H26: =P26 -> 2026-09-01 16:33:44 | K26: {=_xlfn.TEXTSPLIT(R26," ")} -> SAS07A | L26: SAJINGAN_BESAR_01 | P26: 2026-09-01 16:33:44 | Q26: 6660026 AGENT26 | R26: SAS07A SAJINGAN_BESAR_01 | S26: SAS07A000009 | T26: Nuari Sukriawan | U26: obaforever/idnztapp/meeting/20260901/VID_2026-09-01 04-31-59177932406372fc7844ed04406782542e2663442151.mp4
A27: =INT(H27) -> 46266 | B27: =RIGHT(Q27,7) -> AGENT19 | C27: =L27 -> NGANJUK_3 | D27: =K27 -> NGK01A | H27: =P27 -> 2026-09-01 16:31:48 | K27: {=_xlfn.TEXTSPLIT(R27," ")} -> NGK01A | L27: NGANJUK_3 | P27: 2026-09-01 16:31:48 | Q27: 6660019 AGENT19 | R27: NGK01A NGANJUK_3 | S27: NGK01A000004 | T27: Didit JM0430005 | U27: obaforever/idnztapp/meeting/20260901/upload_178825509644168ebca472f9e46c1b52b815c90c8aaf2.mp4 | V27: push pencapaian SLA & Reminder paket High Value
A28: =INT(H28) -> 46266 | B28: =RIGHT(Q28,7) -> AGENT19 | C28: =L28 -> LOCERET | D28: =K28 -> NGK03 | H28: =P28 -> 2026-09-01 16:28:16 | K28: {=_xlfn.TEXTSPLIT(R28," ")} -> NGK03 | L28: LOCERET | P28: 2026-09-01 16:28:16 | Q28: 6660019 AGENT19 | R28: NGK03 LOCERET | S28: NGK03000002 | T28: Didit JM0430005 | U28: obaforever/idnztapp/meeting/20260901/upload_1788254808252dbe77be24d2a49eeb294630c9c8a8142.mp4 | V28: push pencapaian SLA & Reminder paket High Value
A29: =INT(H29) -> 46266 | B29: =RIGHT(Q29,7) -> AGENT16 | C29: =L29 -> DC_MARGAASIH | D29: =K29 -> SOG30 | H29: =P29 -> 2026-09-01 16:21:29 | K29: {=_xlfn.TEXTSPLIT(R29," ")} -> SOG30 | L29: DC_MARGAASIH | P29: 2026-09-01 16:21:29 | Q29: 6660016 AGENT16 | R29: SOG30 DC_MARGAASIH | S29: LS0000415111 | T29: Soni | U29: obaforever/idnztapp/meeting/20260901/upload_1788254380566eb1bf1b57a53415db052d5a542a5fe13.mp4 | V29: 1.Ttd jam 12 2.Rating sprinter 3.Sop 6s
A30: =INT(H30) -> 46266 | B30: =RIGHT(Q30,7) -> AGENT19 | C30: =L30 -> DC_TUGU_PENDEKAR | D30: =K30 -> MDN09 | H30: =P30 -> 2026-09-01 16:19:56 | K30: {=_xlfn.TEXTSPLIT(R30," ")} -> MDN09 | L30: DC_TUGU_PENDEKAR | P30: 2026-09-01 16:19:56 | Q30: 6660019 AGENT19 | R30: MDN09 DC_TUGU_PENDEKAR | S30: MDN09000012 | T30: Boma JM0420001 | U30: obaforever/idnztapp/meeting/20260901/upload_1788254384048052b4cf852434b8d98aa9df572067cbb.mp4 | V30: parcel care
A31: =INT(H31) -> 46266 | B31: =RIGHT(Q31,7) -> AGENT19 | C31: =L31 -> SRENGAT | D31: =K31 -> BLT03 | H31: =P31 -> 2026-09-01 16:18:52 | K31: {=_xlfn.TEXTSPLIT(R31," ")} -> BLT03 | L31: SRENGAT | P31: 2026-09-01 16:18:52 | Q31: 6660019 AGENT19 | R31: BLT03 SRENGAT | S31: BLT030131 | T31: Andrean Jm0390005 | U31: obaforever/idnztapp/meeting/20260901/upload_17882543094310b508f2d0cee4a2c87a2ab84273444e0.MOV
A32: =INT(H32) -> 46266 | B32: =RIGHT(Q32,7) -> AGENT16 | C32: =L32 -> IDM07E | D32: =K32 -> IDM07E | H32: =P32 -> 2026-09-01 16:17:34 | K32: {=_xlfn.TEXTSPLIT(R32," ")} -> IDM07E | L32: IDM07E | P32: 2026-09-01 16:17:34 | Q32: 6660016 AGENT16 | R32: IDM07E IDM07E | S32: LS0000415239 | T32: Muhamad Ali Assegap | U32: obaforever/idnztapp/meeting/20260901/VID_2026-09-01 04-16-35225829087450caa870ab641d5847caaed19100090.mp4
A33: =INT(H33) -> 46266 | B33: =RIGHT(Q33,7) -> AGENT19 | C33: =L33 -> GUBENG_2 | D33: =K33 -> SUB12B | H33: =P33 -> 2026-09-01 16:16:04 | K33: {=_xlfn.TEXTSPLIT(R33," ")} -> SUB12B | L33: GUBENG_2 | P33: 2026-09-01 16:16:04 | Q33: 6660019 AGENT19 | R33: SUB12B GUBENG_2 | S33: SUB12B000001 | T33: Ainun JM0580007 | U33: obaforever/idnztapp/meeting/20260901/VID_2026-09-01 04-15-2516618453116f0832f4404a46738f2ca92212653654.mp4 | V33: UPM Sprinter Persiapan kunjungan dari Malaysia dan Thailand
A34: =INT(H34) -> 46266 | B34: =RIGHT(Q34,7) -> AGENT16 | C34: =L34 -> KARAWANG_WETAN | D34: =K34 -> KRW23B | H34: =P34 -> 2026-09-01 16:15:12 | K34: {=_xlfn.TEXTSPLIT(R34," ")} -> KRW23B | L34: KARAWANG_WETAN | P34: 2026-09-01 16:15:12 | Q34: 6660016 AGENT16 | R34: KRW23B KARAWANG_WETAN | S34: LS0000415118 | T34: Asep | U34: obaforever/idnztapp/meeting/20260901/upload_17882540951225fa117b625074ddfa4b62a0004d566f5.mp4 | V34: briefing
A35: =INT(H35) -> 46266 | B35: =RIGHT(Q35,7) -> AGENT16 | C35: =L35 -> GRT32A | D35: =K35 -> GRT32A | H35: =P35 -> 2026-09-01 16:14:59 | K35: {=_xlfn.TEXTSPLIT(R35," ")} -> GRT32A | L35: GRT32A | P35: 2026-09-01 16:14:59 | Q35: 6660016 AGENT16 | R35: GRT32A GRT32A | S35: LS0000415094 | T35: Undang Ramdani | U35: obaforever/idnztapp/meeting/20260901/upload_178825409201689a9e37c840d4c938e6daa3ecaa459ed.mp4
A36: =INT(H36) -> 46266 | B36: =RIGHT(Q36,7) -> AGENT19 | C36: =L36 -> TEGALSARI_4 | D36: =K36 -> SUB30B | H36: =P36 -> 2026-09-01 16:07:12 | K36: {=_xlfn.TEXTSPLIT(R36," ")} -> SUB30B | L36: TEGALSARI_4 | P36: 2026-09-01 16:07:12 | Q36: 6660019 AGENT19 | R36: SUB30B TEGALSARI_4 | S36: SUB30B000001 | T36: Taufiq JM0580048 | U36: obaforever/idnztapp/meeting/20260901/VID_2026-09-01 04-04-57-537609488601a7c0ffd4b3bb995cc985e155b6e.mp4 | V36: Nama DP : TEGALSARI_4 Kode DP : SUB30B Total Brifing : 33 orang Materi Brifing : 1.Kebersihan DP 2.Grooming kayawan 3.Evaluasi kinerja di bulan Agustus dan plan September 4.persiapan kunjungan
A37: =INT(H37) -> 46266 | B37: =RIGHT(Q37,7) -> AGENT16 | C37: =L37 -> CIBUAYA | D37: =K37 -> KRW21 | H37: =P37 -> 2026-09-01 16:05:48 | K37: {=_xlfn.TEXTSPLIT(R37," ")} -> KRW21 | L37: CIBUAYA | P37: 2026-09-01 16:05:48 | Q37: 6660016 AGENT16 | R37: KRW21 CIBUAYA | S37: LS0000415119 | T37: Dede Asikin | U37: obaforever/idnztapp/meeting/20260901/VID_2026-09-01 04-04-4213733761782df34881868438a83a0d71025eaeafc.mp4 | V37: marketing dan penanganan paket retur outgoing
A38: =INT(H38) -> 46266 | B38: =RIGHT(Q38,7) -> AGENT19 | C38: =L38 -> WONOREJO_PSR | D38: =K38 -> PSR05 | H38: =P38 -> 2026-09-01 16:04:56 | K38: {=_xlfn.TEXTSPLIT(R38," ")} -> PSR05 | L38: WONOREJO_PSR | P38: 2026-09-01 16:04:56 | Q38: 6660019 AGENT19 | R38: PSR05 WONOREJO_PSR | S38: 01820826 | T38: Ilham Ramadhan | U38: obaforever/idnztapp/meeting/20260901/VID_2026-09-01 04-04-44-20843276924cf895e4434e427dbb5f233901b9facc.mp4
A39: =INT(H39) -> 46266 | B39: =RIGHT(Q39,7) -> AGENT18 | C39: =L39 -> PEDAN | D39: =K39 -> KLT06 | H39: =P39 -> 2026-09-01 16:01:27 | K39: {=_xlfn.TEXTSPLIT(R39," ")} -> KLT06 | L39: PEDAN | P39: 2026-09-01 16:01:27 | Q39: 6660018 AGENT18 | R39: KLT06 PEDAN | S39: 00571208 | T39: Eko Febri ,Laksono | U39: obaforever/idnztapp/meeting/20260901/upload_1788253231718cfd356afd49f4494bdf431e7e9666f3d.mp4 | V39: absen sebelum jam 6.00 kwis app sprinter ttd jam 12.00
A40: =INT(H40) -> 46266 | B40: =RIGHT(Q40,7) -> AGENT19 | C40: =L40 -> BWI_TEGALSARI_2 | D40: =K40 -> BWI13A | H40: =P40 -> 2026-09-01 15:57:17 | K40: {=_xlfn.TEXTSPLIT(R40," ")} -> BWI13A | L40: BWI_TEGALSARI_2 | P40: 2026-09-01 15:57:17 | Q40: 6660019 AGENT19 | R40: BWI13A BWI_TEGALSARI_2 | S40: LS0000029908 | T40: Riva J07210989 | U40: obaforever/idnztapp/meeting/20260901/VID_2026-09-01 03-56-15-1917005546dc010f6569dd46a9be98640991f16bbb.mp4 | V40: brefing pagi bersama kurir pembahasan terkait cara identifikasi calon customer dengan volume tinggi dan lebih fokus terhadap seller UMKM dan toko rumahan serta memperhatikan area kompetitor
A41: =INT(H41) -> 46266 | B41: =RIGHT(Q41,7) -> AGENT08 | C41: =L41 -> RANGKUI | D41: =K41 -> PGK04 | H41: =P41 -> 2026-09-01 15:56:27 | K41: {=_xlfn.TEXTSPLIT(R41," ")} -> PGK04 | L41: RANGKUI | P41: 2026-09-01 15:56:27 | Q41: 6660008 AGENT08 | R41: PGK04 RANGKUI | S41: PGK040055 | T41: Asep Pratama | U41: obaforever/idnztapp/meeting/20260901/upload_178825296483882803104a1054c09901559f3954704a0.mp4 | V41: absensi d24 gopay qr sprinter parcale care
A42: =INT(H42) -> 46266 | B42: =RIGHT(Q42,7) -> AGENT19 | C42: =L42 -> CLURING | D42: =K42 -> BWI14 | H42: =P42 -> 2026-09-01 15:55:43 | K42: {=_xlfn.TEXTSPLIT(R42," ")} -> BWI14 | L42: CLURING | P42: 2026-09-01 15:55:43 | Q42: 6660019 AGENT19 | R42: BWI14 CLURING | S42: LS0000191132 | T42: Rifqi J07210989 | U42: obaforever/idnztapp/meeting/20260901/upload_178825293412953ef78841bc24db981744f3f20f01b19.mp4 | V42: brefing pagi bersama kurir pembahasan terkait cara identifikasi calon customer dengan volume tinggi dan lebih fokus terhadap seller UMKM dan toko rumahan serta memperhatikan area kompetitor
A43: =INT(H43) -> 46266 | B43: =RIGHT(Q43,7) -> AGENT06 | C43: =L43 -> DHAMASRAYA_01 | D43: =K43 -> DHR07 | H43: =P43 -> 2026-09-01 15:55:13 | K43: {=_xlfn.TEXTSPLIT(R43," ")} -> DHR07 | L43: DHAMASRAYA_01 | P43: 2026-09-01 15:55:13 | Q43: 6660006 AGENT06 | R43: DHR07 DHAMASRAYA_01 | S43: 01941220 | T43: Annisa Rahma Asfitrin | U43: obaforever/idnztapp/meeting/20260901/upload_17882515952286bea4bedbb4748d9b5282b7ef27e861b.mp4
A44: =INT(H44) -> 46266 | B44: =RIGHT(Q44,7) -> AGENT04 | C44: =L44 -> LIPAT_KAIN_01 | D44: =K44 -> BNG06 | H44: =P44 -> 2026-09-01 15:55:05 | K44: {=_xlfn.TEXTSPLIT(R44," ")} -> BNG06 | L44: LIPAT_KAIN_01 | P44: 2026-09-01 15:55:05 | Q44: 6660004 AGENT04 | R44: BNG06 LIPAT_KAIN_01 | S44: BNG060042 | T44: Fadli Rubama | U44: obaforever/idnztapp/meeting/20260901/upload_17882528637779fd01d2148054544838ae5f3365356df.mp4
A45: =INT(H45) -> 46266 | B45: =RIGHT(Q45,7) -> AGENT19 | C45: =L45 -> PURWOHARJO | D45: =K45 -> BWI03 | H45: =P45 -> 2026-09-01 15:54:54 | K45: {=_xlfn.TEXTSPLIT(R45," ")} -> BWI03 | L45: PURWOHARJO | P45: 2026-09-01 15:54:54 | Q45: 6660019 AGENT19 | R45: BWI03 PURWOHARJO | S45: 00556671 | T45: Mochammad Rifqi Riva | U45: obaforever/idnztapp/meeting/20260901/upload_17882528082811911bf89d2c1478eb373c3afa2c4febd.mp4 | V45: brefing pagi bersama kurir pembahasan terkait cara identifikasi calon customer dengan volume tinggi dan lebih fokus terhadap seller UMKM dan toko rumahan serta memperhatikan area kompetitor
A46: =INT(H46) -> 46266 | B46: =RIGHT(Q46,7) -> AGENT19 | C46: =L46 -> KEBON | D46: =K46 -> GSK09 | H46: =P46 -> 2026-09-01 15:52:33 | K46: {=_xlfn.TEXTSPLIT(R46," ")} -> GSK09 | L46: KEBON | P46: 2026-09-01 15:52:33 | Q46: 6660019 AGENT19 | R46: GSK09 KEBON | S46: LS0000191121 | T46: Fariszulhazmi J07190028 | U46: obaforever/idnztapp/meeting/20260901/upload_17882527165285955472862d04c4c9ebb2b771a8092be.mp4 | V46: Briefing awal bulan KPI kurir
A47: =INT(H47) -> 46266 | B47: =RIGHT(Q47,7) -> AGENT19 | C47: =L47 -> KALIWATES_2 | D47: =K47 -> JBR13A | H47: =P47 -> 2026-09-01 15:48:00 | K47: {=_xlfn.TEXTSPLIT(R47," ")} -> JBR13A | L47: KALIWATES_2 | P47: 2026-09-01 15:48:00 | Q47: 6660019 AGENT19 | R47: JBR13A KALIWATES_2 | S47: 00551812 | T47: Rizki Eki Prayoga | U47: obaforever/idnztapp/meeting/20260901/upload_17882524414597ab90f6b068a4e918c180b7d33f7c378.MOV | V47: reminder ujian upm sdm belum lulus dan belum ujian
A48: =INT(H48) -> 46266 | B48: =RIGHT(Q48,7) -> AGENT06 | C48: =L48 -> LUBUK_ALUNG_02 | D48: =K48 -> PPR16A | H48: =P48 -> 2026-09-01 15:46:34 | K48: {=_xlfn.TEXTSPLIT(R48," ")} -> PPR16A | L48: LUBUK_ALUNG_02 | P48: 2026-09-01 15:46:34 | Q48: 6660006 AGENT06 | R48: PPR16A LUBUK_ALUNG_02 | S48: PPR16A000003 | T48: Rafli Ramadhinata | U48: obaforever/idnztapp/meeting/20260901/upload_178825236809058AC9AD8-CACE-4670-896B-27C50E1012119b641b346d2f4955954a94d21998a6e4.mp4
A49: =INT(H49) -> 46266 | B49: =RIGHT(Q49,7) -> AGENT02 | C49: =L49 -> SEI_RAMPAH | D49: =K49 -> SER01 | H49: =P49 -> 2026-09-01 15:45:38 | K49: {=_xlfn.TEXTSPLIT(R49," ")} -> SER01 | L49: SEI_RAMPAH | P49: 2026-09-01 15:45:38 | Q49: 6660002 AGENT02 | R49: SER01 SEI_RAMPAH | S49: SER010026 | T49: Riko Prayoga | U49: obaforever/idnztapp/meeting/20260901/upload_1788252326926B946A21F-5808-4838-B6A5-C92904E0B19170764baafe5d4dab8037db080db51e5a.mp4
A50: =INT(H50) -> 46266 | B50: =RIGHT(Q50,7) -> AGENT02 | C50: =L50 -> TIGA_LINGGA | D50: =K50 -> ZIK02 | H50: =P50 -> 2026-09-01 15:43:46 | K50: {=_xlfn.TEXTSPLIT(R50," ")} -> ZIK02 | L50: TIGA_LINGGA | P50: 2026-09-01 15:43:46 | Q50: 6660002 AGENT02 | R50: ZIK02 TIGA_LINGGA | S50: ZIK02000036 | T50: Herry R Tarigan | U50: obaforever/idnztapp/meeting/20260901/VID_2026-09-01 03-41-16-17686742215908aa9cb69c45e7a63cfe3cfbf0cc40.mp4
A51: =INT(H51) -> 46266 | B51: =RIGHT(Q51,7) -> AGENT19 | C51: =L51 -> MUMBULSARI_1 | D51: =K51 -> JBR12A | H51: =P51 -> 2026-09-01 15:43:23 | K51: {=_xlfn.TEXTSPLIT(R51," ")} -> JBR12A | L51: MUMBULSARI_1 | P51: 2026-09-01 15:43:23 | Q51: 6660019 AGENT19 | R51: JBR12A MUMBULSARI_1 | S51: JBR16000005 | T51: Miftahul JM0080063 | U51: obaforever/idnztapp/meeting/20260901/upload_1788252170856cd4707f3d2d7463ebd61e62cb2f51b32.mp4
A52: =INT(H52) -> 46266 | B52: =RIGHT(Q52,7) -> AGENT19 | C52: =L52 -> KARANG_PLOSO_1 | D52: =K52 -> MLG42 | H52: =P52 -> 2026-09-01 15:42:17 | K52: {=_xlfn.TEXTSPLIT(R52," ")} -> MLG42 | L52: KARANG_PLOSO_1 | P52: 2026-09-01 15:42:17 | Q52: 6660019 AGENT19 | R52: MLG42 KARANG_PLOSO_1 | S52: MLG420109 | T52: Zainuri J07160589 | U52: obaforever/idnztapp/meeting/20260901/upload_178825207796806459bc1e0344613bd8e8f9a303e94cd.mp4 | V52: indikator rating sprinter
A53: =INT(H53) -> 46266 | B53: =RIGHT(Q53,7) -> AGENT23 | C53: =L53 -> SAUMLAKI | D53: =K53 -> SML01 | H53: =P53 -> 2026-09-01 15:41:26 | K53: {=_xlfn.TEXTSPLIT(R53," ")} -> SML01 | L53: SAUMLAKI | P53: 2026-09-01 15:41:26 | Q53: 6660023 AGENT23 | R53: SML01 SAUMLAKI | S53: 00568147 | T53: Sofyan Azzis | U53: obaforever/idnztapp/meeting/20260901/upload_17882520496212402c345ece8497694f5a8fad233d238.mp4
A54: =INT(H54) -> 46266 | B54: =RIGHT(Q54,7) -> AGENT19 | C54: =L54 -> PAKUSARI | D54: =K54 -> JBR04A | H54: =P54 -> 2026-09-01 15:41:00 | K54: {=_xlfn.TEXTSPLIT(R54," ")} -> JBR04A | L54: PAKUSARI | P54: 2026-09-01 15:41:00 | Q54: 6660019 AGENT19 | R54: JBR04A PAKUSARI | S54: JBR04A000001 | T54: Kusnadi JM0080076 | U54: obaforever/idnztapp/meeting/20260901/upload_1788252039621658fb302bff04d28a6f2f7c4b1b53580.mp4 | V54: doa bersama, awal bulan penuh dengan semangat team dan capai target
A55: =INT(H55) -> 46266 | B55: =RIGHT(Q55,7) -> AGENT19 | C55: =L55 -> MAYANG | D55: =K55 -> JBR16 | H55: =P55 -> 2026-09-01 15:39:44 | K55: {=_xlfn.TEXTSPLIT(R55," ")} -> JBR16 | L55: MAYANG | P55: 2026-09-01 15:39:44 | Q55: 6660019 AGENT19 | R55: JBR16 MAYANG | S55: JBR16000006 | T55: Kusnadi JM0080076 | U55: obaforever/idnztapp/meeting/20260901/upload_1788251940021b51bd610771541fabbb022399ef33a48.mp4 | V55: doa bersama, awal bulan penuh dengan semangat untuk targeting
A56: =INT(H56) -> 46266 | B56: =RIGHT(Q56,7) -> AGENT04 | C56: =L56 -> BALAM_02 | D56: =K56 -> BAS03B | H56: =P56 -> 2026-09-01 15:39:07 | K56: {=_xlfn.TEXTSPLIT(R56," ")} -> BAS03B | L56: BALAM_02 | P56: 2026-09-01 15:39:07 | Q56: 6660004 AGENT04 | R56: BAS03B BALAM_02 | S56: BAS03B0025 | T56: Rasyid Ahmad | U56: obaforever/idnztapp/meeting/20260901/upload_17882519097472406f2b515d94291aeb8bf90a5b615e5.mp4 | V56: absensi TT-REVERSE/PENGEMBALIAN
A57: =INT(H57) -> 46266 | B57: =RIGHT(Q57,7) -> AGENT01 | C57: =L57 -> BEBESEN | D57: =K57 -> TKO02 | H57: =P57 -> 2026-09-01 15:38:38 | K57: {=_xlfn.TEXTSPLIT(R57," ")} -> TKO02 | L57: BEBESEN | P57: 2026-09-01 15:38:38 | Q57: 6660001 AGENT01 | R57: TKO02 BEBESEN | S57: TKO020012 | T57: Dedi Setia | U57: obaforever/idnztapp/meeting/20260901/upload_1788251906036dd15a5c50ffc4e95b8392a765e81097e.mp4
A58: =INT(H58) -> 46266 | B58: =RIGHT(Q58,7) -> AGENT19 | C58: =L58 -> JEMBER | D58: =K58 -> JBR01 | H58: =P58 -> 2026-09-01 15:35:29 | K58: {=_xlfn.TEXTSPLIT(R58," ")} -> JBR01 | L58: JEMBER | P58: 2026-09-01 15:35:29 | Q58: 6660019 AGENT19 | R58: JBR01 JEMBER | S58: LS0000377476 | T58: Miftahul_01 JM0080063 | U58: obaforever/idnztapp/meeting/20260901/upload_17882517238660c3e489fdadb463f9bc44d7e59c96b00.mp4
A59: =INT(H59) -> 46266 | B59: =RIGHT(Q59,7) -> AGENT19 | C59: =L59 -> BANYUATES_1 | D59: =K59 -> SPG06 | H59: =P59 -> 2026-09-01 15:34:09 | K59: {=_xlfn.TEXTSPLIT(R59," ")} -> SPG06 | L59: BANYUATES_1 | P59: 2026-09-01 15:34:09 | Q59: 6660019 AGENT19 | R59: SPG06 BANYUATES_1 | S59: SPG060017 | T59: Cp_banyuates1 Ilham | U59: obaforever/idnztapp/meeting/20260901/upload_1788251644087504b9f1ed41748ddbbe3fb5d294b4fec.mp4
A60: =INT(H60) -> 46266 | B60: =RIGHT(Q60,7) -> AGENT16 | C60: =L60 -> SUM02B | D60: =K60 -> SUM02B | H60: =P60 -> 2026-09-01 15:31:28 | K60: {=_xlfn.TEXTSPLIT(R60," ")} -> SUM02B | L60: SUM02B | P60: 2026-09-01 15:31:28 | Q60: 6660016 AGENT16 | R60: SUM02B SUM02B | S60: LS0000415175 | T60: Muhammad Ramdhan | U60: obaforever/idnztapp/meeting/20260901/upload_178825144707489160cedd44144a98bc1c516909dd4ad.mp4 | V60: pph21
A61: =INT(H61) -> 46266 | B61: =RIGHT(Q61,7) -> AGENT16 | C61: =L61 -> SMB10C | D61: =K61 -> SMB10C | H61: =P61 -> 2026-09-01 15:31:15 | K61: {=_xlfn.TEXTSPLIT(R61," ")} -> SMB10C | L61: SMB10C | P61: 2026-09-01 15:31:15 | Q61: 6660016 AGENT16 | R61: SMB10C SMB10C | S61: LS0000415307 | T61: Kuswanto Hendriyana | U61: obaforever/idnztapp/meeting/20260901/VID_2026-09-01 03-29-38-1062600085e5c4599325b04ea68a6f3337e566bd1b.mp4 | V61: edukasi calon customer, bukan hanya mencari customer yg kirimannya banyak saja tapi bisa juga customer umkm ataupun customer yg ingin kirim ke anak ataupun saudaranya
A62: =INT(H62) -> 46266 | B62: =RIGHT(Q62,7) -> AGENT16 | C62: =L62 -> SUM01B | D62: =K62 -> SUM01B | H62: =P62 -> 2026-09-01 15:30:11 | K62: {=_xlfn.TEXTSPLIT(R62," ")} -> SUM01B | L62: SUM01B | P62: 2026-09-01 15:30:11 | Q62: 6660016 AGENT16 | R62: SUM01B SUM01B | S62: LS0000415174 | T62: Muhammad Ramdhan | U62: obaforever/idnztapp/meeting/20260901/upload_17882513759466496a8f75fa54a28980c4a54938af863.mp4 | V62: pph21 dan ketentuan penggajian
A63: =INT(H63) -> 46266 | B63: =RIGHT(Q63,7) -> AGENT16 | C63: =L63 -> GRT31B | D63: =K63 -> GRT31B | H63: =P63 -> 2026-09-01 15:29:59 | K63: {=_xlfn.TEXTSPLIT(R63," ")} -> GRT31B | L63: GRT31B | P63: 2026-09-01 15:29:59 | Q63: 6660016 AGENT16 | R63: GRT31B GRT31B | S63: LS0000415088 | T63: Rifki Shafik Fadillah | U63: obaforever/idnztapp/meeting/20260901/upload_17882513703899d2aa01ee46f4716b4455979f61521ac.mp4 | V63: Push naikin penggunaan paycool dan gopay
A64: =INT(H64) -> 46266 | B64: =RIGHT(Q64,7) -> AGENT19 | C64: =L64 -> KEDIRI | D64: =K64 -> KDR01 | H64: =P64 -> 2026-09-01 15:26:41 | K64: {=_xlfn.TEXTSPLIT(R64," ")} -> KDR01 | L64: KEDIRI | P64: 2026-09-01 15:26:41 | Q64: 6660019 AGENT19 | R64: KDR01 KEDIRI | S64: KDR010337 | T64: Prasetyo Jm0310023 | U64: obaforever/idnztapp/meeting/20260901/VID_2026-09-01 03-26-27-3817833985bc30510d5934bf0b7c8cb8e5a7d16fb.mp4
A65: =INT(H65) -> 46266 | B65: =RIGHT(Q65,7) -> AGENT19 | C65: =L65 -> LARANGAN_PAMEKASAN | D65: =K65 -> PKS04 | H65: =P65 -> 2026-09-01 15:25:29 | K65: {=_xlfn.TEXTSPLIT(R65," ")} -> PKS04 | L65: LARANGAN_PAMEKASAN | P65: 2026-09-01 15:25:29 | Q65: 6660019 AGENT19 | R65: PKS04 LARANGAN_PAMEKASAN | S65: PKS04000005 | T65: Nanda JM0370046 | U65: obaforever/idnztapp/meeting/20260901/upload_17882511269737b2f7ae6418c4a79b9a8dcf845bb488a.MOV
A66: =INT(H66) -> 46266 | B66: =RIGHT(Q66,7) -> AGENT19 | C66: =L66 -> GUNUNG_ANYAR | D66: =K66 -> SUB26 | H66: =P66 -> 2026-09-01 15:23:57 | K66: {=_xlfn.TEXTSPLIT(R66," ")} -> SUB26 | L66: GUNUNG_ANYAR | P66: 2026-09-01 15:23:57 | Q66: 6660019 AGENT19 | R66: SUB26 GUNUNG_ANYAR | S66: SUB260075 | T66: Satrio Jm0110026 | U66: obaforever/idnztapp/meeting/20260901/upload_17882509986861dea3b434f3d46678dc0c781385b9959.mp4 | V66: - Ujian Pengendalian Mutu Sprinter - Grooming - Rating Sprinter
A67: =INT(H67) -> 46266 | B67: =RIGHT(Q67,7) -> AGENT06 | C67: =L67 -> CP_CAHAYA_SAMUDRA | D67: =K67 -> PDG16 | H67: =P67 -> 2026-09-01 15:21:22 | K67: {=_xlfn.TEXTSPLIT(R67," ")} -> PDG16 | L67: CP_CAHAYA_SAMUDRA | P67: 2026-09-01 15:21:22 | Q67: 6660006 AGENT06 | R67: PDG16 CP_CAHAYA_SAMUDRA | S67: PDG16000005 | T67: Rode Vrianus | U67: obaforever/idnztapp/meeting/20260901/upload_17882508721835acaf69d98fb4efdaf90f96a1ea7fde2.mp4
A68: =INT(H68) -> 46266 | B68: =RIGHT(Q68,7) -> AGENT16 | C68: =L68 -> CIMANGGU_PER | D68: =K68 -> PER16 | H68: =P68 -> 2026-09-01 15:19:42 | K68: {=_xlfn.TEXTSPLIT(R68," ")} -> PER16 | L68: CIMANGGU_PER | P68: 2026-09-01 15:19:42 | Q68: 6660016 AGENT16 | R68: PER16 CIMANGGU_PER | S68: LS0000418236 | T68: Rendi Muhamad | U68: obaforever/idnztapp/meeting/20260901/upload_17882507745297a94a35241a5467db0b29bc0c323d273.MOV | V68: ttd jam 12
A69: =INT(H69) -> 46266 | B69: =RIGHT(Q69,7) -> AGENT19 | C69: =L69 -> PLOSOKLATEN | D69: =K69 -> KDR09 | H69: =P69 -> 2026-09-01 15:18:03 | K69: {=_xlfn.TEXTSPLIT(R69," ")} -> KDR09 | L69: PLOSOKLATEN | P69: 2026-09-01 15:18:03 | Q69: 6660019 AGENT19 | R69: KDR09 PLOSOKLATEN | S69: KDR09000007 | T69: Laga JM0400006 | U69: obaforever/idnztapp/meeting/20260901/upload_1788250678846df7aff6f0243462b9739896f163c581d.mp4
A70: =INT(H70) -> 46266 | B70: =RIGHT(Q70,7) -> AGENT19 | C70: =L70 -> NGADILUWIH | D70: =K70 -> KDR07 | H70: =P70 -> 2026-09-01 15:17:01 | K70: {=_xlfn.TEXTSPLIT(R70," ")} -> KDR07 | L70: NGADILUWIH | P70: 2026-09-01 15:17:01 | Q70: 6660019 AGENT19 | R70: KDR07 NGADILUWIH | S70: KDR070132 | T70: Laga Jm0400006 | U70: obaforever/idnztapp/meeting/20260901/upload_1788250617006e2dae0a45bd34e558388f4edc9f5ecde.mp4
A71: =INT(H71) -> 46266 | B71: =RIGHT(Q71,7) -> AGENT19 | C71: =L71 -> TUTUR_1 | D71: =K71 -> PND06A | H71: =P71 -> 2026-09-01 15:16:56 | K71: {=_xlfn.TEXTSPLIT(R71," ")} -> PND06A | L71: TUTUR_1 | P71: 2026-09-01 15:16:56 | Q71: 6660019 AGENT19 | R71: PND06A TUTUR_1 | S71: LS0000085706 | T71: Ridwan J07171620 | U71: obaforever/idnztapp/meeting/20260901/upload_17882505923892f0d9cdb349142158a68cf70a641ada2.mp4 | V71: pod scand gagal pu reverse valid sla ttd jam 12 & all day
A72: =INT(H72) -> 46266 | B72: =RIGHT(Q72,7) -> AGENT05 | C72: =L72 -> SENJULUNG | D72: =K72 -> BTH31 | H72: =P72 -> 2026-09-01 15:16:12 | K72: {=_xlfn.TEXTSPLIT(R72," ")} -> BTH31 | L72: SENJULUNG | P72: 2026-09-01 15:16:12 | Q72: 6660005 AGENT05 | R72: BTH31 SENJULUNG | S72: BTH31000002 | T72: Alex Ryan Yulianto | U72: obaforever/idnztapp/meeting/20260901/upload_1788250547889fda5b25505ee4d4f9cbc4b96c0344cb2.mp4
A73: =INT(H73) -> 46266 | B73: =RIGHT(Q73,7) -> AGENT19 | C73: =L73 -> PURWOSARI_PND | D73: =K73 -> PND03 | H73: =P73 -> 2026-09-01 15:15:36 | K73: {=_xlfn.TEXTSPLIT(R73," ")} -> PND03 | L73: PURWOSARI_PND | P73: 2026-09-01 15:15:36 | Q73: 6660019 AGENT19 | R73: PND03 PURWOSARI_PND | S73: 00552199 | T73: Ridwan Fatarudin | U73: obaforever/idnztapp/meeting/20260901/upload_178825049119298a2d95be1cf4c83bbdb4fc1a5df0dbd.mp4 | V73: jadwal pick up ecommerce sortir paket outgoing reminder sprinter bc target bulanan
A74: =INT(H74) -> 46266 | B74: =RIGHT(Q74,7) -> AGENT19 | C74: =L74 -> NGORO | D74: =K74 -> MOJ01 | H74: =P74 -> 2026-09-01 15:14:41 | K74: {=_xlfn.TEXTSPLIT(R74," ")} -> MOJ01 | L74: NGORO | P74: 2026-09-01 15:14:41 | Q74: 6660019 AGENT19 | R74: MOJ01 NGORO | S74: 00554276 | T74: Indra Kokasih | U74: obaforever/idnztapp/meeting/20260901/upload_1788250462906FEB97798-37ED-44A0-B283-1798D77D84B6e2fda53978a34223b554f9b9f14339e9.mp4 | V74: materi SOP Hight Value
A75: =INT(H75) -> 46266 | B75: =RIGHT(Q75,7) -> AGENT04 | C75: =L75 -> BUKIT_KAPUR_01 | D75: =K75 -> DUM01B | H75: =P75 -> 2026-09-01 15:12:42 | K75: {=_xlfn.TEXTSPLIT(R75," ")} -> DUM01B | L75: BUKIT_KAPUR_01 | P75: 2026-09-01 15:12:42 | Q75: 6660004 AGENT04 | R75: DUM01B BUKIT_KAPUR_01 | S75: 01578769 | T75: Winda Wati | U75: obaforever/idnztapp/meeting/20260901/upload_178825034688818bf180b53b540538dd8ba4ac2554c7c.mp4 | V75: DUM01B BRIEFFING 01/09/2026
A76: =INT(H76) -> 46266 | B76: =RIGHT(Q76,7) -> AGENT16 | C76: =L76 -> GRT17B | D76: =K76 -> GRT17B | H76: =P76 -> 2026-09-01 15:08:03 | K76: {=_xlfn.TEXTSPLIT(R76," ")} -> GRT17B | L76: GRT17B | P76: 2026-09-01 15:08:03 | Q76: 6660016 AGENT16 | R76: GRT17B GRT17B | S76: LS0000415073 | T76: Adi Firmansyah | U76: obaforever/idnztapp/meeting/20260901/upload_1788250073408cf4aafe24e584f099faf2c3bb248054f.MOV | V76: indikator rating sprinter
A77: =INT(H77) -> 46266 | B77: =RIGHT(Q77,7) -> AGENT05 | C77: =L77 -> BATAM_KOTA | D77: =K77 -> BTH02 | H77: =P77 -> 2026-09-01 15:07:44 | K77: {=_xlfn.TEXTSPLIT(R77," ")} -> BTH02 | L77: BATAM_KOTA | P77: 2026-09-01 15:07:44 | Q77: 6660005 AGENT05 | R77: BTH02 BATAM_KOTA | S77: BTH02000058 | T77: HARI HANSYA | U77: obaforever/idnztapp/meeting/20260901/VID_2026-09-01 03-06-53-208264830544961ceb94814d7e8a82629c6bf91b87.mp4 | V77: ttd aktual
A78: =INT(H78) -> 46266 | B78: =RIGHT(Q78,7) -> AGENT16 | C78: =L78 -> DC_NGAMPRAH | D78: =K78 -> NGP14 | H78: =P78 -> 2026-09-01 15:07:29 | K78: {=_xlfn.TEXTSPLIT(R78," ")} -> NGP14 | L78: DC_NGAMPRAH | P78: 2026-09-01 15:07:29 | Q78: 6660016 AGENT16 | R78: NGP14 DC_NGAMPRAH | S78: LS0000415148 | T78: Tresha Oktariana | U78: obaforever/idnztapp/meeting/20260901/VID_2026-09-01 03-05-3220672976256d9b89de380548019724e81de672ee8b.mp4
A79: =INT(H79) -> 46266 | B79: =RIGHT(Q79,7) -> AGENT04 | C79: =L79 -> TAMBUSAI_UTARA_01 | D79: =K79 -> PAP07 | H79: =P79 -> 2026-09-01 15:05:21 | K79: {=_xlfn.TEXTSPLIT(R79," ")} -> PAP07 | L79: TAMBUSAI_UTARA_01 | P79: 2026-09-01 15:05:21 | Q79: 6660004 AGENT04 | R79: PAP07 TAMBUSAI_UTARA_01 | S79: PAP070020 | T79: Munir Munadi | U79: obaforever/idnztapp/meeting/20260901/VID_2026-09-01 03-02-57327434879c99b5c964a3c40a4ae1d7ed8eb60b035.mp4
A80: =INT(H80) -> 46266 | B80: =RIGHT(Q80,7) -> AGENT16 | C80: =L80 -> DC_KARAWANG_BARAT | D80: =K80 -> KRW23 | H80: =P80 -> 2026-09-01 15:04:58 | K80: {=_xlfn.TEXTSPLIT(R80," ")} -> KRW23 | L80: DC_KARAWANG_BARAT | P80: 2026-09-01 15:04:58 | Q80: 6660016 AGENT16 | R80: KRW23 DC_KARAWANG_BARAT | S80: LS0000415114 | T80: Ansor Fauzi Fadillah | U80: obaforever/idnztapp/meeting/20260901/upload_1788249838780d0e054c592604402ae3b4f01fbe98315.mp4 | V80: Penilaian Sprinter & Quiz APP Sprinter
A81: =INT(H81) -> 46266 | B81: =RIGHT(Q81,7) -> AGENT19 | C81: =L81 -> PALENGAAN_1 | D81: =K81 -> PKS05 | H81: =P81 -> 2026-09-01 15:04:40 | K81: {=_xlfn.TEXTSPLIT(R81," ")} -> PKS05 | L81: PALENGAAN_1 | P81: 2026-09-01 15:04:40 | Q81: 6660019 AGENT19 | R81: PKS05 PALENGAAN_1 | S81: PKS05000007 | T81: Farida JM0370006 | U81: obaforever/idnztapp/meeting/20260901/upload_1788250470924a01bd0e5cc3f42ad85790cb6ae17a494.mp4
A82: =INT(H82) -> 46266 | B82: =RIGHT(Q82,7) -> AGENT05 | C82: =L82 -> SUNGAI_RAYA_KARIMUN | D82: =K82 -> TJU05 | H82: =P82 -> 2026-09-01 15:03:49 | K82: {=_xlfn.TEXTSPLIT(R82," ")} -> TJU05 | L82: SUNGAI_RAYA_KARIMUN | P82: 2026-09-01 15:03:49 | Q82: 6660005 AGENT05 | R82: TJU05 SUNGAI_RAYA_KARIMUN | S82: LS0000430318 | T82: MUHAMMAD ALFIAN SYAH | U82: obaforever/idnztapp/meeting/20260901/upload_17882498181684b0949ea8bd84afabe961b4e9fa215d5.mp4 | V82: SUNGAI RAYA
A83: =INT(H83) -> 46266 | B83: =RIGHT(Q83,7) -> AGENT16 | C83: =L83 -> SOG26A | D83: =K83 -> SOG26A | H83: =P83 -> 2026-09-01 15:02:57 | K83: {=_xlfn.TEXTSPLIT(R83," ")} -> SOG26A | L83: SOG26A | P83: 2026-09-01 15:02:57 | Q83: 6660016 AGENT16 | R83: SOG26A SOG26A | S83: LS0000415096 | T83: Ade Rahmat | U83: obaforever/idnztapp/meeting/20260901/VID_2026-09-01 03-02-53222964153afcdeafac31d46c59d17944ff17fe146.mp4
A84: =INT(H84) -> 46266 | B84: =RIGHT(Q84,7) -> AGENT19 | C84: =L84 -> MULYOREJO | D84: =K84 -> SUB97 | H84: =P84 -> 2026-09-01 15:02:26 | K84: {=_xlfn.TEXTSPLIT(R84," ")} -> SUB97 | L84: MULYOREJO | P84: 2026-09-01 15:02:26 | Q84: 6660019 AGENT19 | R84: SUB97 MULYOREJO | S84: SUB970656 | T84: Vebyola Jm0010049 | U84: obaforever/idnztapp/meeting/20260901/upload_1788249682114362d571d3007464fa6b23e40b3d1f2f8.MOV | V84: Sticker High Value Target Pemasangan Banner Warung
A85: =INT(H85) -> 46266 | B85: =RIGHT(Q85,7) -> AGENT05 | C85: =L85 -> LAGOI | D85: =K85 -> BSB02 | H85: =P85 -> 2026-09-01 15:01:29 | K85: {=_xlfn.TEXTSPLIT(R85," ")} -> BSB02 | L85: LAGOI | P85: 2026-09-01 15:01:29 | Q85: 6660005 AGENT05 | R85: BSB02 LAGOI | S85: BSB020006 | T85: Reni | U85: obaforever/idnztapp/meeting/20260901/VID_2026-09-01 02-57-2310837967940dbc9bbb5aba449b8e3bfa5e821507f5.mp4
A86: =INT(H86) -> 46266 | B86: =RIGHT(Q86,7) -> AGENT14 | C86: =L86 -> PARUNG_PANJANG | D86: =K86 -> CIB08 | H86: =P86 -> 2026-09-01 15:01:03 | K86: {=_xlfn.TEXTSPLIT(R86," ")} -> CIB08 | L86: PARUNG_PANJANG | P86: 2026-09-01 15:01:03 | Q86: 6660014 AGENT14 | R86: CIB08 PARUNG_PANJANG | S86: CIB080045 | T86: Indra Aenudin | U86: obaforever/idnztapp/meeting/20260901/upload_17882496312147beb9b6893b64c9dbf4fbe2fb56cf069.mp4 | V86: ratting spriq¹nter
A87: =INT(H87) -> 46266 | B87: =RIGHT(Q87,7) -> AGENT16 | C87: =L87 -> DC_KATAPANG | D87: =K87 -> SOG32 | H87: =P87 -> 2026-09-01 15:00:46 | K87: {=_xlfn.TEXTSPLIT(R87," ")} -> SOG32 | L87: DC_KATAPANG | P87: 2026-09-01 15:00:46 | Q87: 6660016 AGENT16 | R87: SOG32 DC_KATAPANG | S87: LS0000415107 | T87: Muhammad Salim Riyadul Gupron | U87: obaforever/idnztapp/meeting/20260901/upload_17882496427617c8fe344dfda4e44b032f333a218cb9c.mp4
A88: =INT(H88) -> 46266 | B88: =RIGHT(Q88,7) -> AGENT12 | C88: =L88 -> PONDOK_PUCUNG | D88: =K88 -> CIP05I | H88: =P88 -> 2026-09-01 15:00:11 | K88: {=_xlfn.TEXTSPLIT(R88," ")} -> CIP05I | L88: PONDOK_PUCUNG | P88: 2026-09-01 15:00:11 | Q88: 6660012 AGENT12 | R88: CIP05I PONDOK_PUCUNG | S88: LS0000214136 | T88: MSML_MUHAMMAD RIFKI FAUZI | U88: obaforever/idnztapp/meeting/20260901/upload_17882496004473590a1d9b48b4d88bb635a0a1864e8cb.mp4 | V88: oprasional dp
A89: =INT(H89) -> 46266 | B89: =RIGHT(Q89,7) -> AGENT16 | C89: =L89 -> CITAPEN | D89: =K89 -> NGP11B | H89: =P89 -> 2026-09-01 15:00:09 | K89: {=_xlfn.TEXTSPLIT(R89," ")} -> NGP11B | L89: CITAPEN | P89: 2026-09-01 15:00:09 | Q89: 6660016 AGENT16 | R89: NGP11B CITAPEN | S89: LS0000415146 | T89: Sandi Mutakin | U89: obaforever/idnztapp/meeting/20260901/VID_2026-09-01 02-59-461969425208858e7f34caab4fd2b8e419ac2608dd61.mp4 | V89: edukasi mengenai target kurir dan juga pickup reguler
A90: =INT(H90) -> 46266 | B90: =RIGHT(Q90,7) -> AGENT06 | C90: =L90 -> GUNUNG_TULEH | D90: =K90 -> PSB06 | H90: =P90 -> 2026-09-01 15:00:08 | K90: {=_xlfn.TEXTSPLIT(R90," ")} -> PSB06 | L90: GUNUNG_TULEH | P90: 2026-09-01 15:00:08 | Q90: 6660006 AGENT06 | R90: PSB06 GUNUNG_TULEH | S90: 02037060 | T90: Yulia ,Amelia Febri | U90: obaforever/idnztapp/meeting/20260901/upload_178824958039760a523739b6940dc849d99571d8da744.mp4 | V90: masih melakukan brief7ng di PSB01B
A91: =INT(H91) -> 46266 | B91: =RIGHT(Q91,7) -> AGENT25 | C91: =L91 -> KAHAYAN_KUALA | D91: =K91 -> PUP02 | H91: =P91 -> 2026-09-01 14:59:44 | K91: {=_xlfn.TEXTSPLIT(R91," ")} -> PUP02 | L91: KAHAYAN_KUALA | P91: 2026-09-01 14:59:44 | Q91: 6660025 AGENT25 | R91: PUP02 KAHAYAN_KUALA | S91: PUP02000004 | T91: Selvia | U91: obaforever/idnztapp/meeting/20260901/upload_17882495770311fb018432bed495aaeb74a8eea2128c6.mp4
A92: =INT(H92) -> 46266 | B92: =RIGHT(Q92,7) -> AGENT19 | C92: =L92 -> RAYA_TENGGILIS | D92: =K92 -> SUB57 | H92: =P92 -> 2026-09-01 14:58:17 | K92: {=_xlfn.TEXTSPLIT(R92," ")} -> SUB57 | L92: RAYA_TENGGILIS | P92: 2026-09-01 14:58:17 | Q92: 6660019 AGENT19 | R92: SUB57 RAYA_TENGGILIS | S92: SUB57000010 | T92: Miko JM0510012 | U92: obaforever/idnztapp/meeting/20260901/upload_178824947762525dd761587a94f839222e2a619e2f852.MOV | V92: briefing korlap target awal bulan
A93: =INT(H93) -> 46266 | B93: =RIGHT(Q93,7) -> AGENT19 | C93: =L93 -> WRINGINANOM | D93: =K93 -> GSK15 | H93: =P93 -> 2026-09-01 14:58:17 | K93: {=_xlfn.TEXTSPLIT(R93," ")} -> GSK15 | L93: WRINGINANOM | P93: 2026-09-01 14:58:17 | Q93: 6660019 AGENT19 | R93: GSK15 WRINGINANOM | S93: LS0000372541 | T93: Ardyanita J07240624 | U93: obaforever/idnztapp/meeting/20260901/upload_1788249427856a9b3847247c746f898fe52e637dd9c53.mp4 | V93: Paket HV, parcel Care.
A94: =INT(H94) -> 46266 | B94: =RIGHT(Q94,7) -> AGENT14 | C94: =L94 -> DRAMAGA_2 | D94: =K94 -> CIB08A | H94: =P94 -> 2026-09-01 14:58:01 | K94: {=_xlfn.TEXTSPLIT(R94," ")} -> CIB08A | L94: DRAMAGA_2 | P94: 2026-09-01 14:58:01 | Q94: 6660014 AGENT14 | R94: CIB08A DRAMAGA_2 | S94: 00571761 | T94: Mochamad Firmansyah | U94: obaforever/idnztapp/meeting/20260901/upload_17882494553802f6254e40d5c45ddacc6134f04c8f387.mp4 | V94: edukasi perihal tanggung jawab pekerjaan
A95: =INT(H95) -> 46266 | B95: =RIGHT(Q95,7) -> AGENT19 | C95: =L95 -> KALI_RUNGKUT_1 | D95: =K95 -> SUB19E | H95: =P95 -> 2026-09-01 14:57:17 | K95: {=_xlfn.TEXTSPLIT(R95," ")} -> SUB19E | L95: KALI_RUNGKUT_1 | P95: 2026-09-01 14:57:17 | Q95: 6660019 AGENT19 | R95: SUB19E KALI_RUNGKUT_1 | S95: SUB19E000001 | T95: Sujatmiko JM0510012 | U95: obaforever/idnztapp/meeting/20260901/upload_1788249418729a2dbf8619a7d4f46971294c4a1e7f938.MOV | V95: briefing korlap target awal bulan
A96: =INT(H96) -> 46266 | B96: =RIGHT(Q96,7) -> AGENT13 | C96: =L96 -> BINTARA_JAYA_01 | D96: =K96 -> BKI08F | H96: =P96 -> 2026-09-01 14:56:16 | K96: {=_xlfn.TEXTSPLIT(R96," ")} -> BKI08F | L96: BINTARA_JAYA_01 | P96: 2026-09-01 14:56:16 | Q96: 6660013 AGENT13 | R96: BKI08F BINTARA_JAYA_01 | S96: BKI08F000001 | T96: Angga Kusuma | U96: obaforever/idnztapp/meeting/20260901/upload_17882493714106c82018ae29747f1a22f85a886470f59.mp4
A97: =INT(H97) -> 46266 | B97: =RIGHT(Q97,7) -> AGENT16 | C97: =L97 -> GRT27B | D97: =K97 -> GRT27B | H97: =P97 -> 2026-09-01 14:56:08 | K97: {=_xlfn.TEXTSPLIT(R97," ")} -> GRT27B | L97: GRT27B | P97: 2026-09-01 14:56:08 | Q97: 6660016 AGENT16 | R97: GRT27B GRT27B | S97: LS0000415074 | T97: Adi Firmansyah | U97: obaforever/idnztapp/meeting/20260901/upload_17882493262689c98bcd29ea9411eb5f9bc8a719af732.MOV | V97: indikator rating sprinter
A98: =INT(H98) -> 46266 | B98: =RIGHT(Q98,7) -> AGENT16 | C98: =L98 -> SUM22 | D98: =K98 -> SUM22 | H98: =P98 -> 2026-09-01 14:55:59 | K98: {=_xlfn.TEXTSPLIT(R98," ")} -> SUM22 | L98: SUM22 | P98: 2026-09-01 14:55:59 | Q98: 6660016 AGENT16 | R98: SUM22 SUM22 | S98: LS0000415176 | T98: Rudi Hermawan | U98: obaforever/idnztapp/meeting/20260901/upload_17882493520632f726ac417b74dd6aa9b52a4479aeb4a.mp4
A99: =INT(H99) -> 46266 | B99: =RIGHT(Q99,7) -> AGENT16 | C99: =L99 -> PER17A | D99: =K99 -> PER17A | H99: =P99 -> 2026-09-01 14:55:04 | K99: {=_xlfn.TEXTSPLIT(R99," ")} -> PER17A | L99: PER17A | P99: 2026-09-01 14:55:04 | Q99: 6660016 AGENT16 | R99: PER17A PER17A | S99: LS0000415198 | T99: Rendi Muhamad | U99: obaforever/idnztapp/meeting/20260901/upload_178824924036915cd1e8860f047f5ab8cc95e58b961a3.mp4 | V99: ttd jam 12
A100: =INT(H100) -> 46266 | B100: =RIGHT(Q100,7) -> AGENT19 | C100: =L100 -> DC_SRATU | D100: =K100 -> BJE07 | H100: =P100 -> 2026-09-01 14:54:44 | K100: {=_xlfn.TEXTSPLIT(R100," ")} -> BJE07 | L100: DC_SRATU | P100: 2026-09-01 14:54:44 | Q100: 6660019 AGENT19 | R100: BJE07 DC_SRATU | S100: 00552162 | T100: Ali Subeki | U100: obaforever/idnztapp/meeting/20260901/upload_1788249259677d3207fc1ef094e4292a8d48edc268c4f.mp4 | V100: regular
...

Sheet Raw data yang sudah upload
A1: Tanggal upload fin | B1: Kode Agent 代理区代码 | C1: Nama Drop Point 网点名称 | D1: Kode Drop Point 网点代码 | E1: Video Briefing 班前例会视频 | F1: Summary Briefing 会议要点总结 | G1: Kategori Materi | H1: Tanggal Upload 上传日期 | I1: Sprinter Ikut breifing hari ini | J1: Total Sprinter | K1: created by | L1: status | M1: Last Modified Date 2 | N1: feedback DP | O1: total DP | W1: Status DP | X1: Sebelum 15:00
A2: 46266 | B2: AGENT23 | C2: MASOHI | D2: MSI01 | E2: 2026-09-01 06.34.05_.mp4 | F2: POD VALID DAN MARKETING | G2: Marketing | H2: 46266.194 | I2: 8 | J2: 16 | K2: Amina Abd. Khair | M2: 46266.194 | N2: Masih | O2: 175 | W2: =_xlfn.XLOOKUP(D2,'All DP'!B:B,'All DP'!D:D,"Tidak") -> Masih | X2: =IFERROR(IF(MOD(H2,1)<=TIME(15,0,0),"YA","TIDAK"),0) -> YA
A3: 46266 | B3: AGENT23 | C3: WAEAPO | D3: NAM02 | E3: 1ac716247d7932dbfa26a61de418409e.jpg | F3: BRIFING DP NAM02 1 AGUSTUS 2026 - RITASE - PAYCOOLS - E POD - POD RETUR VALID - ARBITRASE - LONG TAIL - TIKET PLATFROM - PARCEL CARE - DENDA HQ | G3: other | H3: 46266.196 | I3: 5 | J3: 10 | K3: Marselinus Tehe | M3: 46266.196 | N3: Masih | O3: 175 | W3: =_xlfn.XLOOKUP(D3,'All DP'!B:B,'All DP'!D:D,"Tidak") -> Masih | X3: =IFERROR(IF(MOD(H3,1)<=TIME(15,0,0),"YA","TIDAK"),0) -> YA
A4: 46266 | B4: AGENT23 | C4: GEMBA | D4: PRU02 | E4: BREFING.jpeg | F4: BREAFING GEMBA TGL 01 September 2026 1. PUSH TTD KEJAR RITASE > 90% 2. PEMBAYARAN PAYCOOLS 3. EPOD HARUS VALID 92% 4. KODE KETIGA 5. RETUR DGN POD VALID 6. KEBERSIHAN DP 7. PENGGUNAAN KODE QR DP & SPRINTER 8. SOP MENGANTAR 9.PARCEL CARE | G4: Marketing | H4: 46266.213 | I4: 3 | J4: 3 | K4: Dewi Sriyanti Seipalla | M4: 46266.213 | N4: Masih | O4: 175 | W4: =_xlfn.XLOOKUP(D4,'All DP'!B:B,'All DP'!D:D,"Tidak") -> Masih | X4: =IFERROR(IF(MOD(H4,1)<=TIME(15,0,0),"YA","TIDAK"),0) -> YA
A5: 46266 | B5: AGENT23 | C5: LABUHA | D5: LAH01 | E5: 2026-09-01 06.46.11__(Judul-Absensi).mp4 | F5: 1. Absensi sebelum jam 6:30 2. Delivery sebelum jam 12 3. Tidak boleh tahan paket diatas 3 hari Jaga kebersihan dp 4. Terapkan 3S | G5: other | H5: 46266.227 | I5: 21 | J5: 25 | K5: Rifaldi Sanaba | M5: 46266.227 | N5: Masih | O5: 175 | W5: =_xlfn.XLOOKUP(D5,'All DP'!B:B,'All DP'!D:D,"Tidak") -> Masih | X5: =IFERROR(IF(MOD(H5,1)<=TIME(15,0,0),"YA","TIDAK"),0) -> YA
A6: 46266 | B6: AGENT23 | C6: GALALA | D6: AMQ07 | E6: 2026-09-01 07.20.44_Jalan Jenderal Sudirman_(Pemeriksa-DP AMQ07_GALALA).jpg | F6: BRIEFING PAGI AMQ07 GALALA 1 SEPTEMBER 2026 ABSEN 6.30 PUSH TTD JAM 12 LONGTAIL PARCEL CARE POD RETUR DAN PU VALID PUSH PAYCOOLS | G6: other | H6: 46266.229 | I6: 23 | J6: 24 | K6: Zulfikry Ramadhan Ismail | M6: 46266.229 | N6: Masih | O6: 175 | W6: =_xlfn.XLOOKUP(D6,'All DP'!B:B,'All DP'!D:D,"Tidak") -> Masih | X6: =IFERROR(IF(MOD(H6,1)<=TIME(15,0,0),"YA","TIDAK"),0) -> YA
A7: 46266 | B7: AGENT23 | C7: BOBONG | D7: BOB01 | E7: 20260901_70848AMByGPSMapCamera.jpg | F7: *GROOMING & BRIEFING BOBONG* Pembahasan. ->Push TTD ->TTD REAL TIME ->Di perhatikan paket yg stuck. ->Jujur dalam berkerja. ->Disiplin dgn waktu. ->Penambahan SDM | G7: other | H7: 46266.234 | I7: 1 | J7: 1 | K7: Farisal Irawan | M7: 46266.234 | N7: Masih | O7: 175 | W7: =_xlfn.XLOOKUP(D7,'All DP'!B:B,'All DP'!D:D,"Tidak") -> Masih | X7: =IFERROR(IF(MOD(H7,1)<=TIME(15,0,0),"YA","TIDAK"),0) -> YA
A8: 46266 | B8: AGENT23 | C8: PAGUYAMAN | D8: LBO02 | E8: 2026-09-01 06.32.23_.mp4 | F8: PUSH 6.30 PUSH QR SPRINTER PUSH TTD/RITASE | G8: Marketing | H8: 46266.234 | I8: 7 | J8: 8 | K8: Alvian Ahmad | M8: 46266.234 | N8: Masih | O8: 175 | W8: =_xlfn.XLOOKUP(D8,'All DP'!B:B,'All DP'!D:D,"Tidak") -> Masih | X8: =IFERROR(IF(MOD(H8,1)<=TIME(15,0,0),"YA","TIDAK"),0) -> YA
A9: 46266 | B9: AGENT23 | C9: DONGGALA | D9: DON01 | E9: 2026-09-01 06.33.10_Jalan Pettalolo_(Judul-DP DON01).jpg | F9: ABSENSI PUSH TTD PAYCOOLS POD VALID LONGTAIL QR SPRINTER | G9: Marketing | H9: 46266.235 | I9: 10 | J9: 17 | K9: Zainuddin . | M9: 46266.236 | N9: Masih | O9: 175 | W9: =_xlfn.XLOOKUP(D9,'All DP'!B:B,'All DP'!D:D,"Tidak") -> Masih | X9: =IFERROR(IF(MOD(H9,1)<=TIME(15,0,0),"YA","TIDAK"),0) -> YA
A10: 46266 | B10: AGENT23 | C10: KEBUN_CENGKEH | D10: AMQ02 | E10: 20260901-053848.jpg | F10: 1. QUIZ APP SPRINTER 2. PUSH ABSENSI 06.30 3. PICK-UP 4. SIMPANG GUDANG POD VALID 5. KELUAR 07.30 DAN TTD JAM 12.00 6. PAYCOOLS & GOPAY 7. LONGTAIL | G10: other | H10: 46266.239 | I10: 4 | J10: 20 | K10: Fahbi Safitri | M10: 46266.239 | N10: Masih | O10: 175 | W10: =_xlfn.XLOOKUP(D10,'All DP'!B:B,'All DP'!D:D,"Tidak") -> Masih | X10: =IFERROR(IF(MOD(H10,1)<=TIME(15,0,0),"YA","TIDAK"),0) -> YA
A11: 46266 | B11: AGENT23 | C11: FALAJAWA2 | D11: TTE05 | E11: WhatsApp Video 2026-09-01 at 07.46.25.mp4 | F11: PUSH KPI | G11: other | H11: 46266.244 | I11: 2 | J11: 3 | K11: Fadila Samsudin | M11: 46266.244 | N11: Masih | O11: 175 | W11: =_xlfn.XLOOKUP(D11,'All DP'!B:B,'All DP'!D:D,"Tidak") -> Masih | X11: =IFERROR(IF(MOD(H11,1)<=TIME(15,0,0),"YA","TIDAK"),0) -> YA
A12: 46266 | B12: AGENT23 | C12: SOJOL | D12: DON13 | E12: IMG-20260901-WA0003(1).jpg | F12: Awb HV,pod, simpan gudang, ujian sprinter | G12: Marketing | H12: 46266.244 | I12: 5 | J12: 5 | K12: Memet . | M12: 46266.244 | N12: Masih | O12: 175 | W12: =_xlfn.XLOOKUP(D12,'All DP'!B:B,'All DP'!D:D,"Tidak") -> Masih | X12: =IFERROR(IF(MOD(H12,1)<=TIME(15,0,0),"YA","TIDAK"),0) -> YA
A13: 46266 | B13: AGENT21 | C13: KETEWEL | D13: GIA01B | E13: 20260901_64122AMByGPSMapCamera.mp4 | F13: brifing tentang TTD paksa T7 keatas | G13: other | H13: 46266.245 | I13: 19 | J13: 26 | K13: Rifqi Al'Afif Ramadhan | M13: 46266.245 | N13: Masih | O13: 176 | W13: =_xlfn.XLOOKUP(D13,'All DP'!B:B,'All DP'!D:D,"Tidak") -> Masih | X13: =IFERROR(IF(MOD(H13,1)<=TIME(15,0,0),"YA","TIDAK"),0) -> YA
... A17: 46266 | B17: AGENT23 | C17: TUAL | D17: UAL01 | E17: 2026-09-01 07.14.34_Jalan Doktor Leimena_(Judul-Visit)_(Catatan-Kunjungan Harian).jpg | F17: Push TTD sebelum jam 12 Push paycools Push satu sprinter satu pickupan | G17: Marketing | H17: 46266.252 | I17: 6 | J17: 8 | K17: Kufra Ahmad Toha Rery | M17: 46266.252 | N17: Masih | O17: 175 | W17: =_xlfn.XLOOKUP(D17,'All DP'!B:B,'All DP'!D:D,"Tidak") -> Masih | X17: =IFERROR(IF(MOD(H17,1)<=TIME(15,0,0),"YA","TIDAK"),0) -> YA
A18: 46266 | B18: AGENT22 | C18: PEKKABATA | D18: PRR02 | E18: VID-20260901-WA0051.mp4 | F18: Absensi Quis app Paket longtail | G18: other | H18: 46266.252 | I18: 11 | J18: 16 | K18: Rusli At | M18: 46266.253 | O18: 148 | W18: =_xlfn.XLOOKUP(D18,'All DP'!B:B,'All DP'!D:D,"Tidak") -> Masih | X18: =IFERROR(IF(MOD(H18,1)<=TIME(15,0,0),"YA","TIDAK"),0) -> YA
A19: 46266 | B19: AGENT23 | C19: BONE_PANTAI | D19: SUW02 | E19: 2026-09-01 06.46.43_.jpg | F19: ABESENSI 06.30, TTD SEBELUM JAM 12 | G19: other | H19: 46266.254 | I19: 5 | J19: 9 | K19: Arya Yoga Pangestu | M19: 46266.254 | N19: Masih | O19: 175 | W19: =_xlfn.XLOOKUP(D19,'All DP'!B:B,'All DP'!D:D,"Tidak") -> Masih | X19: =IFERROR(IF(MOD(H19,1)<=TIME(15,0,0),"YA","TIDAK"),0) -> YA
A20: 46266 | B20: AGENT23 | C20: MABA | D20: MAB01 | E20: 2026-09-01 07.42.55_Maba Sangaji.JPEG | F20: QR SPRINTER (mkt) ptmp, stuck (NM) | G20: Marketing | H20: 46266.257 | I20: 10 | J20: 6 | K20: Hardi . | M20: 46266.257 | N20: Masih | O20: 175 | W20: =_xlfn.XLOOKUP(D20,'All DP'!B:B,'All DP'!D:D,"Tidak") -> Masih | X20: =IFERROR(IF(MOD(H20,1)<=TIME(15,0,0),"YA","TIDAK"),0) -> YA
A21: 46266 | B21: AGENT23 | C21: AMPIBABO | D21: PII04 | E21: BRIFING PAGI.jpg | F21: PUSH PAKET LONGTAIL ABSENSI TIKTOK REVERSE | G21: other | H21: 46266.257 | I21: 4 | J21: 9 | K21: Nurhaliza . | M21: 46266.257 | N21: Masih | O21: 175 | W21: =_xlfn.XLOOKUP(D21,'All DP'!B:B,'All DP'!D:D,"Tidak") -> Masih | X21: =IFERROR(IF(MOD(H21,1)<=TIME(15,0,0),"YA","TIDAK"),0) -> YA
A22: 46266 | B22: AGENT23 | C22: DIMEMBE | D22: AID02A | E22: 2026-09-01_06.51.38_Jalan_Sukur_-_Likupang_(Company-J&T_Express)[1].jpg | F22: END STATUS, POD | G22: other | H22: 46266.257 | I22: 4 | J22: 9 | K22: Febrika Falensia Effendie | M22: 46266.257 | O22: 175 | W22: =_xlfn.XLOOKUP(D22,'All DP'!B:B,'All DP'!D:D,"Tidak") -> Masih | X22: =IFERROR(IF(MOD(H22,1)<=TIME(15,0,0),"YA","TIDAK"),0) -> YA
A23: 46266 | B23: AGENT22 | C23: BENU_BENUA | D23: KDI11 | E23: 2026-09-01 07.03.32_Jnt Benu Benua.jpeg | F23: memaksimalkan paket di dp mengedukasikan untuk datang lebih awal agar keluar delivery lebih awal juga hati2 saat berkendara mengedukasikan uktuk menggunakan pod valid pada saat meretur dan gagal pick up paket | G23: other | H23: 46266.257 | I23: 15 | J23: 19 | K23: Fitra Chalik | M23: 46266.257 | O23: 148 | W23: =_xlfn.XLOOKUP(D23,'All DP'!B:B,'All DP'!D:D,"Tidak") -> Masih | X23: =IFERROR(IF(MOD(H23,1)<=TIME(15,0,0),"YA","TIDAK"),0) -> YA
A24: 46266 | B24: AGENT23 | C24: TENTENA | D24: PSJ02 | E24: IMG_4724.JPEG | F24: 1. PARCEL CARE 2. KEBERSIHAN DP 3. PUSH TTD SEBELUM JAM 12 4. POD VALID 5. POD RETUR 6. PELAYANAN DP 7. MAKSIMALKAN PAKET 8. PICKUP QR SPRINTER 9. ABSENSI 6.30 | G24: Marketing | H24: 46266.257 | I24: 11 | J24: 11 | K24: Stefi Landika | M24: 46266.258 | N24: Masih | O24: 175 | W24: =_xlfn.XLOOKUP(D24,'All DP'!B:B,'All DP'!D:D,"Tidak") -> Masih | X24: =IFERROR(IF(MOD(H24,1)<=TIME(15,0,0),"YA","TIDAK"),0) -> YA
A25: 46266 | B25: AGENT28 | C25: MERAUKE | D25: MKQ01 | E25: TimePhoto_20260901_075908.jpg | F25: paket lontail dan paket priofitas | G25: other | H25: 46266.258 | I25: 19 | J25: 3 | K25: Pengguna Tamu 46219 | M25: 46266.258 | O25: 13 | W25: =_xlfn.XLOOKUP(D25,'All DP'!B:B,'All DP'!D:D,"Tidak") -> Masih | X25: =IFERROR(IF(MOD(H25,1)<=TIME(15,0,0),"YA","TIDAK"),0) -> YA
A26: 46266 | B26: AGENT22 | C26: NGAPA | D26: LAS02 | E26: hasil_LAS02_1788217968721.mp4 | F26: pod, absensi, delivery jam 07.30 | G26: other | H26: 46266.261 | I26: 13 | J26: 15 | K26: Pengguna Tamu 90586 | M26: 46266.261 | O26: 148 | W26: =_xlfn.XLOOKUP(D26,'All DP'!B:B,'All DP'!D:D,"Tidak") -> Masih | X26: =IFERROR(IF(MOD(H26,1)<=TIME(15,0,0),"YA","TIDAK"),0) -> YA
A27: 46266 | B27: AGENT23 | C27: MADIDIR | D27: BIT03 | E27: WhatsApp Image 2026-09-01 at 07.04.35.jpeg,WhatsApp Video 2026-09-01 at 07.06.30.mp4 | F27: LONG TAIL TTD JAM 12 ABSENSI KEBERSIHAN | G27: other | H27: 46266.261 | I27: 23 | J27: 23 | K27: Anglie Meihua Lim | M27: 46266.261 | N27: Masih | O27: 175 | W27: =_xlfn.XLOOKUP(D27,'All DP'!B:B,'All DP'!D:D,"Tidak") -> Masih | X27: =IFERROR(IF(MOD(H27,1)<=TIME(15,0,0),"YA","TIDAK"),0) -> YA
A28: 46266 | B28: AGENT21 | C28: SEMINYAK_1 | D28: MGW04C | E28: b1ddf51b-73cb-4ea1-a651-99ab727fd3e8.mp4 | F28: Longtail | G28: other | H28: 46266.261 | I28: 40 | J28: 50 | K28: Diana Ursula Wati | M28: 46266.261 | N28: Masih | O28: 176 | W28: =_xlfn.XLOOKUP(D28,'All DP'!B:B,'All DP'!D:D,"Tidak") -> Masih | X28: =IFERROR(IF(MOD(H28,1)<=TIME(15,0,0),"YA","TIDAK"),0) -> YA
A29: 46266 | B29: AGENT22 | C29: TINANGGEA | D29: WAG21 | E29: 2026-09-01 07.13.58_Jalan Poros Lapulu_(TINANGGEA).jpg | F29: pod Ttd absen | G29: other | H29: 46266.261 | I29: 18 | J29: 18 | K29: Sutarno . | M29: 46266.261 | O29: 148 | W29: =_xlfn.XLOOKUP(D29,'All DP'!B:B,'All DP'!D:D,"Tidak") -> Masih | X29: =IFERROR(IF(MOD(H29,1)<=TIME(15,0,0),"YA","TIDAK"),0) -> YA
A30: 46266 | B30: AGENT23 | C30: KAKASKASEN | D30: TMH02 | E30: img_v3_02154_e328b5c8-c7cd-4eec-8fc6-d2f54ec1e2hu.jpg | F30: POD PARCELCARE QR SPRINTER/DP PAYCOOLS LONGTAIL KEBERSIHAN | G30: Marketing | H30: 46266.262 | I30: 13 | J30: 20 | K30: Anggreyni Marini Marentek | M30: 46266.262 | N30: Masih | O30: 175 | W30: =_xlfn.XLOOKUP(D30,'All DP'!B:B,'All DP'!D:D,"Tidak") -> Masih | X30: =IFERROR(IF(MOD(H30,1)<=TIME(15,0,0),"YA","TIDAK"),0) -> YA
A31: 46266 | B31: AGENT23 | C31: SOFIFI | D31: TID02 | E31: VID-20260901-WA0006.mp4 | F31: PAKET 3 HARI STORAN | G31: other | H31: 46266.264 | I31: 12 | J31: 20 | K31: Karmila Gorotomole | M31: 46266.264 | N31: Masih | O31: 175 | W31: =_xlfn.XLOOKUP(D31,'All DP'!B:B,'All DP'!D:D,"Tidak") -> Masih | X31: =IFERROR(IF(MOD(H31,1)<=TIME(15,0,0),"YA","TIDAK"),0) -> YA
A32: 46266 | B32: AGENT22 | C32: BALANIPA | D32: PWX03 | E32: IMG-20260901-WA0021.jpg | F32: Target pick up dan pod retur | G32: other | H32: 46266.264 | I32: 18 | J32: 28 | K32: Wahyu . | M32: 46266.264 | O32: 148 | W32: =_xlfn.XLOOKUP(D32,'All DP'!B:B,'All DP'!D:D,"Tidak") -> Masih | X32: =IFERROR(IF(MOD(H32,1)<=TIME(15,0,0),"YA","TIDAK"),0) -> YA
A33: 46266 | B33: AGENT18 | C33: NGAGLIK | D33: SLM03 | E33: aa0c843b-4be0-42dd-9224-5dafa88ce718.JPEG | F33: ttd jam 12 | G33: other | H33: 46266.266 | I33: 7 | J33: 23 | K33: Soeko Wicaksono Novianto | M33: 46266.266 | N33: Masih | O33: 129 | W33: =_xlfn.XLOOKUP(D33,'All DP'!B:B,'All DP'!D:D,"Tidak") -> Masih | X33: =IFERROR(IF(MOD(H33,1)<=TIME(15,0,0),"YA","TIDAK"),0) -> YA
A34: 46266 | B34: AGENT21 | C34: NEGARA_1 | D34: NRG01A | E34: 20260901_71748AMByGPSMapCamera.mp4 | F34: mengenai paket yang sudah 3 hari dan simpan gudang atau paket bermasalah | G34: other | H34: 46266.266 | I34: 30 | J34: 45 | K34: Pengguna Tamu 95133 | M34: 46266.266 | N34: Masih | O34: 176 | W34: =_xlfn.XLOOKUP(D34,'All DP'!B:B,'All DP'!D:D,"Tidak") -> Masih | X34: =IFERROR(IF(MOD(H34,1)<=TIME(15,0,0),"YA","TIDAK"),0) -> YA
A35: 46266 | B35: AGENT27 | C35: SAMARINDA | D35: SRI01 | E35: 2026-09-01 07.23.24_Citraland City.jpeg | F35: ttd sblm jm12 | G35: other | H35: 46266.267 | I35: 4 | J35: 21 | K35: Pengguna Tamu 68821 | M35: 46266.267 | O35: 165 | W35: =_xlfn.XLOOKUP(D35,'All DP'!B:B,'All DP'!D:D,"Tidak") -> Masih | X35: =IFERROR(IF(MOD(H35,1)<=TIME(15,0,0),"YA","TIDAK"),0) -> YA
A36: 46266 | B36: AGENT22 | C36: MAKASSAR | D36: UPG01 | E36: 2026-09-01 7.12.33 AM_Jalan Veteran Selatan No. 64.mp4 | F36: POD Scan Bermasalah | G36: other | H36: 46266.268 | I36: 7 | J36: 31 | K36: Guest User 21841 | M36: 46266.268 | O36: 148 | W36: =_xlfn.XLOOKUP(D36,'All DP'!B:B,'All DP'!D:D,"Tidak") -> Masih | X36: =IFERROR(IF(MOD(H36,1)<=TIME(15,0,0),"YA","TIDAK"),0) -> YA
A37: 46266 | B37: AGENT23 | C37: TOMPASO_BARU | D37: AMR16 | E37: 2026-09-01 07.09.58_.jpg | F37: ABSENSI SLA TTD SSEBELUM JAM 12 PEYCOLS | G37: other | H37: 46266.269 | I37: 5 | J37: 11 | K37: Cinta Celsi Tarumingkeng | M37: 46266.269 | N37: Masih | O37: 175 | W37: =_xlfn.XLOOKUP(D37,'All DP'!B:B,'All DP'!D:D,"Tidak") -> Masih | X37: =IFERROR(IF(MOD(H37,1)<=TIME(15,0,0),"YA","TIDAK"),0) -> YA
A38: 46266 | B38: AGENT21 | C38: JEMBRANA | D38: NRG03A | E38: WhatsApp Video 2026-09-01 at 06.25.40.mp4 | F38: SHARING SPRINTER BINTANG 5 PENILAIAN CUSTOMER DI APP CUSTOMER | G38: Marketing | H38: 46266.269 | I38: 18 | J38: 19 | K38: Eni Maryana | M38: 46266.269 | N38: Masih | O38: 176 | W38: =_xlfn.XLOOKUP(D38,'All DP'!B:B,'All DP'!D:D,"Tidak") -> Masih | X38: =IFERROR(IF(MOD(H38,1)<=TIME(15,0,0),"YA","TIDAK"),0) -> YA
A39: 46266 | B39: AGENT22 | C39: WUNDULAKO | D39: KOL05 | E39: 2026-09-01 07.16.56_.mp4 | F39: memaksimalkanp | G39: other | H39: 46266.271 | I39: 8 | J39: 9 | K39: Irpandi . | M39: 46266.271 | O39: 148 | W39: =_xlfn.XLOOKUP(D39,'All DP'!B:B,'All DP'!D:D,"Tidak") -> Masih | X39: =IFERROR(IF(MOD(H39,1)<=TIME(15,0,0),"YA","TIDAK"),0) -> YA
A40: 46266 | B40: AGENT22 | C40: KADIA | D40: KDI02 | E40: WhatsApp Image 2026-09-01 at 06.29.32.jpeg | F40: 1awb perhari | G40: Marketing | H40: 46266.272 | I40: 23 | J40: 26 | K40: Andi Fachri Ramadhan | M40: 46266.273 | O40: 148 | W40: =_xlfn.XLOOKUP(D40,'All DP'!B:B,'All DP'!D:D,"Tidak") -> Masih | X40: =IFERROR(IF(MOD(H40,1)<=TIME(15,0,0),"YA","TIDAK"),0) -> YA
A41: 46266 | B41: AGENT19 | C41: DC_PORONG | D41: SDA24 | E41: 2026-09-01 06.29.42_No.447, Jalan Bhayangkari.jpg,2026-09-01 06.29.45_No.447, Jalan Bhayangkari.mp4 | F41: SDA JAM 12 TARGET LEGULER KEDATANGAN | G41: other | H41: 46266.273 | I41: 50 | J41: 56 | K41: fandi rakhmad_SDA24 | M41: 46266.273 | N41: Masih | O41: 365 | W41: =_xlfn.XLOOKUP(D41,'All DP'!B:B,'All DP'!D:D,"Tidak") -> Masih | X41: =IFERROR(IF(MOD(H41,1)<=TIME(15,0,0),"YA","TIDAK"),0) -> YA
A42: 46266 | B42: AGENT21 | C42: NUSA_PENIDA | D42: KKL03 | E42: 1 September.mp4 | F42: Briefing pagi : Menyampaikan materi briefing sesuai ketentuan HQ yang dibagi menjadi 3 section. | G42: other | H42: 46266.275 | I42: 26 | J42: 27 | K42: I Dewa Made Dwipayana | M42: 46266.275 | N42: Masih | O42: 176 | W42: =_xlfn.XLOOKUP(D42,'All DP'!B:B,'All DP'!D:D,"Tidak") -> Masih | X42: =IFERROR(IF(MOD(H42,1)<=TIME(15,0,0),"YA","TIDAK"),0) -> YA
A43: 46266 | B43: AGENT40 | C43: CP_PULO_GADUNG | D43: JKT57G | E43: image.png | F43: brifing pagi cp pulo gadung absen 6.30 keluar gudang 7.30 ttd jam 12.00 dan all ritase longtail, paket stuck penanganan paket DG qr sprinter kejar dari awal bulan dan juga prospek pelanggan vip evaluasi pencapaian agustus | G43: Marketing | H43: 46266.276 | I43: 147 | J43: 155 | K43: Arman Suryadi | M43: 46266.276 | O43: 73 | W43: =_xlfn.XLOOKUP(D43,'All DP'!B:B,'All DP'!D:D,"Tidak") -> Masih | X43: =IFERROR(IF(MOD(H43,1)<=TIME(15,0,0),"YA","TIDAK"),0) -> YA
A44: 46266 | B44: AGENT40 | C44: CP_TANJUNG_DUREN_2 | D44: JKT39O | E44: 2026-09-01 06.29.58_No. 118, Jalan Daan Mogot.jpg,2026-09-01 06.30.01_No. 118, Jalan Daan Mogot.mp4 | F44: .Brifing pagi cp tanjung duren raya .masuk 06.30 pagi .keluar gudang 07.30 .TTD JAM 12 .TTD ALL RITASE . Sosialisasi paket barang barang DG . Kebersihan lingkungan kerja .pod retur valid | G44: other | H44: 46266.277 | I44: 79 | J44: 88 | K44: Retno Pratama | M44: 46266.277 | N44: Masih | O44: 73 | W44: =_xlfn.XLOOKUP(D44,'All DP'!B:B,'All DP'!D:D,"Tidak") -> Masih | X44: =IFERROR(IF(MOD(H44,1)<=TIME(15,0,0),"YA","TIDAK"),0) -> YA
A45: 46266 | B45: AGENT23 | C45: BOROKO | D45: BRK01 | E45: IMG_1287.jpeg | F45: ABSENSI LONGTAIL RITASE QR SPRINTER | G45: Marketing | H45: 46266.277 | I45: 10 | J45: 6 | K45: Pengguna Tamu 74791 | M45: 46266.277 | N45: Masih | O45: 175 | W45: =_xlfn.XLOOKUP(D45,'All DP'!B:B,'All DP'!D:D,"Tidak") -> Masih | X45: =IFERROR(IF(MOD(H45,1)<=TIME(15,0,0),"YA","TIDAK"),0) -> YA
A46: 46266 | B46: AGENT40 | C46: TEBET | D46: JKT25 | E46: image.png | F46: - ABSENSI KEHADIRAN - QR SPRINTER - PICKUP REGULER - RIMENDER PAKET DG/DILARANG KIRIM - POD VALID - TTD JAM 12&ALLRITASE - KELUAR GUDANG 07.30 | G46: Marketing | H46: 46266.278 | I46: 92 | J46: 133 | K46: Muhamad Faisal | M46: 46266.278 | N46: Masih | O46: 73 | W46: =_xlfn.XLOOKUP(D46,'All DP'!B:B,'All DP'!D:D,"Tidak") -> Masih | X46: =IFERROR(IF(MOD(H46,1)<=TIME(15,0,0),"YA","TIDAK"),0) -> YA
A47: 46266 | B47: AGENT23 | C47: DAMPAL | D47: TLI04 | E47: WhatsApp Video 2026-09-01 at 06.10.25.mp4,WhatsApp Image 2026-09-01 at 06.10.22.jpeg | F47: tli04 dampal tgl 1/9/2026 penggunaan paycools ttd realtime pod valid longtail | G47: other | H47: 46266.278 | I47: 7 | J47: 12 | K47: Nurul Istiqamah | M47: 46266.278 | N47: Masih | O47: 175 | W47: =_xlfn.XLOOKUP(D47,'All DP'!B:B,'All DP'!D:D,"Tidak") -> Masih | X47: =IFERROR(IF(MOD(H47,1)<=TIME(15,0,0),"YA","TIDAK"),0) -> YA
A48: 46266 | B48: AGENT23 | C48: KALAWAT | D48: AID02 | E48: WhatsApp Video 2026-09-01 at 06.37.51.mp4 | F48: MAKSIMALKAN TTD SEBLUM JAM 12 | G48: other | H48: 46266.279 | I48: 15 | J48: 15 | K48: Ariandani Musbar Norcahayanto | M48: 46266.279 | N48: Masih | O48: 175 | W48: =_xlfn.XLOOKUP(D48,'All DP'!B:B,'All DP'!D:D,"Tidak") -> Masih | X48: =IFERROR(IF(MOD(H48,1)<=TIME(15,0,0),"YA","TIDAK"),0) -> YA
A49: 46266 | B49: AGENT40 | C49: MERUYA_UTARA | D49: JKT02Q | E49: TimePhoto_20260901_063457.jpg | F49: Briefing DC Meruya Utara - Keluar gudang 07.30 - Absensi 06.30 - TTD 12.00 - TTD all ritase - QR Sprinter - CODFD - Dangerous Goods - POD Valid | G49: Marketing | H49: 46266.279 | I49: 51 | J49: 60 | K49: Raka Fahrizki | M49: 46266.279 | N49: Tidak | O49: 73 | W49: =_xlfn.XLOOKUP(D49,'All DP'!B:B,'All DP'!D:D,"Tidak") -> Masih | X49: =IFERROR(IF(MOD(H49,1)<=TIME(15,0,0),"YA","TIDAK"),0) -> YA
A50: 46266 | B50: AGENT40 | C50: KAMAL_MUARA | D50: JKT08L | E50: 20260901-064225.jpg | F50: Brifing pagi DC kamal muara - Ketepatan absensi 06:30 target 90% - Keluar gudang 07:30 - TTD real-time sebelum jam 12:00 90% ( Balik rit sebelum jam 12, simgud paket bermasalah dengan POD Valid) - Pickup QR Sprinter 1 Hari 1 Awb - Sosialisasi mengenai barang dilarang kirim | G50: Marketing | H50: 46266.28 | I50: 37 | J50: 37 | K50: Fikri Gilang P JKT-08L | M50: 46266.28 | N50: Masih | O50: 73 | W50: =_xlfn.XLOOKUP(D50,'All DP'!B:B,'All DP'!D:D,"Tidak") -> Masih | X50: =IFERROR(IF(MOD(H50,1)<=TIME(15,0,0),"YA","TIDAK"),0) -> YA
A51: 46266 | B51: AGENT40 | C51: KEPULAUAN_SERIBU | D51: JKT08C | E51: 20260901-064225.jpg | F51: - Ketepatan absensi 06:30 target 90% - Keluar gudang 07:30 - TTD real-time sebelum jam 12:00 90% ( Balik rit sebelum jam 12, simgud paket bermasalah dengan POD Valid) - Pickup QR Sprinter 1 Hari 1 Awb - Sosialisasi mengenai barang dilarang kirim | G51: Marketing | H51: 46266.28 | I51: 31 | J51: 31 | K51: Fikri Gilang P JKT-08L | M51: 46266.28 | N51: Masih | O51: 73 | W51: =_xlfn.XLOOKUP(D51,'All DP'!B:B,'All DP'!D:D,"Tidak") -> Masih | X51: =IFERROR(IF(MOD(H51,1)<=TIME(15,0,0),"YA","TIDAK"),0) -> YA
A52: 46266 | B52: AGENT21 | C52: ENDE | D52: ENE01 | E52: TimeVideo_20260901_073618.mp4 | F52: Push TTD dan target dp | G52: other | H52: 46266.28 | I52: 13 | J52: 19 | K52: Nur Azizah | M52: 46266.28 | N52: Masih | O52: 176 | W52: =_xlfn.XLOOKUP(D52,'All DP'!B:B,'All DP'!D:D,"Tidak") -> Tidak | X52: =IFERROR(IF(MOD(H52,1)<=TIME(15,0,0),"YA","TIDAK"),0) -> YA
A53: 46266 | B53: AGENT22 | C53: WANGGODO | D53: WAG01 | E53: WhatsApp Video 2026-09-01 at 06.49.10.mp4 | F53: TT RIVERS & TPTW | G53: other | H53: 46266.281 | I53: 20 | J53: 20 | K53: Pengguna Tamu 75295 | M53: 46266.281 | O53: 148 | W53: =_xlfn.XLOOKUP(D53,'All DP'!B:B,'All DP'!D:D,"Tidak") -> Masih | X53: =IFERROR(IF(MOD(H53,1)<=TIME(15,0,0),"YA","TIDAK"),0) -> YA
A54: 46266 | B54: AGENT40 | C54: DC_KELAPA_GADING | D54: JKT07U | E54: 20260901-064409.jpg | F54: Briefing Pagi DC Kelapa gading - Absensi 06.30 - Scan Deliv 07.30 - TTD Jam 12.00 - TTD All Ritase - POD Valid - Longtail - Penggunaan Pembayaran Online - Parcel & RSAT - QR Sprinter - Quiz App Sprinter - Prospek pelanggan - paket DG | G54: Marketing | H54: 46266.281 | I54: 77 | J54: 105 | K54: Ikhsan Alif Al Mi' Roj | M54: 46266.281 | N54: Masih | O54: 73 | W54: =_xlfn.XLOOKUP(D54,'All DP'!B:B,'All DP'!D:D,"Tidak") -> Masih | X54: =IFERROR(IF(MOD(H54,1)<=TIME(15,0,0),"YA","TIDAK"),0) -> YA
A55: 46266 | B55: AGENT40 | C55: DC_KEMAYORAN | D55: JKT15K | E55: image.png | F55: Briefing pagi DC kemayoran Absensi 06.30 Keluar Gudang 07.30 TTD 12.00 TTD ALL Ritase Pemaksimalan Area Office yang tutup Parcel Care QR Sprinter 1 AWB 1 Sprinter Paket Dangerous Goods, paket-paket berbahaya dilarang kirim, Paket Cairan harus dengan packing yang rapat dan baik Penambahan Man Power untuk Persiapan Peak Season 6S POD Retur Valid Penekanan serta penurunan CODFD | G55: Marketing | H55: 46266.281 | I55: 50 | J55: 128 | K55: M Satiri | M55: 46266.281 | N55: Masih | O55: 73 | W55: =_xlfn.XLOOKUP(D55,'All DP'!B:B,'All DP'!D:D,"Tidak") -> Masih | X55: =IFERROR(IF(MOD(H55,1)<=TIME(15,0,0),"YA","TIDAK"),0) -> YA
A56: 46266 | B56: AGENT40 | C56: ROROTAN | D56: JKT10B | E56: WhatsApp Image 2026-09-01 at 06.44.24.jpeg | F56: . Absensi 06:30 . keluar DC 07:30 . TTD JAM 12 . TTD all ritase . Pickup reguler . QR sprinter . Quis app sprinter . Menghindari paket2 dilarang kirim DG | G56: Marketing | H56: 46266.283 | I56: 65 | J56: 75 | K56: Tadin Saputra | M56: 46266.283 | N56: Masih | O56: 73 | W56: =_xlfn.XLOOKUP(D56,'All DP'!B:B,'All DP'!D:D,"Tidak") -> Masih | X56: =IFERROR(IF(MOD(H56,1)<=TIME(15,0,0),"YA","TIDAK"),0) -> YA
A57: 46266 | B57: AGENT28 | C57: NABIRE | D57: NBX01 | E57: 1495b594-2966-479b-b9d9-9cdee5952f71.jpg | F57: push paket,paket complaint,parcel care,push ttd | G57: other | H57: 46266.283 | I57: 3 | J57: 5 | K57: Hayu Hutami | M57: 46266.283 | O57: 13 | W57: =_xlfn.XLOOKUP(D57,'All DP'!B:B,'All DP'!D:D,"Tidak") -> Masih | X57: =IFERROR(IF(MOD(H57,1)<=TIME(15,0,0),"YA","TIDAK"),0) -> YA
A58: 46266 | B58: AGENT40 | C58: DC_PALMERAH | D58: JKT03E | E58: VID-20260901-WA0031.mp4 | F58: BRIEFING PAGI DC PALMERAH •KELUAR GUDANG 07:30 •QR SPRINTER •POD RETUR •TTD ALLRITASE •TTD JAM 12:00 •EVALUASI PERFORMANCE BULAN AGUSTUS •MEMINUMALISIR PAKET SIMPAN GUDANG | G58: Marketing | H58: 46266.283 | I58: 63 | J58: 138 | K58: Govur | M58: 46266.283 | N58: Masih | O58: 73 | W58: =_xlfn.XLOOKUP(D58,'All DP'!B:B,'All DP'!D:D,"Tidak") -> Masih | X58: =IFERROR(IF(MOD(H58,1)<=TIME(15,0,0),"YA","TIDAK"),0) -> YA
A59: 46266 | B59: AGENT21 | C59: APU05A | D59: APU05A | E59: VID-20260528-WA0002.mp4 | F59: Asen, paket stuck, setoran, ttd | G59: other | H59: 46266.284 | I59: 25 | J59: 27 | K59: I Wayan Widia | M59: 46266.284 | N59: Masih | O59: 176 | W59: =_xlfn.XLOOKUP(D59,'All DP'!B:B,'All DP'!D:D,"Tidak") -> Masih | X59: =IFERROR(IF(MOD(H59,1)<=TIME(15,0,0),"YA","TIDAK"),0) -> YA
A60: 46266 | B60: AGENT21 | C60: LARANTUKA | D60: LKA01 | E60: 20260721_80234AM_ByGPSVideoCamera.mp4 | F60: Absensi, pus TTD, retur tepat waktu, | G60: other | H60: 46266.284 | I60: 15 | J60: 20 | K60: Yulianus Hedung Hajon | M60: 46266.284 | N60: Masih | O60: 176 | W60: =_xlfn.XLOOKUP(D60,'All DP'!B:B,'All DP'!D:D,"Tidak") -> Tidak | X60: =IFERROR(IF(MOD(H60,1)<=TIME(15,0,0),"YA","TIDAK"),0) -> YA
A61: 46266 | B61: AGENT23 | C61: MASAMA | D61: BAG06 | E61: 2026-09-01 07.43.48_Jalan Trans Luwuk.jpg | F61: RITASE LONGTAIL TTD SEBELUM JAM 12 ABSENSI | G61: other | H61: 46266.284 | I61: 5 | J61: 9 | K61: Susi Susanti | M61: 46266.284 | N61: Masih | O61: 175 | W61: =_xlfn.XLOOKUP(D61,'All DP'!B:B,'All DP'!D:D,"Tidak") -> Masih | X61: =IFERROR(IF(MOD(H61,1)<=TIME(15,0,0),"YA","TIDAK"),0) -> YA
A62: 46266 | B62: AGENT22 | C62: SUNGGUMINASA | D62: SGM01 | E62: 2026-09-01 07.35.41_No.47, Jalan Andi Tonro.jpg | F62: pencarian new customer | G62: Marketing | H62: 46266.285 | I62: 26 | J62: 26 | K62: Dedhy Amiruddin | M62: 46266.285 | O62: 148 | W62: =_xlfn.XLOOKUP(D62,'All DP'!B:B,'All DP'!D:D,"Tidak") -> Masih | X62: =IFERROR(IF(MOD(H62,1)<=TIME(15,0,0),"YA","TIDAK"),0) -> YA
A63: 46266 | B63: AGENT22 | C63: SUNU | D63: UPG09 | E63: IMG-20260901-WA0003.jpg | F63: pod scan bermasalah valid | G63: other | H63: 46266.286 | I63: 9 | J63: 23 | K63: Firwansyah M | M63: 46266.286 | O63: 148 | W63: =_xlfn.XLOOKUP(D63,'All DP'!B:B,'All DP'!D:D,"Tidak") -> Masih | X63: =IFERROR(IF(MOD(H63,1)<=TIME(15,0,0),"YA","TIDAK"),0) -> YA
A64: 46266 | B64: AGENT40 | C64: CP_KOJA_1 | D64: JKT63B | E64: 999.jpg | F64: Selamat pagi, berikut laporan briefing pagi CP KOJA : 1. Absensi tepat waktu jam 06:30 pagi target 92% 2. Keluar gudang tepat waktu jam 07:30 pagi target 95% 3. TTD Sebelum jam 12:00 siang target 90% 4. TTD All ritase harian dan bulanan target 97% 5. Reminder pod retur valid (bukti chat dan foto) 6. Sosialisasi mengenai barang yang di larang kirim (DG) Terima kasih🙏 | G64: other | H64: 46266.287 | I64: 30 | J64: 161 | K64: Mohamad Irvan | M64: 46266.287 | N64: Masih | O64: 73 | W64: =_xlfn.XLOOKUP(D64,'All DP'!B:B,'All DP'!D:D,"Tidak") -> Masih | X64: =IFERROR(IF(MOD(H64,1)<=TIME(15,0,0),"YA","TIDAK"),0) -> YA
A65: 46266 | B65: AGENT40 | C65: DC_PASAR_MINGGU | D65: JKT23P | E65: img_v3_02154_4bcd5cba-334b-4ebe-8ede-dbd86c3875ix.jpg | F65: ABSENSI 6:30 KELUAR GUDANG 7:30 TTD JAM 12:00 TTD ALL RITASE PROSPECT PELUANG PELANGGAN SOSIALISASI PAKET DG POD VALID LONGTAIL QUIZ SPRINTER QR SPRINTER | G65: Marketing | H65: 46266.289 | I65: 14 | J65: 85 | K65: MuhamadRamdan_DC PASAR MINGGU | M65: 46266.289 | N65: Masih | O65: 73 | W65: =_xlfn.XLOOKUP(D65,'All DP'!B:B,'All DP'!D:D,"Tidak") -> Masih | X65: =IFERROR(IF(MOD(H65,1)<=TIME(15,0,0),"YA","TIDAK"),0) -> YA
A66: 46266 | B66: AGENT23 | C66: TATAARAN | D66: TDO04 | E66: img_v3_02154_5cd1991d-f740-4ff6-8271-9260857173hu.jpg | F66: PUSH KPI ABSENSI POD VALID | G66: other | H66: 46266.289 | I66: 10 | J66: 11 | K66: Keven Joshua Van Bone | M66: 46266.289 | N66: Masih | O66: 175 | W66: =_xlfn.XLOOKUP(D66,'All DP'!B:B,'All DP'!D:D,"Tidak") -> Masih | X66: =IFERROR(IF(MOD(H66,1)<=TIME(15,0,0),"YA","TIDAK"),0) -> YA
A67: 46266 | B67: AGENT22 | C67: UPG_SALES | D67: UPG888 | E67: TimePhoto_20260901_071431.jpg | F67: PEMAKSIMALAN PICKUP DAN TTD JAM 12 | G67: other | H67: 46266.289 | I67: 32 | J67: 36 | K67: Edwin Saifuddin Thayeb | M67: 46266.289 | O67: 148 | W67: =_xlfn.XLOOKUP(D67,'All DP'!B:B,'All DP'!D:D,"Tidak") -> Masih | X67: =IFERROR(IF(MOD(H67,1)<=TIME(15,0,0),"YA","TIDAK"),0) -> YA
A68: 46266 | B68: AGENT21 | C68: DENPASAR_SELATAN_2 | D68: DPS05B | E68: 20260901_73815AMByGPSMapCamera.mp4 | F68: Marketing Absensi Keluar gudang 07.30 TTD sebelum jam 12.00 TTD Ritase | G68: Marketing | H68: 46266.289 | I68: 6 | J68: 32 | K68: Rezky Fernando Labidu | M68: 46266.289 | N68: Masih | O68: 176 | W68: =_xlfn.XLOOKUP(D68,'All DP'!B:B,'All DP'!D:D,"Tidak") -> Masih | X68: =IFERROR(IF(MOD(H68,1)<=TIME(15,0,0),"YA","TIDAK"),0) -> YA
A69: 46266 | B69: AGENT21 | C69: RUTENG | D69: RTG01 | E69: VID-20260901-WA0005.mp4 | F69: RTK DAN PTMP | G69: other | H69: 46266.29 | I69: 11 | J69: 17 | K69: Aloysius Riwanto | M69: 46266.29 | N69: Masih | O69: 176 | W69: =_xlfn.XLOOKUP(D69,'All DP'!B:B,'All DP'!D:D,"Tidak") -> Tidak | X69: =IFERROR(IF(MOD(H69,1)<=TIME(15,0,0),"YA","TIDAK"),0) -> YA
A70: 46266 | B70: AGENT40 | C70: KALIBARU_01 | D70: JKT10H | E70: image.png,image.png | F70: BRIFING PAGI DC KALIBARU_01 ABSENSI 06:30 KELUAR GUDANG 07:30 TTD JAM 12 90% ALL RITASE 97% QR SPRINTER 1 AWB 1 HARI BARANG BARANG YANG DILARANG KIRIM / ATAU BARANG DG KEBERSIHAN GUDANG | G70: Marketing | H70: 46266.29 | I70: 107 | J70: 135 | K70: A.Abdullah JKT10H | M70: 46266.29 | N70: Masih | O70: 73 | W70: =_xlfn.XLOOKUP(D70,'All DP'!B:B,'All DP'!D:D,"Tidak") -> Masih | X70: =IFERROR(IF(MOD(H70,1)<=TIME(15,0,0),"YA","TIDAK"),0) -> YA
A71: 46266 | B71: AGENT23 | C71: BIAU_01 | D71: BUO07B | E71: img_v3_02154_366f634b-cce8-4d80-bf3b-55f8023c68hu.jpg | F71: PAYCOOLS PUSH TTD PARCEL CARE | G71: other | H71: 46266.29 | I71: 4 | J71: 14 | K71: Chikita S. Mentemas | M71: 46266.29 | N71: Tidak | O71: 175 | W71: =_xlfn.XLOOKUP(D71,'All DP'!B:B,'All DP'!D:D,"Tidak") -> Masih | X71: =IFERROR(IF(MOD(H71,1)<=TIME(15,0,0),"YA","TIDAK"),0) -> YA
A72: 46266 | B72: AGENT21 | C72: AMPENAN | D72: AMI15 | E72: VID-20260901-WA0064.mp4 | F72: push delivery sebelum 7:30 dan ttd tepat waktu sebelum jam 12 | G72: other | H72: 46266.29 | I72: 24 | J72: 28 | K72: Abdul Latip | M72: 46266.29 | N72: Masih | O72: 176 | W72: =_xlfn.XLOOKUP(D72,'All DP'!B:B,'All DP'!D:D,"Tidak") -> Masih | X72: =IFERROR(IF(MOD(H72,1)<=TIME(15,0,0),"YA","TIDAK"),0) -> YA
A73: 46266 | B73: AGENT22 | C73: TELKOMAS | D73: UPG57A | E73: VID-20260720-WA0085.mp4 | F73: Push pencapaian pickup 1 awb 1spt/hari dan scan bermasalah wajib pod valid | G73: other | H73: 46266.291 | I73: 29 | J73: 34 | K73: Supriadi . | M73: 46266.291 | O73: 148 | W73: =_xlfn.XLOOKUP(D73,'All DP'!B:B,'All DP'!D:D,"Tidak") -> Masih | X73: =IFERROR(IF(MOD(H73,1)<=TIME(15,0,0),"YA","TIDAK"),0) -> YA
A74: 46266 | B74: AGENT23 | C74: SOEKARNO_HATTA_01 | D74: PLW03G | E74: 046860d1-fbac-48c3-83e8-33c591328afc.jpg | F74: KEBERSIHAN LONGTAIL PUSH TTD | G74: other | H74: 46266.291 | I74: 3 | J74: 14 | K74: Safril Nasaru | M74: 46266.291 | O74: 175 | W74: =_xlfn.XLOOKUP(D74,'All DP'!B:B,'All DP'!D:D,"Tidak") -> Masih | X74: =IFERROR(IF(MOD(H74,1)<=TIME(15,0,0),"YA","TIDAK"),0) -> YA
A75: 46266 | B75: AGENT23 | C75: TAHUNA_01 | D75: THA01A | E75: 01-09-2026.jpg | F75: ABSENSI LONGTAIL TTD SBLM JAM 12 | G75: other | H75: 46266.293 | I75: 23 | J75: 32 | K75: Yesenia Makapedua | M75: 46266.293 | N75: Masih | O75: 175 | W75: =_xlfn.XLOOKUP(D75,'All DP'!B:B,'All DP'!D:D,"Tidak") -> Masih | X75: =IFERROR(IF(MOD(H75,1)<=TIME(15,0,0),"YA","TIDAK"),0) -> YA
A76: 46266 | B76: AGENT21 | C76: DC_MENGWI_1 | D76: MGW01F | E76: 31-03-202608:21:47AM_1486_ByGPSMapCamera.mp4 | F76: stuk | G76: other | H76: 46266.293 | I76: 51 | J76: 51 | K76: I Putu Adi Putra | M76: 46266.293 | N76: Masih | O76: 176 | W76: =_xlfn.XLOOKUP(D76,'All DP'!B:B,'All DP'!D:D,"Tidak") -> Masih | X76: =IFERROR(IF(MOD(H76,1)<=TIME(15,0,0),"YA","TIDAK"),0) -> YA
A77: 46266 | B77: AGENT07 | C77: TEBO_ILIR | D77: MUT07 | E77: TimeVideo_20260901_065852.mp4 | F77: target ttd aktual target ttd jam 12 absensi | G77: other | H77: 46266.294 | I77: 20 | J77: 21 | K77: Guest User 84911 | M77: 46266.294 | N77: Masih | O77: 65 | W77: =_xlfn.XLOOKUP(D77,'All DP'!B:B,'All DP'!D:D,"Tidak") -> Masih | X77: =IFERROR(IF(MOD(H77,1)<=TIME(15,0,0),"YA","TIDAK"),0) -> YA
A78: 46266 | B78: AGENT21 | C78: SERUNI | D78: AMI06 | E78: VID_20260901_080228.mp4 | F78: perbaikan TTTDAktual | G78: other | H78: 46266.295 | I78: 23 | J78: 27 | K78: Muhammad Tazki Ardian | M78: 46266.295 | N78: Masih | O78: 176 | W78: =_xlfn.XLOOKUP(D78,'All DP'!B:B,'All DP'!D:D,"Tidak") -> Masih | X78: =IFERROR(IF(MOD(H78,1)<=TIME(15,0,0),"YA","TIDAK"),0) -> YA
A79: 46266 | B79: AGENT40 | C79: DC_MAKASAR | D79: JKT20J | E79: WhatsApp Image 2026-09-01 at 07.02.49.jpeg | F79: ABSEN KLUAR GUDANG TTD JAM 12 TTD ALL RITASE | G79: other | H79: 46266.295 | I79: 33 | J79: 99 | K79: Rio Permanna Wijaya | M79: 46266.295 | N79: Masih | O79: 73 | W79: =_xlfn.XLOOKUP(D79,'All DP'!B:B,'All DP'!D:D,"Tidak") -> Masih | X79: =IFERROR(IF(MOD(H79,1)<=TIME(15,0,0),"YA","TIDAK"),0) -> YA
A80: 46266 | B80: AGENT40 | C80: SENEN | D80: JKT12 | E80: img_v3_02154_afc825b1-ce4b-4457-b5e3-1406eda55ahu.jpg | F80: BRIFING PAGI DC_SENEN -ABSEN PAGI 06.30 -KELUAR DC 07.30 -TARGET TTD JAM 12 -TARGET ALRITASE -QR SPRINTER 1 AWB/HARI -POD VALID RETUR -6S -PAKET DG | G80: Marketing | H80: 46266.295 | I80: 80 | J80: 132 | K80: Agusman Hulu | M80: 46266.296 | N80: Masih | O80: 73 | W80: =_xlfn.XLOOKUP(D80,'All DP'!B:B,'All DP'!D:D,"Tidak") -> Masih | X80: =IFERROR(IF(MOD(H80,1)<=TIME(15,0,0),"YA","TIDAK"),0) -> YA
A81: 46266 | B81: AGENT07 | C81: SLN07 | D81: SLN07 | E81: VID20260812071100.mp4,IMG20260812071146_01.jpg | F81: POD & TTD RETUR | G81: other | H81: 46266.296 | I81: 9 | J81: 9 | K81: Guest User 56467 | M81: 46266.296 | N81: Masih | O81: 65 | W81: =_xlfn.XLOOKUP(D81,'All DP'!B:B,'All DP'!D:D,"Tidak") -> Masih | X81: =IFERROR(IF(MOD(H81,1)<=TIME(15,0,0),"YA","TIDAK"),0) -> YA
A82: 46266 | B82: AGENT40 | C82: JOHAR_BARU_01 | D82: JKT13K | E82: TC_00577.jpeg | F82: DANGEROUS GOODS TTD ALL RITASE TTD JAM 12 ABSENSI SPRINTER | G82: other | H82: 46266.296 | I82: 139 | J82: 139 | K82: Pengguna Tamu 97405 | M82: 46266.296 | N82: Masih | O82: 73 | W82: =_xlfn.XLOOKUP(D82,'All DP'!B:B,'All DP'!D:D,"Tidak") -> Masih | X82: =IFERROR(IF(MOD(H82,1)<=TIME(15,0,0),"YA","TIDAK"),0) -> YA
A83: 46266 | B83: AGENT22 | C83: LAEYA | D83: WAG04 | E83: IMG-20260901-WA0072.jpg | F83: Pemaksimalan Backup Coveran Delivery | G83: other | H83: 46266.297 | I83: 7 | J83: 10 | K83: Tamsir Tawakal Sp | M83: 46266.297 | O83: 148 | W83: =_xlfn.XLOOKUP(D83,'All DP'!B:B,'All DP'!D:D,"Tidak") -> Masih | X83: =IFERROR(IF(MOD(H83,1)<=TIME(15,0,0),"YA","TIDAK"),0) -> YA
A84: 46266 | B84: AGENT21 | C84: WAIKABUBAK | D84: WBK01 | E84: VID-20260901-WA0015.mp4 | F84: Outgoing,target TTD,dan penilaian RSAT DAN PARCEL CARE | G84: other | H84: 46266.297 | I84: 10 | J84: 14 | K84: Dewiyana Yuliana Malo | M84: 46266.297 | N84: Masih | O84: 176 | W84: =_xlfn.XLOOKUP(D84,'All DP'!B:B,'All DP'!D:D,"Tidak") -> Masih | X84: =IFERROR(IF(MOD(H84,1)<=TIME(15,0,0),"YA","TIDAK"),0) -> YA
A85: 46266 | B85: AGENT22 | C85: RANDOMAYANG | D85: PAK03 | E85: 2026-09-01 07.58.18_.jpg | F85: Mengarahkan Sprinter mencari customer potensial di lapangan | G85: Marketing | H85: 46266.298 | I85: 11 | J85: 11 | K85: Andi Sudirman Adi Putra | M85: 46266.298 | O85: 148 | W85: =_xlfn.XLOOKUP(D85,'All DP'!B:B,'All DP'!D:D,"Tidak") -> Masih | X85: =IFERROR(IF(MOD(H85,1)<=TIME(15,0,0),"YA","TIDAK"),0) -> YA
A86: 46266 | B86: AGENT23 | C86: AMPANA_RAYA | D86: AMP01A | E86: 1788221303069_img_v3_02154_a2808d28-8759-44a6-8e90-253d6e38b5hu.jpg | F86: AMPANA_RAYA LONGTAIL PAYCOOLS TTD SEBELUM JAM 12 POD VALID RITASE TTD QR SPRINTER | G86: Marketing | H86: 46266.298 | I86: 16 | J86: 18 | K86: Moh. Laxmana | M86: 46266.298 | N86: Masih | O86: 175 | W86: =_xlfn.XLOOKUP(D86,'All DP'!B:B,'All DP'!D:D,"Tidak") -> Masih | X86: =IFERROR(IF(MOD(H86,1)<=TIME(15,0,0),"YA","TIDAK"),0) -> YA
A87: 46266 | B87: AGENT40 | C87: CP_PONDOK_PINANG_2 | D87: JKT31I | E87: 2026-09-01 07.05.17_5, Jalan Ismail_(Company-BASEY 1).jpg | F87: Briefing pagi cp pondok pinang 2 1. Absensi 06:30 target 92% 2. Keluar gudang 07:30 target 94% 3. TTD jam 12 target 90% 4. Longtail 5. parcel care tiktok dan tokped ( RSAT ) 6. All ritase target 97% 7. Pickup reguler per hari 1 8. Peluang Pelanggan customer baru 9. Penggunaan QR Sprinter 10. COD FD 11. Setoran gopay (reward 80% : 60rb , 90% : 80rb , 100% :100rb) 12. Ketentuan POD Retur 13. Quis sprinter jawab bener semua 14. Barang DG | G87: Marketing | H87: 46266.298 | I87: 30 | J87: 50 | K87: Guest User 92352 | M87: 46266.298 | N87: Masih | O87: 73 | W87: =_xlfn.XLOOKUP(D87,'All DP'!B:B,'All DP'!D:D,"Tidak") -> Masih | X87: =IFERROR(IF(MOD(H87,1)<=TIME(15,0,0),"YA","TIDAK"),0) -> YA
A88: 46266 | B88: AGENT22 | C88: MALILI | D88: MAL01 | E88: TimeVideo_20260901_065515.mp4 | F88: QR sprinter bagi prospek bagi untung. | G88: Marketing | H88: 46266.299 | I88: 18 | J88: 23 | K88: Holidin Din | M88: 46266.299 | O88: 148 | W88: =_xlfn.XLOOKUP(D88,'All DP'!B:B,'All DP'!D:D,"Tidak") -> Masih | X88: =IFERROR(IF(MOD(H88,1)<=TIME(15,0,0),"YA","TIDAK"),0) -> YA
A89: 46266 | B89: AGENT12 | C89: CILANGKAHAN | D89: RKS20 | E89: 2026-09-01 07.05.56_Jalan Raya Pasar Malingping.mp4 | F89: TTD JAM 12 DAN MEMAKSIMALKAN PAKET PAKET SISA | G89: other | H89: 46266.299 | I89: 60 | J89: 74 | K89: Muhammad SamsudinRKS20 | M89: 46266.299 | O89: 114 | W89: =_xlfn.XLOOKUP(D89,'All DP'!B:B,'All DP'!D:D,"Tidak") -> Masih | X89: =IFERROR(IF(MOD(H89,1)<=TIME(15,0,0),"YA","TIDAK"),0) -> YA
A90: 46266 | B90: AGENT22 | C90: UIN_ALAUDDIN | D90: UPG16 | E90: image_2026-09-01_071046075.png | F90: Kode ketiga dan TTD jam 12 | G90: other | H90: 46266.299 | I90: 20 | J90: 39 | K90: Wilhelmus Owen Johnson | M90: 46266.3 | O90: 148 | W90: =_xlfn.XLOOKUP(D90,'All DP'!B:B,'All DP'!D:D,"Tidak") -> Masih | X90: =IFERROR(IF(MOD(H90,1)<=TIME(15,0,0),"YA","TIDAK"),0) -> YA
A91: 46266 | B91: AGENT21 | C91: LEWOLEBA | D91: LEW01 | E91: VID-20260901-WA0053.mp4 | F91: push ttd, kurangi paket stuck dan sebelum pulang pastikan aplikasitkosekelumsud | G91: other | H91: 46266.302 | I91: 10 | J91: 15 | K91: Arnoldus Olak Tukan | M91: 46266.302 | N91: Masih | O91: 176 | W91: =_xlfn.XLOOKUP(D91,'All DP'!B:B,'All DP'!D:D,"Tidak") -> Tidak | X91: =IFERROR(IF(MOD(H91,1)<=TIME(15,0,0),"YA","TIDAK"),0) -> YA
A92: 46266 | B92: AGENT07 | C92: MUS08 | D92: MUS08 | E92: WhatsApp Image 2026-09-01 at 07.13.00.jpeg | F92: POD DAN TTD RETUR | G92: other | H92: 46266.302 | I92: 5 | J92: 10 | K92: Muhammad Rizky | M92: 46266.302 | N92: Masih | O92: 65 | W92: =_xlfn.XLOOKUP(D92,'All DP'!B:B,'All DP'!D:D,"Tidak") -> Masih | X92: =IFERROR(IF(MOD(H92,1)<=TIME(15,0,0),"YA","TIDAK"),0) -> YA
A93: 46266 | B93: AGENT40 | C93: DC_CILINCING | D93: JKT10G | E93: IMG-20260901-WA0007.jpg | F93: Absensi Keluar Gudang TTD 12 TTD Ritase Qr Reguler Paket DG Kebersihan Gudang | G93: other | H93: 46266.302 | I93: 89 | J93: 89 | K93: Saleh Saleh | M93: 46266.302 | N93: Tidak | O93: 73 | W93: =_xlfn.XLOOKUP(D93,'All DP'!B:B,'All DP'!D:D,"Tidak") -> Masih | X93: =IFERROR(IF(MOD(H93,1)<=TIME(15,0,0),"YA","TIDAK"),0) -> YA
A94: 46266 | B94: AGENT03 | C94: PULAU_RAKYAT | D94: AEK03 | E94: 2026-09-01 07.08.27_No. 50, Jalan Perintis Kemerdekaan_(Judul-JNT EXPRESS PULAU RAKYAT)_(Catatan-PANGLIMA KURIR).jpg | F94: 1. JAM ABSENSI 2. SOP RETURAN 3. MARKETING QR DP DAN QR SPRINTER | G94: Marketing | H94: 46266.303 | I94: 24 | J94: 25 | K94: Pengguna Tamu 66302 | M94: 46266.303 | O94: 74 | W94: =_xlfn.XLOOKUP(D94,'All DP'!B:B,'All DP'!D:D,"Tidak") -> Masih | X94: =IFERROR(IF(MOD(H94,1)<=TIME(15,0,0),"YA","TIDAK"),0) -> YA
A95: 46266 | B95: AGENT40 | C95: CP_CIGANJUR | D95: JKT62C | E95: image.png | F95: *ABSENSI 06.30 *KELUAR GUDANG // DC 07.30 *TTD 12.00 & ALL RITASE *KODE KE 3 *KEBERSIHAN GUDANG // DC *PENANGANAN PAKET DG(DANGEROUS GOODS) *SETORAN CODFOD *PENGGUNAAN GOPAY, PAYCOL & QR SPRINTER | G95: Marketing | H95: 46266.303 | I95: 23 | J95: 80 | K95: Rendi CP_ciganjur | M95: 46266.303 | N95: Masih | O95: 73 | W95: =_xlfn.XLOOKUP(D95,'All DP'!B:B,'All DP'!D:D,"Tidak") -> Masih | X95: =IFERROR(IF(MOD(H95,1)<=TIME(15,0,0),"YA","TIDAK"),0) -> YA
A96: 46266 | B96: AGENT21 | C96: TNW02B | D96: TNW02B | E96: briefing 1 sep.mp4 | F96: Push TTD sebelum jam 12 dan push stuck , dan pick up sprinter QR | G96: Marketing | H96: 46266.303 | I96: 14 | J96: 24 | K96: I Putu Aridana | M96: 46266.303 | N96: Masih | O96: 176 | W96: =_xlfn.XLOOKUP(D96,'All DP'!B:B,'All DP'!D:D,"Tidak") -> Masih | X96: =IFERROR(IF(MOD(H96,1)<=TIME(15,0,0),"YA","TIDAK"),0) -> YA
A97: 46266 | B97: AGENT23 | C97: LANGOWAN | D97: TDO02 | E97: d8b77c54-eb8d-409e-ae5e-60e1b3ffd0f2.JPEG,IMG_9847.mp4 | F97: PUSH KPI | G97: other | H97: 46266.304 | I97: 10 | J97: 12 | K97: Hizkia Runtuwarow | M97: 46266.304 | N97: Masih | O97: 175 | W97: =_xlfn.XLOOKUP(D97,'All DP'!B:B,'All DP'!D:D,"Tidak") -> Masih | X97: =IFERROR(IF(MOD(H97,1)<=TIME(15,0,0),"YA","TIDAK"),0) -> YA
A98: 46266 | B98: AGENT22 | C98: ATTAPANGE | D98: SEK03 | E98: 2026-09-01 06.39.40_.jpg | F98: Target pickup harian sprinter pod simpan gudang prospek pelanggan | G98: Marketing | H98: 46266.304 | I98: 10 | J98: 18 | K98: Guest User 15040 | M98: 46266.305 | O98: 148 | W98: =_xlfn.XLOOKUP(D98,'All DP'!B:B,'All DP'!D:D,"Tidak") -> Masih | X98: =IFERROR(IF(MOD(H98,1)<=TIME(15,0,0),"YA","TIDAK"),0) -> YA
A99: 46266 | B99: AGENT22 | C99: SOROAKO | D99: MAL02 | E99: VID-20260822-WA0268.mp4 | F99: Pod valid Paket longtail | G99: other | H99: 46266.305 | I99: 15 | J99: 19 | K99: Bagus Adi Saputra | M99: 46266.305 | O99: 148 | W99: =_xlfn.XLOOKUP(D99,'All DP'!B:B,'All DP'!D:D,"Tidak") -> Masih | X99: =IFERROR(IF(MOD(H99,1)<=TIME(15,0,0),"YA","TIDAK"),0) -> YA
A100: 46266 | B100: AGENT28 | C100: MANOKWARI | D100: MKW01 | E100: WhatsApp Video 2026-09-01 at 07.14.01.mp4 | F100: MEMPERKENALKAN KURIR BARU, MENGINFOKAN WAJIB INVENTORI, KEBERSIHAN | G100: other | H100: 46266.305 | I100: 4 | J100: 11 | K100: Pengguna Tamu 42526 | M100: 46266.305 | O100: 13 | W100: =_xlfn.XLOOKUP(D100,'All DP'!B:B,'All DP'!D:D,"Tidak") -> Masih | X100: =IFERROR(IF(MOD(H100,1)<=TIME(15,0,0),"YA","TIDAK"),0) -> YA
A101: 46266 | B101: AGENT12 | C101: JAMBE_RAYA | D101: BAL02A | E101: VID-20260901-WA0003(1).mp4 | F101: Absensi kehadiran 06:29 Ttd sebelum jam 12 Ttd aktual Gopay Pod Retur | G101: other | H101: 46266.305 | I101: 28 | J101: 36 | K101: Kadiday _BAL02A | M101: 46266.305 | O101: 114 | W101: =_xlfn.XLOOKUP(D101,'All DP'!B:B,'All DP'!D:D,"Tidak") -> Masih | X101: =IFERROR(IF(MOD(H101,1)<=TIME(15,0,0),"YA","TIDAK"),0) -> YA
A102: 46266 | B102: AGENT07 | C102: KTL12 | D102: KTL12 | E102: WhatsApp Image 2026-09-01 at 07.16.05.jpeg | F102: PENGEMBANGAN CHANEL SPRINTER | G102: Marketing | H102: 46266.305 | I102: 46 | J102: 46 | K102: M. Sofyan | M102: 46266.305 | N102: Masih | O102: 65 | W102: =_xlfn.XLOOKUP(D102,'All DP'!B:B,'All DP'!D:D,"Tidak") -> Masih | X102: =IFERROR(IF(MOD(H102,1)<=TIME(15,0,0),"YA","TIDAK"),0) -> YA
A103: 46266 | B103: AGENT21 | C103: MAULAFA | D103: KOE02 | E103: 20260901_71742AMByGPSMapCamera.mp4 | F103: Ttd dibawah jam 12 | G103: other | H103: 46266.306 | I103: 7 | J103: 24 | K103: Firdaustian Aka Heku | M103: 46266.306 | N103: Masih | O103: 176 | W103: =_xlfn.XLOOKUP(D103,'All DP'!B:B,'All DP'!D:D,"Tidak") -> Masih | X103: =IFERROR(IF(MOD(H103,1)<=TIME(15,0,0),"YA","TIDAK"),0) -> YA
...

Sheet Display
D2: c
F4: ="网管 - 各代理早会上传状态 "&TEXT(AJ7,"yyyy-mm-dd")&" NM - Status Upload Briefing Pagi Agent "&TEXT(AJ7,"yyyy-mm-dd") -> 网管 - 各代理早会上传状态 2026-09-03 NM - Status Upload Briefing Pagi Agent 2026-09-03
F5: Sumber Data : 1. JMS > Monitoring Briefing > Karyawan 2. Feishu Base > Feedback Briefing Kerja Penarikan data = Tanggal 1 bulan berjalan - H-1 Penjelasan : 1. Total DP = Jumlah DP yang harus upload briefing pagi 2. Yang Sudah Upload Tepat Waktu = DP yang sudah upload dan submit form briefing pagi pada tanggal berjalan, dengan waktu upload 00:00–15:00. 3. Upload setelah pukul 15:00 = Tidak dihitung sebagai upload tepat waktu. 4. Persentase Upload Tepat Waktu = Jumlah DP yang upload tepat waktu ÷ Total DP. | Q5: 数据来源： 1. JMS > 班前例会监控报表 > 按员工统计 2. Feishu Base > 工作早会反馈 数据提取范围：当月1日至前一天（H-1） 说明： 1. 网点总数 = 需要上传早会的网点数量。 2. 及时上传 = 网点在当天完成早会上传及提交表单，上传时间为 00:00–15:00。 3. 15:00之后上传 = 不计入及时上传。 4. 及时上传率 = 及时上传网点数 ÷ 网点总数。
F6: 区域 Area | G6: 代理区 Agent | J6: 排名 Rank | K6: 目标 Target | L6: ="日度达成 "&TEXT(AJ7,"YYYY-MM-DD")&" Pencapaian Harian " -> 日度达成 2026-09-03 Pencapaian Harian | O6: 周度达成 Pencapaian Mingguan | AC6: 月度达成 Pencapaian Bulanan
O7: 网点总数 Total DP | P7: ="W1"&CHAR(10)&TEXT(AJ8,"DD MMM")&" - "&TEXT(AK8,"DD MMM") -> W1 01 Sep - 07 Sep | R7: ="W2"&CHAR(10)&TEXT(AK8+1,"DD MMM")&" - "&TEXT(AL8,"DD MMM") -> W2 08 Sep - 14 Sep | T7: ="W3"&CHAR(10)&TEXT(AL8+1,"DD MMM")&" - "&TEXT(AM8,"DD MMM") -> W3 15 Sep - 21 Sep | V7: ="W4"&CHAR(10)&TEXT(AM8+1,"DD MMM")&" - "&TEXT(AN8,"DD MMM") -> W4 22 Sep - 28 Sep | X7: w1 | Y7: w2 | Z7: w3 | AA7: w4 | AB7: 周度趋势线 Trendline Mingguan | AI7: update V | AJ7: =DATE(2026,9,AI8) -> 46268
L8: 网点总数 Total DP | M8: 已及时上传 Upload Tepat Waktu | N8: 上传及时率 Persentase Upload Tepat Waktu | P8: 已及时上传 Upload Tepat Waktu | Q8: 上传及时率 Persentase Upload Tepat Waktu | R8: 已及时上传 Upload Tepat Waktu | S8: 上传及时率 Persentase Upload Tepat Waktu | T8: 已及时上传 Upload Tepat Waktu | U8: 上传及时率 Persentase Upload Tepat Waktu | V8: 已上传 Yang Sudah Upload | W8: 上传及时率 Persentase Upload Tepat Waktu | AC8: 网点总数 Total DP | AD8: 已及时上传 Upload Tepat Waktu | AE8: 上传及时率 Persentase Upload Tepat Waktu | AH8: =AI8 -> 3 | AI8: 3 | AJ8: =EOMONTH(AJ7,-1)+1 -> 46266 | AK8: =AJ8+6 -> 46272 | AL8: =AK8+7 -> 46279 | AM8: =AL8+7 -> 46286 | AN8: =AM8+7 -> 46293 | AP8: =MIN(7,MAX(0,$AH$8)) -> 3 | AQ8: =MIN(7,MAX(0,$AH$8-7)) -> 0 | AR8: =MIN(7,MAX(0,$AH$8-14)) -> 0 | AS8: =MAX(0,$AH$8-21) -> 0
F9: 合计 Total | J9: - | K9: 0.9 | L9: =SUM(L10:L35) -> 2687 | M9: =SUM(M10:M35) -> 2508 | N9: =M9/L9 -> 0.93338295 | O9: =SUM(O10:O35) -> 18809 | P9: =SUM(P10:P35) -> 7437 | Q9: =IFERROR(P9/($L9*$AP$8),0) -> 0.92259025 | R9: =SUM(R10:R35) -> 0 | S9: =IFERROR(T9/($L9*$AR$8),0) -> 0 | T9: =SUM(T10:T35) -> 0 | U9: =IFERROR(T9/($L9*$AR$8),0) -> 0 | V9: =SUM(V10:V35) -> 0 | W9: =IFERROR(V9/($L9*$AS$8),0) -> 0 | X9: =Q9 -> 0.92259025 | AC9: =SUM(AC10:AC35) -> 8061 | AD9: =SUM(AD10:AD35) -> 7437 | AE9: =AD9/AC9 -> 0.92259025 | AK9: =AK8+1 -> 46273 | AL9: =AL8+1 -> 46280 | AM9: =AM8+1 -> 46287 | AN9: =AN8+1 -> 46294 | AP9: W1 | AQ9: W2 | AR9: W3 | AS9: W4
F10: =_xlfn.XLOOKUP(I10,[1]Lembar1!$A:$A,[1]Lembar1!$C:$C,0) -> Sumatra 苏门答腊岛 | G10: JAMBI占碑 | H10: a | I10: AGENT07 | J10: =_xlfn.RANK.AVG(AE10,$AE$10:$AE$19) -> 1 | K10: 0.9 | L10: =COUNTIFS('All DP'!A:A,I10,'All DP'!D:D,"<>"&"Tidak") -> 64 | M10: =COUNTIFS('Raw data yang sudah upload'!B:B,I10,'Raw data yang sudah upload'!A:A,$AJ$7,'Raw data yang sudah upload'!W:W,"Masih",'Raw data yang sudah upload'!X:X,"YA") -> 63 | N10: =M10/L10 -> 0.984375 | O10: =$L10*7 -> 448 | P10: =COUNTIFS('Raw data yang sudah upload'!$B:$B,$I10,'Raw data yang sudah upload'!$A:$A,">="&$AJ$8,'Raw data yang sudah upload'!$A:$A,"<="&$AK$8,'Raw data yang sudah upload'!W:W,"Masih",'Raw data yang sudah upload'!X:X,"YA") -> 191 | Q10: =IFERROR(P10/($L10*$AP$8),0) -> 0.99479167 | R10: =COUNTIFS('Raw data yang sudah upload'!$B:$B,$I10,'Raw data yang sudah upload'!$A:$A,">="&$AK$9,'Raw data yang sudah upload'!$A:$A,"<="&$AL$8,'Raw data yang sudah upload'!W:W,"Masih",'Raw data yang sudah upload'!X:X,"YA") -> 0 | S10: =IFERROR(R10/($L10*$AQ$8),0) -> 0 | T10: =COUNTIFS('Raw data yang sudah upload'!$B:$B,$I10,'Raw data yang sudah upload'!$A:$A,">="&$AL$9,'Raw data yang sudah upload'!$A:$A,"<="&$AM$8,'Raw data yang sudah upload'!W:W,"Masih",'Raw data yang sudah upload'!X:X,"YA") -> 0 | U10: =IFERROR(T10/($L10*$AR$8),0) -> 0 | V10: =COUNTIFS('Raw data yang sudah upload'!$B:$B,$I10,'Raw data yang sudah upload'!$A:$A,">="&$AM$9,'Raw data yang sudah upload'!$A:$A,"<="&$AN$8,'Raw data yang sudah upload'!W:W,"Masih",'Raw data yang sudah upload'!X:X,"YA") -> 0 | W10: =IFERROR(V10/($L10*$AS$8),0) -> 0 | X10: =Q10 -> 0.99479167 | AC10: =L10*$AH$8 -> 192 | AD10: =COUNTIFS('Raw data yang sudah upload'!B:B,I10,'Raw data yang sudah upload'!A:A,">="&$AJ$8,'Raw data yang sudah upload'!A:A,"<="&$AJ$7,'Raw data yang sudah upload'!W:W,"Masih",'Raw data yang sudah upload'!X:X,"YA") -> 191 | AE10: =AD10/AC10 -> 0.99479167
B11: 01-08 - 07-08 (W2) | G11: BENGKULU明古鲁 | H11: a | I11: AGENT09 | J11: =_xlfn.RANK.AVG(AE11,$AE$10:$AE$19) -> 2 | K11: 0.9 | L11: =COUNTIFS('All DP'!A:A,I11,'All DP'!D:D,"<>"&"Tidak") -> 41 | M11: =COUNTIFS('Raw data yang sudah upload'!B:B,I11,'Raw data yang sudah upload'!A:A,$AJ$7,'Raw data yang sudah upload'!W:W,"Masih",'Raw data yang sudah upload'!X:X,"YA") -> 40 | N11: =M11/L11 -> 0.97560976 | O11: =$L11*7 -> 287 | P11: =COUNTIFS('Raw data yang sudah upload'!$B:$B,$I11,'Raw data yang sudah upload'!$A:$A,">="&$AJ$8,'Raw data yang sudah upload'!$A:$A,"<="&$AK$8,'Raw data yang sudah upload'!W:W,"Masih",'Raw data yang sudah upload'!X:X,"YA") -> 120 | Q11: =IFERROR(P11/($L11*$AP$8),0) -> 0.97560976 | R11: =COUNTIFS('Raw data yang sudah upload'!$B:$B,$I11,'Raw data yang sudah upload'!$A:$A,">="&$AK$9,'Raw data yang sudah upload'!$A:$A,"<="&$AL$8,'Raw data yang sudah upload'!W:W,"Masih",'Raw data yang sudah upload'!X:X,"YA") -> 0 | S11: =IFERROR(R11/($L11*$AQ$8),0) -> 0 | T11: =COUNTIFS('Raw data yang sudah upload'!$B:$B,$I11,'Raw data yang sudah upload'!$A:$A,">="&$AL$9,'Raw data yang sudah upload'!$A:$A,"<="&$AM$8,'Raw data yang sudah upload'!W:W,"Masih",'Raw data yang sudah upload'!X:X,"YA") -> 0 | U11: =IFERROR(T11/($L11*$AR$8),0) -> 0 | V11: =COUNTIFS('Raw data yang sudah upload'!$B:$B,$I11,'Raw data yang sudah upload'!$A:$A,">="&$AM$9,'Raw data yang sudah upload'!$A:$A,"<="&$AN$8,'Raw data yang sudah upload'!W:W,"Masih",'Raw data yang sudah upload'!X:X,"YA") -> 0 | W11: =IFERROR(V11/($L11*$AS$8),0) -> 0 | X11: =Q11 -> 0.97560976 | AC11: =L11*$AH$8 -> 123 | AD11: =COUNTIFS('Raw data yang sudah upload'!B:B,I11,'Raw data yang sudah upload'!A:A,">="&$AJ$8,'Raw data yang sudah upload'!A:A,"<="&$AJ$7,'Raw data yang sudah upload'!W:W,"Masih",'Raw data yang sudah upload'!X:X,"YA") -> 120 | AE11: =AD11/AC11 -> 0.97560976
G12: PADANG巴东 | H12: a | I12: AGENT06 | J12: =_xlfn.RANK.AVG(AE12,$AE$10:$AE$19) -> 7 | K12: 0.9 | L12: =COUNTIFS('All DP'!A:A,I12,'All DP'!D:D,"<>"&"Tidak") -> 56 | M12: =COUNTIFS('Raw data yang sudah upload'!B:B,I12,'Raw data yang sudah upload'!A:A,$AJ$7,'Raw data yang sudah upload'!W:W,"Masih",'Raw data yang sudah upload'!X:X,"YA") -> 54 | N12: =M12/L12 -> 0.96428571 | O12: =$L12*7 -> 392 | P12: =COUNTIFS('Raw data yang sudah upload'!$B:$B,$I12,'Raw data yang sudah upload'!$A:$A,">="&$AJ$8,'Raw data yang sudah upload'!$A:$A,"<="&$AK$8,'Raw data yang sudah upload'!W:W,"Masih",'Raw data yang sudah upload'!X:X,"YA") -> 155 | Q12: =IFERROR(P12/($L12*$AP$8),0) -> 0.92261905 | R12: =COUNTIFS('Raw data yang sudah upload'!$B:$B,$I12,'Raw data yang sudah upload'!$A:$A,">="&$AK$9,'Raw data yang sudah upload'!$A:$A,"<="&$AL$8,'Raw data yang sudah upload'!W:W,"Masih",'Raw data yang sudah upload'!X:X,"YA") -> 0 | S12: =IFERROR(R12/($L12*$AQ$8),0) -> 0 | T12: =COUNTIFS('Raw data yang sudah upload'!$B:$B,$I12,'Raw data yang sudah upload'!$A:$A,">="&$AL$9,'Raw data yang sudah upload'!$A:$A,"<="&$AM$8,'Raw data yang sudah upload'!W:W,"Masih",'Raw data yang sudah upload'!X:X,"YA") -> 0 | U12: =IFERROR(T12/($L12*$AR$8),0) -> 0 | V12: =COUNTIFS('Raw data yang sudah upload'!$B:$B,$I12,'Raw data yang sudah upload'!$A:$A,">="&$AM$9,'Raw data yang sudah upload'!$A:$A,"<="&$AN$8,'Raw data yang sudah upload'!W:W,"Masih",'Raw data yang sudah upload'!X:X,"YA") -> 0 | W12: =IFERROR(V12/($L12*$AS$8),0) -> 0 | X12: =Q12 -> 0.92261905 | AC12: =L12*$AH$8 -> 168 | AD12: =COUNTIFS('Raw data yang sudah upload'!B:B,I12,'Raw data yang sudah upload'!A:A,">="&$AJ$8,'Raw data yang sudah upload'!A:A,"<="&$AJ$7,'Raw data yang sudah upload'!W:W,"Masih",'Raw data yang sudah upload'!X:X,"YA") -> 155 | AE12: =AD12/AC12 -> 0.92261905
G13: PEKANBARU北干巴鲁 | H13: a | I13: AGENT04 | J13: =_xlfn.RANK.AVG(AE13,$AE$10:$AE$19) -> 8 | K13: 0.9 | L13: =COUNTIFS('All DP'!A:A,I13,'All DP'!D:D,"<>"&"Tidak") -> 72 | M13: =COUNTIFS('Raw data yang sudah upload'!B:B,I13,'Raw data yang sudah upload'!A:A,$AJ$7,'Raw data yang sudah upload'!W:W,"Masih",'Raw data yang sudah upload'!X:X,"YA") -> 69 | N13: =M13/L13 -> 0.95833333 | O13: =$L13*7 -> 504 | P13: =COUNTIFS('Raw data yang sudah upload'!$B:$B,$I13,'Raw data yang sudah upload'!$A:$A,">="&$AJ$8,'Raw data yang sudah upload'!$A:$A,"<="&$AK$8,'Raw data yang sudah upload'!W:W,"Masih",'Raw data yang sudah upload'!X:X,"YA") -> 193 | Q13: =IFERROR(P13/($L13*$AP$8),0) -> 0.89351852 | R13: =COUNTIFS('Raw data yang sudah upload'!$B:$B,$I13,'Raw data yang sudah upload'!$A:$A,">="&$AK$9,'Raw data yang sudah upload'!$A:$A,"<="&$AL$8,'Raw data yang sudah upload'!W:W,"Masih",'Raw data yang sudah upload'!X:X,"YA") -> 0 | S13: =IFERROR(R13/($L13*$AQ$8),0) -> 0 | T13: =COUNTIFS('Raw data yang sudah upload'!$B:$B,$I13,'Raw data yang sudah upload'!$A:$A,">="&$AL$9,'Raw data yang sudah upload'!$A:$A,"<="&$AM$8,'Raw data yang sudah upload'!W:W,"Masih",'Raw data yang sudah upload'!X:X,"YA") -> 0 | U13: =IFERROR(T13/($L13*$AR$8),0) -> 0 | V13: =COUNTIFS('Raw data yang sudah upload'!$B:$B,$I13,'Raw data yang sudah upload'!$A:$A,">="&$AM$9,'Raw data yang sudah upload'!$A:$A,"<="&$AN$8,'Raw data yang sudah upload'!W:W,"Masih",'Raw data yang sudah upload'!X:X,"YA") -> 0 | W13: =IFERROR(V13/($L13*$AS$8),0) -> 0 | X13: =Q13 -> 0.89351852 | AC13: =L13*$AH$8 -> 216 | AD13: =COUNTIFS('Raw data yang sudah upload'!B:B,I13,'Raw data yang sudah upload'!A:A,">="&$AJ$8,'Raw data yang sudah upload'!A:A,"<="&$AJ$7,'Raw data yang sudah upload'!W:W,"Masih",'Raw data yang sudah upload'!X:X,"YA") -> 193 | AE13: =AD13/AC13 -> 0.89351852
G14: LAMPUNG班达楠榜 | H14: a | I14: AGENT10 | J14: =_xlfn.RANK.AVG(AE14,$AE$10:$AE$19) -> 3 | K14: 0.9 | L14: =COUNTIFS('All DP'!A:A,I14,'All DP'!D:D,"<>"&"Tidak") -> 68 | M14: =COUNTIFS('Raw data yang sudah upload'!B:B,I14,'Raw data yang sudah upload'!A:A,$AJ$7,'Raw data yang sudah upload'!W:W,"Masih",'Raw data yang sudah upload'!X:X,"YA") -> 65 | N14: =M14/L14 -> 0.95588235 | O14: =$L14*7 -> 476 | P14: =COUNTIFS('Raw data yang sudah upload'!$B:$B,$I14,'Raw data yang sudah upload'!$A:$A,">="&$AJ$8,'Raw data yang sudah upload'!$A:$A,"<="&$AK$8,'Raw data yang sudah upload'!W:W,"Masih",'Raw data yang sudah upload'!X:X,"YA") -> 196 | Q14: =IFERROR(P14/($L14*$AP$8),0) -> 0.96078431 | R14: =COUNTIFS('Raw data yang sudah upload'!$B:$B,$I14,'Raw data yang sudah upload'!$A:$A,">="&$AK$9,'Raw data yang sudah upload'!$A:$A,"<="&$AL$8,'Raw data yang sudah upload'!W:W,"Masih",'Raw data yang sudah upload'!X:X,"YA") -> 0 | S14: =IFERROR(R14/($L14*$AQ$8),0) -> 0 | T14: =COUNTIFS('Raw data yang sudah upload'!$B:$B,$I14,'Raw data yang sudah upload'!$A:$A,">="&$AL$9,'Raw data yang sudah upload'!$A:$A,"<="&$AM$8,'Raw data yang sudah upload'!W:W,"Masih",'Raw data yang sudah upload'!X:X,"YA") -> 0 | U14: =IFERROR(T14/($L14*$AR$8),0) -> 0 | V14: =COUNTIFS('Raw data yang sudah upload'!$B:$B,$I14,'Raw data yang sudah upload'!$A:$A,">="&$AM$9,'Raw data yang sudah upload'!$A:$A,"<="&$AN$8,'Raw data yang sudah upload'!W:W,"Masih",'Raw data yang sudah upload'!X:X,"YA") -> 0 | W14: =IFERROR(V14/($L14*$AS$8),0) -> 0 | X14: =Q14 -> 0.96078431 | AC14: =L14*$AH$8 -> 204 | AD14: =COUNTIFS('Raw data yang sudah upload'!B:B,I14,'Raw data yang sudah upload'!A:A,">="&$AJ$8,'Raw data yang sudah upload'!A:A,"<="&$AJ$7,'Raw data yang sudah upload'!W:W,"Masih",'Raw data yang sudah upload'!X:X,"YA") -> 196 | AE14: =AD14/AC14 -> 0.96078431 | AJ14: =MIN(7,MAX(0,$AH$8)) -> 3
G15: PALEMBANG巨港 | H15: a | I15: AGENT08 | J15: =_xlfn.RANK.AVG(AE15,$AE$10:$AE$19) -> 5 | K15: 0.9 | L15: =COUNTIFS('All DP'!A:A,I15,'All DP'!D:D,"<>"&"Tidak") -> 121 | M15: =COUNTIFS('Raw data yang sudah upload'!B:B,I15,'Raw data yang sudah upload'!A:A,$AJ$7,'Raw data yang sudah upload'!W:W,"Masih",'Raw data yang sudah upload'!X:X,"YA") -> 114 | N15: =M15/L15 -> 0.94214876 | O15: =$L15*7 -> 847 | P15: =COUNTIFS('Raw data yang sudah upload'!$B:$B,$I15,'Raw data yang sudah upload'!$A:$A,">="&$AJ$8,'Raw data yang sudah upload'!$A:$A,"<="&$AK$8,'Raw data yang sudah upload'!W:W,"Masih",'Raw data yang sudah upload'!X:X,"YA") -> 342 | Q15: =IFERROR(P15/($L15*$AP$8),0) -> 0.94214876 | R15: =COUNTIFS('Raw data yang sudah upload'!$B:$B,$I15,'Raw data yang sudah upload'!$A:$A,">="&$AK$9,'Raw data yang sudah upload'!$A:$A,"<="&$AL$8,'Raw data yang sudah upload'!W:W,"Masih",'Raw data yang sudah upload'!X:X,"YA") -> 0 | S15: =IFERROR(R15/($L15*$AQ$8),0) -> 0 | T15: =COUNTIFS('Raw data yang sudah upload'!$B:$B,$I15,'Raw data yang sudah upload'!$A:$A,">="&$AL$9,'Raw data yang sudah upload'!$A:$A,"<="&$AM$8,'Raw data yang sudah upload'!W:W,"Masih",'Raw data yang sudah upload'!X:X,"YA") -> 0 | U15: =IFERROR(T15/($L15*$AR$8),0) -> 0 | V15: =COUNTIFS('Raw data yang sudah upload'!$B:$B,$I15,'Raw data yang sudah upload'!$A:$A,">="&$AM$9,'Raw data yang sudah upload'!$A:$A,"<="&$AN$8,'Raw data yang sudah upload'!W:W,"Masih",'Raw data yang sudah upload'!X:X,"YA") -> 0 | W15: =IFERROR(V15/($L15*$AS$8),0) -> 0 | X15: =Q15 -> 0.94214876 | AC15: =L15*$AH$8 -> 363 | AD15: =COUNTIFS('Raw data yang sudah upload'!B:B,I15,'Raw data yang sudah upload'!A:A,">="&$AJ$8,'Raw data yang sudah upload'!A:A,"<="&$AJ$7,'Raw data yang sudah upload'!W:W,"Masih",'Raw data yang sudah upload'!X:X,"YA") -> 342 | AE15: =AD15/AC15 -> 0.94214876
G16: BATAM巴淡 | H16: a | I16: AGENT05 | J16: =_xlfn.RANK.AVG(AE16,$AE$10:$AE$19) -> 4 | K16: 0.9 | L16: =COUNTIFS('All DP'!A:A,I16,'All DP'!D:D,"<>"&"Tidak") -> 30 | M16: =COUNTIFS('Raw data yang sudah upload'!B:B,I16,'Raw data yang sudah upload'!A:A,$AJ$7,'Raw data yang sudah upload'!W:W,"Masih",'Raw data yang sudah upload'!X:X,"YA") -> 28 | N16: =M16/L16 -> 0.93333333 | O16: =$L16*7 -> 210 | P16: =COUNTIFS('Raw data yang sudah upload'!$B:$B,$I16,'Raw data yang sudah upload'!$A:$A,">="&$AJ$8,'Raw data yang sudah upload'!$A:$A,"<="&$AK$8,'Raw data yang sudah upload'!W:W,"Masih",'Raw data yang sudah upload'!X:X,"YA") -> 85 | Q16: =IFERROR(P16/($L16*$AP$8),0) -> 0.94444444 | R16: =COUNTIFS('Raw data yang sudah upload'!$B:$B,$I16,'Raw data yang sudah upload'!$A:$A,">="&$AK$9,'Raw data yang sudah upload'!$A:$A,"<="&$AL$8,'Raw data yang sudah upload'!W:W,"Masih",'Raw data yang sudah upload'!X:X,"YA") -> 0 | S16: =IFERROR(R16/($L16*$AQ$8),0) -> 0 | T16: =COUNTIFS('Raw data yang sudah upload'!$B:$B,$I16,'Raw data yang sudah upload'!$A:$A,">="&$AL$9,'Raw data yang sudah upload'!$A:$A,"<="&$AM$8,'Raw data yang sudah upload'!W:W,"Masih",'Raw data yang sudah upload'!X:X,"YA") -> 0 | U16: =IFERROR(T16/($L16*$AR$8),0) -> 0 | V16: =COUNTIFS('Raw data yang sudah upload'!$B:$B,$I16,'Raw data yang sudah upload'!$A:$A,">="&$AM$9,'Raw data yang sudah upload'!$A:$A,"<="&$AN$8,'Raw data yang sudah upload'!W:W,"Masih",'Raw data yang sudah upload'!X:X,"YA") -> 0 | W16: =IFERROR(V16/($L16*$AS$8),0) -> 0 | X16: =Q16 -> 0.94444444 | AC16: =L16*$AH$8 -> 90 | AD16: =COUNTIFS('Raw data yang sudah upload'!B:B,I16,'Raw data yang sudah upload'!A:A,">="&$AJ$8,'Raw data yang sudah upload'!A:A,"<="&$AJ$7,'Raw data yang sudah upload'!W:W,"Masih",'Raw data yang sudah upload'!X:X,"YA") -> 85 | AE16: =AD16/AC16 -> 0.94444444
G17: RANTAU兰道 | H17: a | I17: AGENT03 | J17: =_xlfn.RANK.AVG(AE17,$AE$10:$AE$19) -> 10 | K17: 0.9 | L17: =COUNTIFS('All DP'!A:A,I17,'All DP'!D:D,"<>"&"Tidak") -> 74 | M17: =COUNTIFS('Raw data yang sudah upload'!B:B,I17,'Raw data yang sudah upload'!A:A,$AJ$7,'Raw data yang sudah upload'!W:W,"Masih",'Raw data yang sudah upload'!X:X,"YA") -> 69 | N17: =M17/L17 -> 0.93243243 | O17: =$L17*7 -> 518 | P17: =COUNTIFS('Raw data yang sudah upload'!$B:$B,$I17,'Raw data yang sudah upload'!$A:$A,">="&$AJ$8,'Raw data yang sudah upload'!$A:$A,"<="&$AK$8,'Raw data yang sudah upload'!W:W,"Masih",'Raw data yang sudah upload'!X:X,"YA") -> 178 | Q17: =IFERROR(P17/($L17*$AP$8),0) -> 0.8018018 | R17: =COUNTIFS('Raw data yang sudah upload'!$B:$B,$I17,'Raw data yang sudah upload'!$A:$A,">="&$AK$9,'Raw data yang sudah upload'!$A:$A,"<="&$AL$8,'Raw data yang sudah upload'!W:W,"Masih",'Raw data yang sudah upload'!X:X,"YA") -> 0 | S17: =IFERROR(R17/($L17*$AQ$8),0) -> 0 | T17: =COUNTIFS('Raw data yang sudah upload'!$B:$B,$I17,'Raw data yang sudah upload'!$A:$A,">="&$AL$9,'Raw data yang sudah upload'!$A:$A,"<="&$AM$8,'Raw data yang sudah upload'!W:W,"Masih",'Raw data yang sudah upload'!X:X,"YA") -> 0 | U17: =IFERROR(T17/($L17*$AR$8),0) -> 0 | V17: =COUNTIFS('Raw data yang sudah upload'!$B:$B,$I17,'Raw data yang sudah upload'!$A:$A,">="&$AM$9,'Raw data yang sudah upload'!$A:$A,"<="&$AN$8,'Raw data yang sudah upload'!W:W,"Masih",'Raw data yang sudah upload'!X:X,"YA") -> 0 | W17: =IFERROR(V17/($L17*$AS$8),0) -> 0 | X17: =Q17 -> 0.8018018 | AC17: =L17*$AH$8 -> 222 | AD17: =COUNTIFS('Raw data yang sudah upload'!B:B,I17,'Raw data yang sudah upload'!A:A,">="&$AJ$8,'Raw data yang sudah upload'!A:A,"<="&$AJ$7,'Raw data yang sudah upload'!W:W,"Masih",'Raw data yang sudah upload'!X:X,"YA") -> 178 | AE17: =AD17/AC17 -> 0.8018018
G18: ACEH班达亚奇 | H18: a | I18: AGENT01 | J18: =_xlfn.RANK.AVG(AE18,$AE$10:$AE$19) -> 6 | K18: 0.9 | L18: =COUNTIFS('All DP'!A:A,I18,'All DP'!D:D,"<>"&"Tidak") -> 54 | M18: =COUNTIFS('Raw data yang sudah upload'!B:B,I18,'Raw data yang sudah upload'!A:A,$AJ$7,'Raw data yang sudah upload'!W:W,"Masih",'Raw data yang sudah upload'!X:X,"YA") -> 50 | N18: =M18/L18 -> 0.92592593 | O18: =$L18*7 -> 378 | P18: =COUNTIFS('Raw data yang sudah upload'!$B:$B,$I18,'Raw data yang sudah upload'!$A:$A,">="&$AJ$8,'Raw data yang sudah upload'!$A:$A,"<="&$AK$8,'Raw data yang sudah upload'!W:W,"Masih",'Raw data yang sudah upload'!X:X,"YA") -> 151 | Q18: =IFERROR(P18/($L18*$AP$8),0) -> 0.93209877 | R18: =COUNTIFS('Raw data yang sudah upload'!$B:$B,$I18,'Raw data yang sudah upload'!$A:$A,">="&$AK$9,'Raw data yang sudah upload'!$A:$A,"<="&$AL$8,'Raw data yang sudah upload'!W:W,"Masih",'Raw data yang sudah upload'!X:X,"YA") -> 0 | S18: =IFERROR(R18/($L18*$AQ$8),0) -> 0 | T18: =COUNTIFS('Raw data yang sudah upload'!$B:$B,$I18,'Raw data yang sudah upload'!$A:$A,">="&$AL$9,'Raw data yang sudah upload'!$A:$A,"<="&$AM$8,'Raw data yang sudah upload'!W:W,"Masih",'Raw data yang sudah upload'!X:X,"YA") -> 0 | U18: =IFERROR(T18/($L18*$AR$8),0) -> 0 | V18: =COUNTIFS('Raw data yang sudah upload'!$B:$B,$I18,'Raw data yang sudah upload'!$A:$A,">="&$AM$9,'Raw data yang sudah upload'!$A:$A,"<="&$AN$8,'Raw data yang sudah upload'!W:W,"Masih",'Raw data yang sudah upload'!X:X,"YA") -> 0 | W18: =IFERROR(V18/($L18*$AS$8),0) -> 0 | X18: =Q18 -> 0.93209877 | AC18: =L18*$AH$8 -> 162 | AD18: =COUNTIFS('Raw data yang sudah upload'!B:B,I18,'Raw data yang sudah upload'!A:A,">="&$AJ$8,'Raw data yang sudah upload'!A:A,"<="&$AJ$7,'Raw data yang sudah upload'!W:W,"Masih",'Raw data yang sudah upload'!X:X,"YA") -> 151 | AE18: =AD18/AC18 -> 0.93209877
G19: MEDAN棉兰 | H19: a | I19: AGENT02 | J19: =_xlfn.RANK.AVG(AE19,$AE$10:$AE$19) -> 9 | K19: 0.9 | L19: =COUNTIFS('All DP'!A:A,I19,'All DP'!D:D,"<>"&"Tidak") -> 60 | M19: =COUNTIFS('Raw data yang sudah upload'!B:B,I19,'Raw data yang sudah upload'!A:A,$AJ$7,'Raw data yang sudah upload'!W:W,"Masih",'Raw data yang sudah upload'!X:X,"YA") -> 51 | N19: =M19/L19 -> 0.85 | O19: =$L19*7 -> 420 | P19: =COUNTIFS('Raw data yang sudah upload'!$B:$B,$I19,'Raw data yang sudah upload'!$A:$A,">="&$AJ$8,'Raw data yang sudah upload'!$A:$A,"<="&$AK$8,'Raw data yang sudah upload'!W:W,"Masih",'Raw data yang sudah upload'!X:X,"YA") -> 159 | Q19: =IFERROR(P19/($L19*$AP$8),0) -> 0.88333333 | R19: =COUNTIFS('Raw data yang sudah upload'!$B:$B,$I19,'Raw data yang sudah upload'!$A:$A,">="&$AK$9,'Raw data yang sudah upload'!$A:$A,"<="&$AL$8,'Raw data yang sudah upload'!W:W,"Masih",'Raw data yang sudah upload'!X:X,"YA") -> 0 | S19: =IFERROR(R19/($L19*$AQ$8),0) -> 0 | T19: =COUNTIFS('Raw data yang sudah upload'!$B:$B,$I19,'Raw data yang sudah upload'!$A:$A,">="&$AL$9,'Raw data yang sudah upload'!$A:$A,"<="&$AM$8,'Raw data yang sudah upload'!W:W,"Masih",'Raw data yang sudah upload'!X:X,"YA") -> 0 | U19: =IFERROR(T19/($L19*$AR$8),0) -> 0 | V19: =COUNTIFS('Raw data yang sudah upload'!$B:$B,$I19,'Raw data yang sudah upload'!$A:$A,">="&$AM$9,'Raw data yang sudah upload'!$A:$A,"<="&$AN$8,'Raw data yang sudah upload'!W:W,"Masih",'Raw data yang sudah upload'!X:X,"YA") -> 0 | W19: =IFERROR(V19/($L19*$AS$8),0) -> 0 | X19: =Q19 -> 0.88333333 | AC19: =L19*$AH$8 -> 180 | AD19: =COUNTIFS('Raw data yang sudah upload'!B:B,I19,'Raw data yang sudah upload'!A:A,">="&$AJ$8,'Raw data yang sudah upload'!A:A,"<="&$AJ$7,'Raw data yang sudah upload'!W:W,"Masih",'Raw data yang sudah upload'!X:X,"YA") -> 159 | AE19: =AD19/AC19 -> 0.88333333
F20: =_xlfn.XLOOKUP(I20,[1]Lembar1!$A:$A,[1]Lembar1!$C:$C,0) -> Jawa 爪哇岛 | G20: DEPOK德波 | H20: b | I20: AGENT15 | J20: =_xlfn.RANK.AVG(AE20,$AE$20:$AE$28) -> 1 | K20: 0.9 | L20: =COUNTIFS('All DP'!A:A,I20,'All DP'!D:D,"<>"&"Tidak") -> 12 | M20: =COUNTIFS('Raw data yang sudah upload'!B:B,I20,'Raw data yang sudah upload'!A:A,$AJ$7,'Raw data yang sudah upload'!W:W,"Masih",'Raw data yang sudah upload'!X:X,"YA") -> 12 | N20: =M20/L20 -> 1 | O20: =$L20*7 -> 84 | P20: =COUNTIFS('Raw data yang sudah upload'!$B:$B,$I20,'Raw data yang sudah upload'!$A:$A,">="&$AJ$8,'Raw data yang sudah upload'!$A:$A,"<="&$AK$8,'Raw data yang sudah upload'!W:W,"Masih",'Raw data yang sudah upload'!X:X,"YA") -> 36 | Q20: =IFERROR(P20/($L20*$AP$8),0) -> 1 | R20: =COUNTIFS('Raw data yang sudah upload'!$B:$B,$I20,'Raw data yang sudah upload'!$A:$A,">="&$AK$9,'Raw data yang sudah upload'!$A:$A,"<="&$AL$8,'Raw data yang sudah upload'!W:W,"Masih",'Raw data yang sudah upload'!X:X,"YA") -> 0 | S20: =IFERROR(R20/($L20*$AQ$8),0) -> 0 | T20: =COUNTIFS('Raw data yang sudah upload'!$B:$B,$I20,'Raw data yang sudah upload'!$A:$A,">="&$AL$9,'Raw data yang sudah upload'!$A:$A,"<="&$AM$8,'Raw data yang sudah upload'!W:W,"Masih",'Raw data yang sudah upload'!X:X,"YA") -> 0 | U20: =IFERROR(T20/($L20*$AR$8),0) -> 0 | V20: =COUNTIFS('Raw data yang sudah upload'!$B:$B,$I20,'Raw data yang sudah upload'!$A:$A,">="&$AM$9,'Raw data yang sudah upload'!$A:$A,"<="&$AN$8,'Raw data yang sudah upload'!W:W,"Masih",'Raw data yang sudah upload'!X:X,"YA") -> 0 | W20: =IFERROR(V20/($L20*$AS$8),0) -> 0 | X20: =Q20 -> 1 | AC20: =L20*$AH$8 -> 36 | AD20: =COUNTIFS('Raw data yang sudah upload'!B:B,I20,'Raw data yang sudah upload'!A:A,">="&$AJ$8,'Raw data yang sudah upload'!A:A,"<="&$AJ$7,'Raw data yang sudah upload'!W:W,"Masih",'Raw data yang sudah upload'!X:X,"YA") -> 36 | AE20: =AD20/AC20 -> 1
G21: JAKARTA雅加达 | H21: b | I21: AGENT40 | J21: =_xlfn.RANK.AVG(AE21,$AE$20:$AE$28) -> 3 | K21: 0.9 | L21: =COUNTIFS('All DP'!A:A,I21,'All DP'!D:D,"<>"&"Tidak") -> 71 | M21: =COUNTIFS('Raw data yang sudah upload'!B:B,I21,'Raw data yang sudah upload'!A:A,$AJ$7,'Raw data yang sudah upload'!W:W,"Masih",'Raw data yang sudah upload'!X:X,"YA") -> 71 | N21: =M21/L21 -> 1 | O21: =$L21*7 -> 497 | P21: =COUNTIFS('Raw data yang sudah upload'!$B:$B,$I21,'Raw data yang sudah upload'!$A:$A,">="&$AJ$8,'Raw data yang sudah upload'!$A:$A,"<="&$AK$8,'Raw data yang sudah upload'!W:W,"Masih",'Raw data yang sudah upload'!X:X,"YA") -> 210 | Q21: =IFERROR(P21/($L21*$AP$8),0) -> 0.98591549 | R21: =COUNTIFS('Raw data yang sudah upload'!$B:$B,$I21,'Raw data yang sudah upload'!$A:$A,">="&$AK$9,'Raw data yang sudah upload'!$A:$A,"<="&$AL$8,'Raw data yang sudah upload'!W:W,"Masih",'Raw data yang sudah upload'!X:X,"YA") -> 0 | S21: =IFERROR(R21/($L21*$AQ$8),0) -> 0 | T21: =COUNTIFS('Raw data yang sudah upload'!$B:$B,$I21,'Raw data yang sudah upload'!$A:$A,">="&$AL$9,'Raw data yang sudah upload'!$A:$A,"<="&$AM$8,'Raw data yang sudah upload'!W:W,"Masih",'Raw data yang sudah upload'!X:X,"YA") -> 0 | U21: =IFERROR(T21/($L21*$AR$8),0) -> 0 | V21: =COUNTIFS('Raw data yang sudah upload'!$B:$B,$I21,'Raw data yang sudah upload'!$A:$A,">="&$AM$9,'Raw data yang sudah upload'!$A:$A,"<="&$AN$8,'Raw data yang sudah upload'!W:W,"Masih",'Raw data yang sudah upload'!X:X,"YA") -> 0 | W21: =IFERROR(V21/($L21*$AS$8),0) -> 0 | X21: =Q21 -> 0.98591549 | AC21: =L21*$AH$8 -> 213 | AD21: =COUNTIFS('Raw data yang sudah upload'!B:B,I21,'Raw data yang sudah upload'!A:A,">="&$AJ$8,'Raw data yang sudah upload'!A:A,"<="&$AJ$7,'Raw data yang sudah upload'!W:W,"Masih",'Raw data yang sudah upload'!X:X,"YA") -> 210 | AE21: =AD21/AC21 -> 0.98591549
G22: SEMARANG三宝垄 | H22: b | I22: AGENT17 | J22: =_xlfn.RANK.AVG(AE22,$AE$20:$AE$28) -> 2 | K22: 0.9 | L22: =COUNTIFS('All DP'!A:A,I22,'All DP'!D:D,"<>"&"Tidak") -> 238 | M22: =COUNTIFS('Raw data yang sudah upload'!B:B,I22,'Raw data yang sudah upload'!A:A,$AJ$7,'Raw data yang sudah upload'!W:W,"Masih",'Raw data yang sudah upload'!X:X,"YA") -> 237 | N22: =M22/L22 -> 0.99579832 | O22: =$L22*7 -> 1666 | P22: =COUNTIFS('Raw data yang sudah upload'!$B:$B,$I22,'Raw data yang sudah upload'!$A:$A,">="&$AJ$8,'Raw data yang sudah upload'!$A:$A,"<="&$AK$8,'Raw data yang sudah upload'!W:W,"Masih",'Raw data yang sudah upload'!X:X,"YA") -> 713 | Q22: =IFERROR(P22/($L22*$AP$8),0) -> 0.99859944 | R22: =COUNTIFS('Raw data yang sudah upload'!$B:$B,$I22,'Raw data yang sudah upload'!$A:$A,">="&$AK$9,'Raw data yang sudah upload'!$A:$A,"<="&$AL$8,'Raw data yang sudah upload'!W:W,"Masih",'Raw data yang sudah upload'!X:X,"YA") -> 0 | S22: =IFERROR(R22/($L22*$AQ$8),0) -> 0 | T22: =COUNTIFS('Raw data yang sudah upload'!$B:$B,$I22,'Raw data yang sudah upload'!$A:$A,">="&$AL$9,'Raw data yang sudah upload'!$A:$A,"<="&$AM$8,'Raw data yang sudah upload'!W:W,"Masih",'Raw data yang sudah upload'!X:X,"YA") -> 0 | U22: =IFERROR(T22/($L22*$AR$8),0) -> 0 | V22: =COUNTIFS('Raw data yang sudah upload'!$B:$B,$I22,'Raw data yang sudah upload'!$A:$A,">="&$AM$9,'Raw data yang sudah upload'!$A:$A,"<="&$AN$8,'Raw data yang sudah upload'!W:W,"Masih",'Raw data yang sudah upload'!X:X,"YA") -> 0 | W22: =IFERROR(V22/($L22*$AS$8),0) -> 0 | X22: =Q22 -> 0.99859944 | AC22: =L22*$AH$8 -> 714 | AD22: =COUNTIFS('Raw data yang sudah upload'!B:B,I22,'Raw data yang sudah upload'!A:A,">="&$AJ$8,'Raw data yang sudah upload'!A:A,"<="&$AJ$7,'Raw data yang sudah upload'!W:W,"Masih",'Raw data yang sudah upload'!X:X,"YA") -> 713 | AE22: =AD22/AC22 -> 0.99859944
G23: TANGERANG唐格朗 | H23: b | I23: AGENT12 | J23: =_xlfn.RANK.AVG(AE23,$AE$20:$AE$28) -> 4 | K23: 0.9 | L23: =COUNTIFS('All DP'!A:A,I23,'All DP'!D:D,"<>"&"Tidak") -> 104 | M23: =COUNTIFS('Raw data yang sudah upload'!B:B,I23,'Raw data yang sudah upload'!A:A,$AJ$7,'Raw data yang sudah upload'!W:W,"Masih",'Raw data yang sudah upload'!X:X,"YA") -> 101 | N23: =M23/L23 -> 0.97115385 | O23: =$L23*7 -> 728 | P23: =COUNTIFS('Raw data yang sudah upload'!$B:$B,$I23,'Raw data yang sudah upload'!$A:$A,">="&$AJ$8,'Raw data yang sudah upload'!$A:$A,"<="&$AK$8,'Raw data yang sudah upload'!W:W,"Masih",'Raw data yang sudah upload'!X:X,"YA") -> 304 | Q23: =IFERROR(P23/($L23*$AP$8),0) -> 0.97435897 | R23: =COUNTIFS('Raw data yang sudah upload'!$B:$B,$I23,'Raw data yang sudah upload'!$A:$A,">="&$AK$9,'Raw data yang sudah upload'!$A:$A,"<="&$AL$8,'Raw data yang sudah upload'!W:W,"Masih",'Raw data yang sudah upload'!X:X,"YA") -> 0 | S23: =IFERROR(R23/($L23*$AQ$8),0) -> 0 | T23: =COUNTIFS('Raw data yang sudah upload'!$B:$B,$I23,'Raw data yang sudah upload'!$A:$A,">="&$AL$9,'Raw data yang sudah upload'!$A:$A,"<="&$AM$8,'Raw data yang sudah upload'!W:W,"Masih",'Raw data yang sudah upload'!X:X,"YA") -> 0 | U23: =IFERROR(T23/($L23*$AR$8),0) -> 0 | V23: =COUNTIFS('Raw data yang sudah upload'!$B:$B,$I23,'Raw data yang sudah upload'!$A:$A,">="&$AM$9,'Raw data yang sudah upload'!$A:$A,"<="&$AN$8,'Raw data yang sudah upload'!W:W,"Masih",'Raw data yang sudah upload'!X:X,"YA") -> 0 | W23: =IFERROR(V23/($L23*$AS$8),0) -> 0 | X23: =Q23 -> 0.97435897 | AC23: =L23*$AH$8 -> 312 | AD23: =COUNTIFS('Raw data yang sudah upload'!B:B,I23,'Raw data yang sudah upload'!A:A,">="&$AJ$8,'Raw data yang sudah upload'!A:A,"<="&$AJ$7,'Raw data yang sudah upload'!W:W,"Masih",'Raw data yang sudah upload'!X:X,"YA") -> 304 | AE23: =AD23/AC23 -> 0.97435897
G24: BOGOR茂物 | H24: b | I24: AGENT14 | J24: =_xlfn.RANK.AVG(AE24,$AE$20:$AE$28) -> 6 | K24: 0.9 | L24: =COUNTIFS('All DP'!A:A,I24,'All DP'!D:D,"<>"&"Tidak") -> 45 | M24: =COUNTIFS('Raw data yang sudah upload'!B:B,I24,'Raw data yang sudah upload'!A:A,$AJ$7,'Raw data yang sudah upload'!W:W,"Masih",'Raw data yang sudah upload'!X:X,"YA") -> 43 | N24: =M24/L24 -> 0.95555556 | O24: =$L24*7 -> 315 | P24: =COUNTIFS('Raw data yang sudah upload'!$B:$B,$I24,'Raw data yang sudah upload'!$A:$A,">="&$AJ$8,'Raw data yang sudah upload'!$A:$A,"<="&$AK$8,'Raw data yang sudah upload'!W:W,"Masih",'Raw data yang sudah upload'!X:X,"YA") -> 128 | Q24: =IFERROR(P24/($L24*$AP$8),0) -> 0.94814815 | R24: =COUNTIFS('Raw data yang sudah upload'!$B:$B,$I24,'Raw data yang sudah upload'!$A:$A,">="&$AK$9,'Raw data yang sudah upload'!$A:$A,"<="&$AL$8,'Raw data yang sudah upload'!W:W,"Masih",'Raw data yang sudah upload'!X:X,"YA") -> 0 | S24: =IFERROR(R24/($L24*$AQ$8),0) -> 0 | T24: =COUNTIFS('Raw data yang sudah upload'!$B:$B,$I24,'Raw data yang sudah upload'!$A:$A,">="&$AL$9,'Raw data yang sudah upload'!$A:$A,"<="&$AM$8,'Raw data yang sudah upload'!W:W,"Masih",'Raw data yang sudah upload'!X:X,"YA") -> 0 | U24: =IFERROR(T24/($L24*$AR$8),0) -> 0 | V24: =COUNTIFS('Raw data yang sudah upload'!$B:$B,$I24,'Raw data yang sudah upload'!$A:$A,">="&$AM$9,'Raw data yang sudah upload'!$A:$A,"<="&$AN$8,'Raw data yang sudah upload'!W:W,"Masih",'Raw data yang sudah upload'!X:X,"YA") -> 0 | W24: =IFERROR(V24/($L24*$AS$8),0) -> 0 | X24: =Q24 -> 0.94814815 | AC24: =L24*$AH$8 -> 135 | AD24: =COUNTIFS('Raw data yang sudah upload'!B:B,I24,'Raw data yang sudah upload'!A:A,">="&$AJ$8,'Raw data yang sudah upload'!A:A,"<="&$AJ$7,'Raw data yang sudah upload'!W:W,"Masih",'Raw data yang sudah upload'!X:X,"YA") -> 128 | AE24: =AD24/AC24 -> 0.94814815
G25: YOGYAKARTA日惹 | H25: b | I25: AGENT18 | J25: =_xlfn.RANK.AVG(AE25,$AE$20:$AE$28) -> 5 | K25: 0.9 | L25: =COUNTIFS('All DP'!A:A,I25,'All DP'!D:D,"<>"&"Tidak") -> 128 | M25: =COUNTIFS('Raw data yang sudah upload'!B:B,I25,'Raw data yang sudah upload'!A:A,$AJ$7,'Raw data yang sudah upload'!W:W,"Masih",'Raw data yang sudah upload'!X:X,"YA") -> 122 | N25: =M25/L25 -> 0.953125 | O25: =$L25*7 -> 896 | P25: =COUNTIFS('Raw data yang sudah upload'!$B:$B,$I25,'Raw data yang sudah upload'!$A:$A,">="&$AJ$8,'Raw data yang sudah upload'!$A:$A,"<="&$AK$8,'Raw data yang sudah upload'!W:W,"Masih",'Raw data yang sudah upload'!X:X,"YA") -> 365 | Q25: =IFERROR(P25/($L25*$AP$8),0) -> 0.95052083 | R25: =COUNTIFS('Raw data yang sudah upload'!$B:$B,$I25,'Raw data yang sudah upload'!$A:$A,">="&$AK$9,'Raw data yang sudah upload'!$A:$A,"<="&$AL$8,'Raw data yang sudah upload'!W:W,"Masih",'Raw data yang sudah upload'!X:X,"YA") -> 0 | S25: =IFERROR(R25/($L25*$AQ$8),0) -> 0 | T25: =COUNTIFS('Raw data yang sudah upload'!$B:$B,$I25,'Raw data yang sudah upload'!$A:$A,">="&$AL$9,'Raw data yang sudah upload'!$A:$A,"<="&$AM$8,'Raw data yang sudah upload'!W:W,"Masih",'Raw data yang sudah upload'!X:X,"YA") -> 0 | U25: =IFERROR(T25/($L25*$AR$8),0) -> 0 | V25: =COUNTIFS('Raw data yang sudah upload'!$B:$B,$I25,'Raw data yang sudah upload'!$A:$A,">="&$AM$9,'Raw data yang sudah upload'!$A:$A,"<="&$AN$8,'Raw data yang sudah upload'!W:W,"Masih",'Raw data yang sudah upload'!X:X,"YA") -> 0 | W25: =IFERROR(V25/($L25*$AS$8),0) -> 0 | X25: =Q25 -> 0.95052083 | AC25: =L25*$AH$8 -> 384 | AD25: =COUNTIFS('Raw data yang sudah upload'!B:B,I25,'Raw data yang sudah upload'!A:A,">="&$AJ$8,'Raw data yang sudah upload'!A:A,"<="&$AJ$7,'Raw data yang sudah upload'!W:W,"Masih",'Raw data yang sudah upload'!X:X,"YA") -> 365 | AE25: =AD25/AC25 -> 0.95052083
G26: BEKASI勿加西 | H26: b | I26: AGENT13 | J26: =_xlfn.RANK.AVG(AE26,$AE$20:$AE$28) -> 7 | K26: 0.9 | L26: =COUNTIFS('All DP'!A:A,I26,'All DP'!D:D,"<>"&"Tidak") -> 40 | M26: =COUNTIFS('Raw data yang sudah upload'!B:B,I26,'Raw data yang sudah upload'!A:A,$AJ$7,'Raw data yang sudah upload'!W:W,"Masih",'Raw data yang sudah upload'!X:X,"YA") -> 38 | N26: =M26/L26 -> 0.95 | O26: =$L26*7 -> 280 | P26: =COUNTIFS('Raw data yang sudah upload'!$B:$B,$I26,'Raw data yang sudah upload'!$A:$A,">="&$AJ$8,'Raw data yang sudah upload'!$A:$A,"<="&$AK$8,'Raw data yang sudah upload'!W:W,"Masih",'Raw data yang sudah upload'!X:X,"YA") -> 109 | Q26: =IFERROR(P26/($L26*$AP$8),0) -> 0.90833333 | R26: =COUNTIFS('Raw data yang sudah upload'!$B:$B,$I26,'Raw data yang sudah upload'!$A:$A,">="&$AK$9,'Raw data yang sudah upload'!$A:$A,"<="&$AL$8,'Raw data yang sudah upload'!W:W,"Masih",'Raw data yang sudah upload'!X:X,"YA") -> 0 | S26: =IFERROR(R26/($L26*$AQ$8),0) -> 0 | T26: =COUNTIFS('Raw data yang sudah upload'!$B:$B,$I26,'Raw data yang sudah upload'!$A:$A,">="&$AL$9,'Raw data yang sudah upload'!$A:$A,"<="&$AM$8,'Raw data yang sudah upload'!W:W,"Masih",'Raw data yang sudah upload'!X:X,"YA") -> 0 | U26: =IFERROR(T26/($L26*$AR$8),0) -> 0 | V26: =COUNTIFS('Raw data yang sudah upload'!$B:$B,$I26,'Raw data yang sudah upload'!$A:$A,">="&$AM$9,'Raw data yang sudah upload'!$A:$A,"<="&$AN$8,'Raw data yang sudah upload'!W:W,"Masih",'Raw data yang sudah upload'!X:X,"YA") -> 0 | W26: =IFERROR(V26/($L26*$AS$8),0) -> 0 | X26: =Q26 -> 0.90833333 | AC26: =L26*$AH$8 -> 120 | AD26: =COUNTIFS('Raw data yang sudah upload'!B:B,I26,'Raw data yang sudah upload'!A:A,">="&$AJ$8,'Raw data yang sudah upload'!A:A,"<="&$AJ$7,'Raw data yang sudah upload'!W:W,"Masih",'Raw data yang sudah upload'!X:X,"YA") -> 109 | AE26: =AD26/AC26 -> 0.90833333
G27: SURABAYA泗水 | H27: b | I27: AGENT19 | J27: =_xlfn.RANK.AVG(AE27,$AE$20:$AE$28) -> 8 | K27: 0.9 | L27: =COUNTIFS('All DP'!A:A,I27,'All DP'!D:D,"<>"&"Tidak") -> 339 | M27: =COUNTIFS('Raw data yang sudah upload'!B:B,I27,'Raw data yang sudah upload'!A:A,$AJ$7,'Raw data yang sudah upload'!W:W,"Masih",'Raw data yang sudah upload'!X:X,"YA") -> 295 | N27: =M27/L27 -> 0.87020649 | O27: =$L27*7 -> 2373 | P27: =COUNTIFS('Raw data yang sudah upload'!$B:$B,$I27,'Raw data yang sudah upload'!$A:$A,">="&$AJ$8,'Raw data yang sudah upload'!$A:$A,"<="&$AK$8,'Raw data yang sudah upload'!W:W,"Masih",'Raw data yang sudah upload'!X:X,"YA") -> 846 | Q27: =IFERROR(P27/($L27*$AP$8),0) -> 0.83185841 | R27: =COUNTIFS('Raw data yang sudah upload'!$B:$B,$I27,'Raw data yang sudah upload'!$A:$A,">="&$AK$9,'Raw data yang sudah upload'!$A:$A,"<="&$AL$8,'Raw data yang sudah upload'!W:W,"Masih",'Raw data yang sudah upload'!X:X,"YA") -> 0 | S27: =IFERROR(R27/($L27*$AQ$8),0) -> 0 | T27: =COUNTIFS('Raw data yang sudah upload'!$B:$B,$I27,'Raw data yang sudah upload'!$A:$A,">="&$AL$9,'Raw data yang sudah upload'!$A:$A,"<="&$AM$8,'Raw data yang sudah upload'!W:W,"Masih",'Raw data yang sudah upload'!X:X,"YA") -> 0 | U27: =IFERROR(T27/($L27*$AR$8),0) -> 0 | V27: =COUNTIFS('Raw data yang sudah upload'!$B:$B,$I27,'Raw data yang sudah upload'!$A:$A,">="&$AM$9,'Raw data yang sudah upload'!$A:$A,"<="&$AN$8,'Raw data yang sudah upload'!W:W,"Masih",'Raw data yang sudah upload'!X:X,"YA") -> 0 | W27: =IFERROR(V27/($L27*$AS$8),0) -> 0 | X27: =Q27 -> 0.83185841 | AC27: =L27*$AH$8 -> 1017 | AD27: =COUNTIFS('Raw data yang sudah upload'!B:B,I27,'Raw data yang sudah upload'!A:A,">="&$AJ$8,'Raw data yang sudah upload'!A:A,"<="&$AJ$7,'Raw data yang sudah upload'!W:W,"Masih",'Raw data yang sudah upload'!X:X,"YA") -> 846 | AE27: =AD27/AC27 -> 0.83185841
G28: BANDUNG万隆 | H28: b | I28: AGENT16 | J28: =_xlfn.RANK.AVG(AE28,$AE$20:$AE$28) -> 9 | K28: 0.9 | L28: =COUNTIFS('All DP'!A:A,I28,'All DP'!D:D,"<>"&"Tidak") -> 293 | M28: =COUNTIFS('Raw data yang sudah upload'!B:B,I28,'Raw data yang sudah upload'!A:A,$AJ$7,'Raw data yang sudah upload'!W:W,"Masih",'Raw data yang sudah upload'!X:X,"YA") -> 246 | N28: =M28/L28 -> 0.83959044 | O28: =$L28*7 -> 2051 | P28: =COUNTIFS('Raw data yang sudah upload'!$B:$B,$I28,'Raw data yang sudah upload'!$A:$A,">="&$AJ$8,'Raw data yang sudah upload'!$A:$A,"<="&$AK$8,'Raw data yang sudah upload'!W:W,"Masih",'Raw data yang sudah upload'!X:X,"YA") -> 724 | Q28: =IFERROR(P28/($L28*$AP$8),0) -> 0.82366325 | R28: =COUNTIFS('Raw data yang sudah upload'!$B:$B,$I28,'Raw data yang sudah upload'!$A:$A,">="&$AK$9,'Raw data yang sudah upload'!$A:$A,"<="&$AL$8,'Raw data yang sudah upload'!W:W,"Masih",'Raw data yang sudah upload'!X:X,"YA") -> 0 | S28: =IFERROR(R28/($L28*$AQ$8),0) -> 0 | T28: =COUNTIFS('Raw data yang sudah upload'!$B:$B,$I28,'Raw data yang sudah upload'!$A:$A,">="&$AL$9,'Raw data yang sudah upload'!$A:$A,"<="&$AM$8,'Raw data yang sudah upload'!W:W,"Masih",'Raw data yang sudah upload'!X:X,"YA") -> 0 | U28: =IFERROR(T28/($L28*$AR$8),0) -> 0 | V28: =COUNTIFS('Raw data yang sudah upload'!$B:$B,$I28,'Raw data yang sudah upload'!$A:$A,">="&$AM$9,'Raw data yang sudah upload'!$A:$A,"<="&$AN$8,'Raw data yang sudah upload'!W:W,"Masih",'Raw data yang sudah upload'!X:X,"YA") -> 0 | W28: =IFERROR(V28/($L28*$AS$8),0) -> 0 | X28: =Q28 -> 0.82366325 | AC28: =L28*$AH$8 -> 879 | AD28: =COUNTIFS('Raw data yang sudah upload'!B:B,I28,'Raw data yang sudah upload'!A:A,">="&$AJ$8,'Raw data yang sudah upload'!A:A,"<="&$AJ$7,'Raw data yang sudah upload'!W:W,"Masih",'Raw data yang sudah upload'!X:X,"YA") -> 724 | AE28: =AD28/AC28 -> 0.82366325
F29: =_xlfn.XLOOKUP(I29,[1]Lembar1!$A:$A,[1]Lembar1!$C:$C,0) -> Kalimantan, Sulawesi & Bali 加里曼丹、苏拉威西 和巴厘岛 | G29: BALIKPAPAN巴厘巴板 | H29: c | I29: AGENT27 | J29: =_xlfn.RANK.AVG(AE29,$AE$29:$AE$35) -> 1 | K29: 0.9 | L29: =COUNTIFS('All DP'!A:A,I29,'All DP'!D:D,"<>"&"Tidak") -> 164 | M29: =COUNTIFS('Raw data yang sudah upload'!B:B,I29,'Raw data yang sudah upload'!A:A,$AJ$7,'Raw data yang sudah upload'!W:W,"Masih",'Raw data yang sudah upload'!X:X,"YA") -> 164 | N29: =M29/L29 -> 1 | O29: =$L29*7 -> 1148 | P29: =COUNTIFS('Raw data yang sudah upload'!$B:$B,$I29,'Raw data yang sudah upload'!$A:$A,">="&$AJ$8,'Raw data yang sudah upload'!$A:$A,"<="&$AK$8,'Raw data yang sudah upload'!W:W,"Masih",'Raw data yang sudah upload'!X:X,"YA") -> 492 | Q29: =IFERROR(P29/($L29*$AP$8),0) -> 1 | R29: =COUNTIFS('Raw data yang sudah upload'!$B:$B,$I29,'Raw data yang sudah upload'!$A:$A,">="&$AK$9,'Raw data yang sudah upload'!$A:$A,"<="&$AL$8,'Raw data yang sudah upload'!W:W,"Masih",'Raw data yang sudah upload'!X:X,"YA") -> 0 | S29: =IFERROR(R29/($L29*$AQ$8),0) -> 0 | T29: =COUNTIFS('Raw data yang sudah upload'!$B:$B,$I29,'Raw data yang sudah upload'!$A:$A,">="&$AL$9,'Raw data yang sudah upload'!$A:$A,"<="&$AM$8,'Raw data yang sudah upload'!W:W,"Masih",'Raw data yang sudah upload'!X:X,"YA") -> 0 | U29: =IFERROR(T29/($L29*$AR$8),0) -> 0 | V29: =COUNTIFS('Raw data yang sudah upload'!$B:$B,$I29,'Raw data yang sudah upload'!$A:$A,">="&$AM$9,'Raw data yang sudah upload'!$A:$A,"<="&$AN$8,'Raw data yang sudah upload'!W:W,"Masih",'Raw data yang sudah upload'!X:X,"YA") -> 0 | W29: =IFERROR(V29/($L29*$AS$8),0) -> 0 | X29: =Q29 -> 1 | AC29: =L29*$AH$8 -> 492 | AD29: =COUNTIFS('Raw data yang sudah upload'!B:B,I29,'Raw data yang sudah upload'!A:A,">="&$AJ$8,'Raw data yang sudah upload'!A:A,"<="&$AJ$7,'Raw data yang sudah upload'!W:W,"Masih",'Raw data yang sudah upload'!X:X,"YA") -> 492 | AE29: =AD29/AC29 -> 1
G30: MAKASSAR望加锡 | H30: c | I30: AGENT22 | J30: =_xlfn.RANK.AVG(AE30,$AE$29:$AE$35) -> 2 | K30: 0.9 | L30: =COUNTIFS('All DP'!A:A,I30,'All DP'!D:D,"<>"&"Tidak") -> 148 | M30: =COUNTIFS('Raw data yang sudah upload'!B:B,I30,'Raw data yang sudah upload'!A:A,$AJ$7,'Raw data yang sudah upload'!W:W,"Masih",'Raw data yang sudah upload'!X:X,"YA") -> 148 | N30: =M30/L30 -> 1 | O30: =$L30*7 -> 1036 | P30: =COUNTIFS('Raw data yang sudah upload'!$B:$B,$I30,'Raw data yang sudah upload'!$A:$A,">="&$AJ$8,'Raw data yang sudah upload'!$A:$A,"<="&$AK$8,'Raw data yang sudah upload'!W:W,"Masih",'Raw data yang sudah upload'!X:X,"YA") -> 443 | Q30: =IFERROR(P30/($L30*$AP$8),0) -> 0.99774775 | R30: =COUNTIFS('Raw data yang sudah upload'!$B:$B,$I30,'Raw data yang sudah upload'!$A:$A,">="&$AK$9,'Raw data yang sudah upload'!$A:$A,"<="&$AL$8,'Raw data yang sudah upload'!W:W,"Masih",'Raw data yang sudah upload'!X:X,"YA") -> 0 | S30: =IFERROR(R30/($L30*$AQ$8),0) -> 0 | T30: =COUNTIFS('Raw data yang sudah upload'!$B:$B,$I30,'Raw data yang sudah upload'!$A:$A,">="&$AL$9,'Raw data yang sudah upload'!$A:$A,"<="&$AM$8,'Raw data yang sudah upload'!W:W,"Masih",'Raw data yang sudah upload'!X:X,"YA") -> 0 | U30: =IFERROR(T30/($L30*$AR$8),0) -> 0 | V30: =COUNTIFS('Raw data yang sudah upload'!$B:$B,$I30,'Raw data yang sudah upload'!$A:$A,">="&$AM$9,'Raw data yang sudah upload'!$A:$A,"<="&$AN$8,'Raw data yang sudah upload'!W:W,"Masih",'Raw data yang sudah upload'!X:X,"YA") -> 0 | W30: =IFERROR(V30/($L30*$AS$8),0) -> 0 | X30: =Q30 -> 0.99774775 | AC30: =L30*$AH$8 -> 444 | AD30: =COUNTIFS('Raw data yang sudah upload'!B:B,I30,'Raw data yang sudah upload'!A:A,">="&$AJ$8,'Raw data yang sudah upload'!A:A,"<="&$AJ$7,'Raw data yang sudah upload'!W:W,"Masih",'Raw data yang sudah upload'!X:X,"YA") -> 443 | AE30: =AD30/AC30 -> 0.99774775
G31: MANADO美娜多 | H31: c | I31: AGENT23 | J31: =_xlfn.RANK.AVG(AE31,$AE$29:$AE$35) -> 3 | K31: 0.9 | L31: =COUNTIFS('All DP'!A:A,I31,'All DP'!D:D,"<>"&"Tidak") -> 175 | M31: =COUNTIFS('Raw data yang sudah upload'!B:B,I31,'Raw data yang sudah upload'!A:A,$AJ$7,'Raw data yang sudah upload'!W:W,"Masih",'Raw data yang sudah upload'!X:X,"YA") -> 175 | N31: =M31/L31 -> 1 | O31: =$L31*7 -> 1225 | P31: =COUNTIFS('Raw data yang sudah upload'!$B:$B,$I31,'Raw data yang sudah upload'!$A:$A,">="&$AJ$8,'Raw data yang sudah upload'!$A:$A,"<="&$AK$8,'Raw data yang sudah upload'!W:W,"Masih",'Raw data yang sudah upload'!X:X,"YA") -> 514 | Q31: =IFERROR(P31/($L31*$AP$8),0) -> 0.97904762 | R31: =COUNTIFS('Raw data yang sudah upload'!$B:$B,$I31,'Raw data yang sudah upload'!$A:$A,">="&$AK$9,'Raw data yang sudah upload'!$A:$A,"<="&$AL$8,'Raw data yang sudah upload'!W:W,"Masih",'Raw data yang sudah upload'!X:X,"YA") -> 0 | S31: =IFERROR(R31/($L31*$AQ$8),0) -> 0 | T31: =COUNTIFS('Raw data yang sudah upload'!$B:$B,$I31,'Raw data yang sudah upload'!$A:$A,">="&$AL$9,'Raw data yang sudah upload'!$A:$A,"<="&$AM$8,'Raw data yang sudah upload'!W:W,"Masih",'Raw data yang sudah upload'!X:X,"YA") -> 0 | U31: =IFERROR(T31/($L31*$AR$8),0) -> 0 | V31: =COUNTIFS('Raw data yang sudah upload'!$B:$B,$I31,'Raw data yang sudah upload'!$A:$A,">="&$AM$9,'Raw data yang sudah upload'!$A:$A,"<="&$AN$8,'Raw data yang sudah upload'!W:W,"Masih",'Raw data yang sudah upload'!X:X,"YA") -> 0 | W31: =IFERROR(V31/($L31*$AS$8),0) -> 0 | X31: =Q31 -> 0.97904762 | AC31: =L31*$AH$8 -> 525 | AD31: =COUNTIFS('Raw data yang sudah upload'!B:B,I31,'Raw data yang sudah upload'!A:A,">="&$AJ$8,'Raw data yang sudah upload'!A:A,"<="&$AJ$7,'Raw data yang sudah upload'!W:W,"Masih",'Raw data yang sudah upload'!X:X,"YA") -> 514 | AE31: =AD31/AC31 -> 0.97904762
G32: PONTIANAK坤甸 | H32: c | I32: AGENT26 | J32: =_xlfn.RANK.AVG(AE32,$AE$29:$AE$35) -> 4 | K32: 0.9 | L32: =COUNTIFS('All DP'!A:A,I32,'All DP'!D:D,"<>"&"Tidak") -> 70 | M32: =COUNTIFS('Raw data yang sudah upload'!B:B,I32,'Raw data yang sudah upload'!A:A,$AJ$7,'Raw data yang sudah upload'!W:W,"Masih",'Raw data yang sudah upload'!X:X,"YA") -> 69 | N32: =M32/L32 -> 0.98571429 | O32: =$L32*7 -> 490 | P32: =COUNTIFS('Raw data yang sudah upload'!$B:$B,$I32,'Raw data yang sudah upload'!$A:$A,">="&$AJ$8,'Raw data yang sudah upload'!$A:$A,"<="&$AK$8,'Raw data yang sudah upload'!W:W,"Masih",'Raw data yang sudah upload'!X:X,"YA") -> 205 | Q32: =IFERROR(P32/($L32*$AP$8),0) -> 0.97619048 | R32: =COUNTIFS('Raw data yang sudah upload'!$B:$B,$I32,'Raw data yang sudah upload'!$A:$A,">="&$AK$9,'Raw data yang sudah upload'!$A:$A,"<="&$AL$8,'Raw data yang sudah upload'!W:W,"Masih",'Raw data yang sudah upload'!X:X,"YA") -> 0 | S32: =IFERROR(R32/($L32*$AQ$8),0) -> 0 | T32: =COUNTIFS('Raw data yang sudah upload'!$B:$B,$I32,'Raw data yang sudah upload'!$A:$A,">="&$AL$9,'Raw data yang sudah upload'!$A:$A,"<="&$AM$8,'Raw data yang sudah upload'!W:W,"Masih",'Raw data yang sudah upload'!X:X,"YA") -> 0 | U32: =IFERROR(T32/($L32*$AR$8),0) -> 0 | V32: =COUNTIFS('Raw data yang sudah upload'!$B:$B,$I32,'Raw data yang sudah upload'!$A:$A,">="&$AM$9,'Raw data yang sudah upload'!$A:$A,"<="&$AN$8,'Raw data yang sudah upload'!W:W,"Masih",'Raw data yang sudah upload'!X:X,"YA") -> 0 | W32: =IFERROR(V32/($L32*$AS$8),0) -> 0 | X32: =Q32 -> 0.97619048 | AC32: =L32*$AH$8 -> 210 | AD32: =COUNTIFS('Raw data yang sudah upload'!B:B,I32,'Raw data yang sudah upload'!A:A,">="&$AJ$8,'Raw data yang sudah upload'!A:A,"<="&$AJ$7,'Raw data yang sudah upload'!W:W,"Masih",'Raw data yang sudah upload'!X:X,"YA") -> 205 | AE32: =AD32/AC32 -> 0.97619048
G33: BALI巴厘 | H33: c | I33: AGENT21 | J33: =_xlfn.RANK.AVG(AE33,$AE$29:$AE$35) -> 5 | K33: 0.9 | L33: =COUNTIFS('All DP'!A:A,I33,'All DP'!D:D,"<>"&"Tidak") -> 164 | M33: =COUNTIFS('Raw data yang sudah upload'!B:B,I33,'Raw data yang sudah upload'!A:A,$AJ$7,'Raw data yang sudah upload'!W:W,"Masih",'Raw data yang sudah upload'!X:X,"YA") -> 139 | N33: =M33/L33 -> 0.84756098 | O33: =$L33*7 -> 1148 | P33: =COUNTIFS('Raw data yang sudah upload'!$B:$B,$I33,'Raw data yang sudah upload'!$A:$A,">="&$AJ$8,'Raw data yang sudah upload'!$A:$A,"<="&$AK$8,'Raw data yang sudah upload'!W:W,"Masih",'Raw data yang sudah upload'!X:X,"YA") -> 435 | Q33: =IFERROR(P33/($L33*$AP$8),0) -> 0.88414634 | R33: =COUNTIFS('Raw data yang sudah upload'!$B:$B,$I33,'Raw data yang sudah upload'!$A:$A,">="&$AK$9,'Raw data yang sudah upload'!$A:$A,"<="&$AL$8,'Raw data yang sudah upload'!W:W,"Masih",'Raw data yang sudah upload'!X:X,"YA") -> 0 | S33: =IFERROR(R33/($L33*$AQ$8),0) -> 0 | T33: =COUNTIFS('Raw data yang sudah upload'!$B:$B,$I33,'Raw data yang sudah upload'!$A:$A,">="&$AL$9,'Raw data yang sudah upload'!$A:$A,"<="&$AM$8,'Raw data yang sudah upload'!W:W,"Masih",'Raw data yang sudah upload'!X:X,"YA") -> 0 | U33: =IFERROR(T33/($L33*$AR$8),0) -> 0 | V33: =COUNTIFS('Raw data yang sudah upload'!$B:$B,$I33,'Raw data yang sudah upload'!$A:$A,">="&$AM$9,'Raw data yang sudah upload'!$A:$A,"<="&$AN$8,'Raw data yang sudah upload'!W:W,"Masih",'Raw data yang sudah upload'!X:X,"YA") -> 0 | W33: =IFERROR(V33/($L33*$AS$8),0) -> 0 | X33: =Q33 -> 0.88414634 | AC33: =L33*$AH$8 -> 492 | AD33: =COUNTIFS('Raw data yang sudah upload'!B:B,I33,'Raw data yang sudah upload'!A:A,">="&$AJ$8,'Raw data yang sudah upload'!A:A,"<="&$AJ$7,'Raw data yang sudah upload'!W:W,"Masih",'Raw data yang sudah upload'!X:X,"YA") -> 435 | AE33: =AD33/AC33 -> 0.88414634
G34: SAMPIT桑皮特 | H34: c | I34: AGENT25 | J34: =_xlfn.RANK.AVG(AE34,$AE$29:$AE$35) -> 6 | K34: 0.9 | L34: =COUNTIFS('All DP'!A:A,I34,'All DP'!D:D,"<>"&"Tidak") -> 43 | M34: =COUNTIFS('Raw data yang sudah upload'!B:B,I34,'Raw data yang sudah upload'!A:A,$AJ$7,'Raw data yang sudah upload'!W:W,"Masih",'Raw data yang sudah upload'!X:X,"YA") -> 36 | N34: =M34/L34 -> 0.8372093 | O34: =$L34*7 -> 301 | P34: =COUNTIFS('Raw data yang sudah upload'!$B:$B,$I34,'Raw data yang sudah upload'!$A:$A,">="&$AJ$8,'Raw data yang sudah upload'!$A:$A,"<="&$AK$8,'Raw data yang sudah upload'!W:W,"Masih",'Raw data yang sudah upload'!X:X,"YA") -> 114 | Q34: =IFERROR(P34/($L34*$AP$8),0) -> 0.88372093 | R34: =COUNTIFS('Raw data yang sudah upload'!$B:$B,$I34,'Raw data yang sudah upload'!$A:$A,">="&$AK$9,'Raw data yang sudah upload'!$A:$A,"<="&$AL$8,'Raw data yang sudah upload'!W:W,"Masih",'Raw data yang sudah upload'!X:X,"YA") -> 0 | S34: =IFERROR(R34/($L34*$AQ$8),0) -> 0 | T34: =COUNTIFS('Raw data yang sudah upload'!$B:$B,$I34,'Raw data yang sudah upload'!$A:$A,">="&$AL$9,'Raw data yang sudah upload'!$A:$A,"<="&$AM$8,'Raw data yang sudah upload'!W:W,"Masih",'Raw data yang sudah upload'!X:X,"YA") -> 0 | U34: =IFERROR(T34/($L34*$AR$8),0) -> 0 | V34: =COUNTIFS('Raw data yang sudah upload'!$B:$B,$I34,'Raw data yang sudah upload'!$A:$A,">="&$AM$9,'Raw data yang sudah upload'!$A:$A,"<="&$AN$8,'Raw data yang sudah upload'!W:W,"Masih",'Raw data yang sudah upload'!X:X,"YA") -> 0 | W34: =IFERROR(V34/($L34*$AS$8),0) -> 0 | X34: =Q34 -> 0.88372093 | AC34: =L34*$AH$8 -> 129 | AD34: =COUNTIFS('Raw data yang sudah upload'!B:B,I34,'Raw data yang sudah upload'!A:A,">="&$AJ$8,'Raw data yang sudah upload'!A:A,"<="&$AJ$7,'Raw data yang sudah upload'!W:W,"Masih",'Raw data yang sudah upload'!X:X,"YA") -> 114 | AE34: =AD34/AC34 -> 0.88372093
G35: PAPUA巴布亚 | H35: c | I35: AGENT28 | J35: =_xlfn.RANK.AVG(AE35,$AE$29:$AE$35) -> 7 | K35: 0.9 | L35: =COUNTIFS('All DP'!A:A,I35,'All DP'!D:D,"<>"&"Tidak") -> 13 | M35: =COUNTIFS('Raw data yang sudah upload'!B:B,I35,'Raw data yang sudah upload'!A:A,$AJ$7,'Raw data yang sudah upload'!W:W,"Masih",'Raw data yang sudah upload'!X:X,"YA") -> 9 | N35: =M35/L35 -> 0.69230769 | O35: =$L35*7 -> 91 | P35: =COUNTIFS('Raw data yang sudah upload'!$B:$B,$I35,'Raw data yang sudah upload'!$A:$A,">="&$AJ$8,'Raw data yang sudah upload'!$A:$A,"<="&$AK$8,'Raw data yang sudah upload'!W:W,"Masih",'Raw data yang sudah upload'!X:X,"YA") -> 29 | Q35: =IFERROR(P35/($L35*$AP$8),0) -> 0.74358974 | R35: =COUNTIFS('Raw data yang sudah upload'!$B:$B,$I35,'Raw data yang sudah upload'!$A:$A,">="&$AK$9,'Raw data yang sudah upload'!$A:$A,"<="&$AL$8,'Raw data yang sudah upload'!W:W,"Masih",'Raw data yang sudah upload'!X:X,"YA") -> 0 | S35: =IFERROR(R35/($L35*$AQ$8),0) -> 0 | T35: =COUNTIFS('Raw data yang sudah upload'!$B:$B,$I35,'Raw data yang sudah upload'!$A:$A,">="&$AL$9,'Raw data yang sudah upload'!$A:$A,"<="&$AM$8,'Raw data yang sudah upload'!W:W,"Masih",'Raw data yang sudah upload'!X:X,"YA") -> 0 | U35: =IFERROR(T35/($L35*$AR$8),0) -> 0 | V35: =COUNTIFS('Raw data yang sudah upload'!$B:$B,$I35,'Raw data yang sudah upload'!$A:$A,">="&$AM$9,'Raw data yang sudah upload'!$A:$A,"<="&$AN$8,'Raw data yang sudah upload'!W:W,"Masih",'Raw data yang sudah upload'!X:X,"YA") -> 0 | W35: =IFERROR(V35/($L35*$AS$8),0) -> 0 | X35: =Q35 -> 0.74358974 | AC35: =L35*$AH$8 -> 39 | AD35: =COUNTIFS('Raw data yang sudah upload'!B:B,I35,'Raw data yang sudah upload'!A:A,">="&$AJ$8,'Raw data yang sudah upload'!A:A,"<="&$AJ$7,'Raw data yang sudah upload'!W:W,"Masih",'Raw data yang sudah upload'!X:X,"YA") -> 29 | AE35: =AD35/AC35 -> 0.74358974

Sheet Status Upload
A1: Status = Tidak maka tidak di wajib upload
A3: Agent | B3: Kode DP | C3: nama dp | D3: status | E3: Status Upload | F3: Status upload hari ini | G3: status upload tepat waktu (15:00) | H3: 3 | I3: =INT(J3) -> 46268 | J3: =DATE(2026,9,H3) -> 46268
A4: AGENT10 | B4: BLM14 | C4: WAY_TUBA | D4: Masih | E4: =IF(F4=0,"Tidak Upload","Sudah Upload") -> Sudah Upload | F4: =COUNTIFS('Raw data yang sudah upload'!C:C,C4,'Raw data yang sudah upload'!A:A,$I$3) -> 1 | G4: =IF(F4=0,"Tidak Upload",IF(COUNTIFS('Raw data yang sudah upload'!C:C,C4,'Raw data yang sudah upload'!A:A,$I$3,'Raw data yang sudah upload'!X:X,"YA")>0,"Tepat Waktu","Terlambat")) -> Tepat Waktu
A5: AGENT10 | B5: SKD15 | C5: PASIR_SAKTI | D5: Masih | E5: =IF(F5=0,"Tidak Upload","Sudah Upload") -> Sudah Upload | F5: =COUNTIFS('Raw data yang sudah upload'!C:C,C5,'Raw data yang sudah upload'!A:A,$I$3) -> 1 | G5: =IF(F5=0,"Tidak Upload",IF(COUNTIFS('Raw data yang sudah upload'!C:C,C5,'Raw data yang sudah upload'!A:A,$I$3,'Raw data yang sudah upload'!X:X,"YA")>0,"Tepat Waktu","Terlambat")) -> Tepat Waktu
A6: AGENT10 | B6: KOG20 | C6: PEKON_WONOSOBO | D6: Masih | E6: =IF(F6=0,"Tidak Upload","Sudah Upload") -> Sudah Upload | F6: =COUNTIFS('Raw data yang sudah upload'!C:C,C6,'Raw data yang sudah upload'!A:A,$I$3) -> 1 | G6: =IF(F6=0,"Tidak Upload",IF(COUNTIFS('Raw data yang sudah upload'!C:C,C6,'Raw data yang sudah upload'!A:A,$I$3,'Raw data yang sudah upload'!X:X,"YA")>0,"Tepat Waktu","Terlambat")) -> Tepat Waktu
A7: AGENT10 | B7: KOG15 | C7: PULAU_PANGGUNG | D7: Masih | E7: =IF(F7=0,"Tidak Upload","Sudah Upload") -> Sudah Upload | F7: =COUNTIFS('Raw data yang sudah upload'!C:C,C7,'Raw data yang sudah upload'!A:A,$I$3) -> 1 | G7: =IF(F7=0,"Tidak Upload",IF(COUNTIFS('Raw data yang sudah upload'!C:C,C7,'Raw data yang sudah upload'!A:A,$I$3,'Raw data yang sudah upload'!X:X,"YA")>0,"Tepat Waktu","Terlambat")) -> Tepat Waktu
A8: AGENT10 | B8: GTT07 | C8: WAY_LIMA | D8: Masih | E8: =IF(F8=0,"Tidak Upload","Sudah Upload") -> Sudah Upload | F8: =COUNTIFS('Raw data yang sudah upload'!C:C,C8,'Raw data yang sudah upload'!A:A,$I$3) -> 1 | G8: =IF(F8=0,"Tidak Upload",IF(COUNTIFS('Raw data yang sudah upload'!C:C,C8,'Raw data yang sudah upload'!A:A,$I$3,'Raw data yang sudah upload'!X:X,"YA")>0,"Tepat Waktu","Terlambat")) -> Tepat Waktu
A9: AGENT10 | B9: LWA02A | C9: KEMBAHANG | D9: Masih | E9: =IF(F9=0,"Tidak Upload","Sudah Upload") -> Sudah Upload | F9: =COUNTIFS('Raw data yang sudah upload'!C:C,C9,'Raw data yang sudah upload'!A:A,$I$3) -> 1 | G9: =IF(F9=0,"Tidak Upload",IF(COUNTIFS('Raw data yang sudah upload'!C:C,C9,'Raw data yang sudah upload'!A:A,$I$3,'Raw data yang sudah upload'!X:X,"YA")>0,"Tepat Waktu","Terlambat")) -> Tepat Waktu
A10: AGENT10 | B10: KBB14 | C10: BERNAH | D10: Masih | E10: =IF(F10=0,"Tidak Upload","Sudah Upload") -> Sudah Upload | F10: =COUNTIFS('Raw data yang sudah upload'!C:C,C10,'Raw data yang sudah upload'!A:A,$I$3) -> 1 | G10: =IF(F10=0,"Tidak Upload",IF(COUNTIFS('Raw data yang sudah upload'!C:C,C10,'Raw data yang sudah upload'!A:A,$I$3,'Raw data yang sudah upload'!X:X,"YA")>0,"Tepat Waktu","Terlambat")) -> Tepat Waktu
A11: AGENT10 | B11: KBB05 | C11: ABUNG_SEMULI | D11: Masih | E11: =IF(F11=0,"Tidak Upload","Sudah Upload") -> Sudah Upload | F11: =COUNTIFS('Raw data yang sudah upload'!C:C,C11,'Raw data yang sudah upload'!A:A,$I$3) -> 1 | G11: =IF(F11=0,"Tidak Upload",IF(COUNTIFS('Raw data yang sudah upload'!C:C,C11,'Raw data yang sudah upload'!A:A,$I$3,'Raw data yang sudah upload'!X:X,"YA")>0,"Tepat Waktu","Terlambat")) -> Tepat Waktu
A12: AGENT10 | B12: KBB21 | C12: NEGARA_RATU | D12: Masih | E12: =IF(F12=0,"Tidak Upload","Sudah Upload") -> Sudah Upload | F12: =COUNTIFS('Raw data yang sudah upload'!C:C,C12,'Raw data yang sudah upload'!A:A,$I$3) -> 1 | G12: =IF(F12=0,"Tidak Upload",IF(COUNTIFS('Raw data yang sudah upload'!C:C,C12,'Raw data yang sudah upload'!A:A,$I$3,'Raw data yang sudah upload'!X:X,"YA")>0,"Tepat Waktu","Terlambat")) -> Tepat Waktu
A13: AGENT10 | B13: BKH02C | C13: SIDOASRI | D13: Masih | E13: =IF(F13=0,"Tidak Upload","Sudah Upload") -> Sudah Upload | F13: =COUNTIFS('Raw data yang sudah upload'!C:C,C13,'Raw data yang sudah upload'!A:A,$I$3) -> 1 | G13: =IF(F13=0,"Tidak Upload",IF(COUNTIFS('Raw data yang sudah upload'!C:C,C13,'Raw data yang sudah upload'!A:A,$I$3,'Raw data yang sudah upload'!X:X,"YA")>0,"Tepat Waktu","Terlambat")) -> Tepat Waktu
A14: AGENT12 | B14: BAL01D | C14: GADING_KELAPA_DUA | D14: Tidak | E14: =IF(F14=0,"Tidak Upload","Sudah Upload") -> Tidak Upload | F14: =COUNTIFS('Raw data yang sudah upload'!C:C,C14,'Raw data yang sudah upload'!A:A,$I$3) -> 0 | G14: =IF(F14=0,"Tidak Upload",IF(COUNTIFS('Raw data yang sudah upload'!C:C,C14,'Raw data yang sudah upload'!A:A,$I$3,'Raw data yang sudah upload'!X:X,"YA")>0,"Tepat Waktu","Terlambat")) -> Tidak Upload
A15: AGENT23 | B15: BUO07B | C15: BIAU_01 | D15: Masih | E15: =IF(F15=0,"Tidak Upload","Sudah Upload") -> Sudah Upload | F15: =COUNTIFS('Raw data yang sudah upload'!C:C,C15,'Raw data yang sudah upload'!A:A,$I$3) -> 1 | G15: =IF(F15=0,"Tidak Upload",IF(COUNTIFS('Raw data yang sudah upload'!C:C,C15,'Raw data yang sudah upload'!A:A,$I$3,'Raw data yang sudah upload'!X:X,"YA")>0,"Tepat Waktu","Terlambat")) -> Tepat Waktu
... A3510: AGENT40 | B3510: JKT21U | C3510: DC_GANDARIA | D3510: Masih | E3510: =IF(F3510=0,"Tidak Upload","Sudah Upload") -> Sudah Upload | F3510: =COUNTIFS('Raw data yang sudah upload'!C:C,C3510,'Raw data yang sudah upload'!A:A,$I$3) -> 1 | G3510: =IF(F3510=0,"Tidak Upload",IF(COUNTIFS('Raw data yang sudah upload'!C:C,C3510,'Raw data yang sudah upload'!A:A,$I$3,'Raw data yang sudah upload'!X:X,"YA")>0,"Tepat Waktu","Terlambat")) -> Tepat Waktu
